Workbook
Name HTML_Control: $M$1:$IA$85,$IB$20:$II$45
Name HTML_Control_1: $M$1:$IA$85,$IB$20:$II$45

Sheet LINKS & LOGINS
A1: Link to Resources Login / Password Sheet Excel
A2: https://www.dropbox.com/scl/fi/a0v10irge7xq4d1boezy9/Resources.xlsx?rlkey=oe2go37ptoo553b7cvlujz5wd&st=nxnlaosl&dl=0
A4: WEBSITE | B4: USERNAME | C4: PASSWORD | D4: NOTES
A5: www.zoho.com/creator/ | B5: heilala@sagerealestate.com | C5: Sage9244SCA**** | D5: Job database (needs updating on outdoor resorts) – Slack team when using
A6: www.sagerealestate.com/webmail | B6: Your email | C6: Your password | D6: Web-Based Company Email
A7: www.dropbox.com/sh/zwu20uff9wfwzzk/AAB_BhDHHNKfIl9Wi-LWoXL6a?dl=0 | D7: Dropbox – Archived Jobs Link
A8: www.stdb.com | B8: heilala@sagerealestate.com | C8: 2021Funfun | D8: Demographic reporting (national), alert group on Skype. Select ESRI Tools – Business Analyst, open General Projects, go to “Define Areas” in the maps
A9: www.realtyrates.com | B9: heilala@sagerealestate.com | C9: sh2303 | D9: Investor and financing survey (current copy in Market Data folder on Dropbox)
A10: www.big-rigs-rv.com | B10: heilala@sagerealestate.com | C10: 9244sage | D10: Tracks RV parks that can handle big rigs
A11: www.allstays.com/pro/full/ | B11: sheilala / heilala@sagerealestate.com | C11: 9244Sage**** | D11: Campground / RV park rental listings
A12: www.airdna.co | B12: heilala@sagerealestate.com | C12: 9244Sage** | D12: Short term rental market statistics
A13: www.timeanddate.com/worldclock/distances.html | B13: No login needed | D13: Drive time to major cities
A14: www.rvia.org | B14: heilala@sagerealestate.com | D14: 9244Sage***
A15: www.fema.gov | B15: No login needed | D15: Flood maps (use search function for Map Service Center and search by address)
A16: www.fws.gov/wetlands/data/mapper.html | B16: No login needed | D16: Search by address
A17: www.upwork.com | B17: harsell@sageoutdooradvisory.com | C17: Sageoutdoor2022! | D17: Web scraper project. Contract developers to work on project.
A18: Zoning: Local municipality site or county if unincorporated (Zoning and or Planning department)
A19: Taxes: County Assessor (County GIS for parcel outlines)
A20: Travel and Tourism Statistics (in addition to local tourism organizations):
A21: www.Deanrunyan.com
A22: § www.trade.gov/travel-and-tourism-research
A23: RV Industry Statistics:
A24: https://www.rvia.org/reports-trends
A25: www.koa.com/north-american-camping-report
A26: RV Resort Searches (in addition to Allstays and Google Maps):
A27: www.Goodsam.com
A28: www.Gorving.com
A29: www.Campgrounds.rvlife.com
... A36: www.Thedyrt.com

Sheet CHAT GPT, AI HELP
B2: Hi, You'll also find copy and paste Prompts for AI, ChatGPT, or even Google Search throughout the ALL CAPS REFERENCE TABS here in Excel Templates that contain reference info to use after you perform the setup below.
B4: CHAT GPT / AI SETUP INFO: COPY AND PASTE
B6: CHAT GPT: SAVED MEMORY REPLY AND DOWNLOAD FORMATTING FOR EASY IMPLEMENTATION INTO YOUR REPORTS
B8: HUMAN USER NOTE (Not to paste into ChatGPT): User, for improved AI productivity, turn on ALL your ChatGPT memory functions in your profile Settings > Personalization, including turning on the Reference Chat History memory function, so the AI can learn and remember in all projects, folders, chats, etc. and you save time and effort with less time repeating yourself, less time teaching the AI.
B10: BELOW TO COPY AND PASTE INTO YOUR CHAT GPT ACCOUNT IN A CHAT (*NOTE: be sure you read above and turned on All memory functions)
B12: CHAT GPT / AI PROMPT: DOC / EXCEL CHAT STYLE GUIDE & WRITING STYLE (Have it in Saved Memory of your ChatGPT Account)
B13: Here are a few things to save to your "saved memory" to use across projects, folders, chats, agent mode sessions, etc., in my account.
B15: CITATION: In general, please cite your work, research, analysis, etc. with URLs, sources, and such. When calculating or extrapolating data, please show your work / calculations (whether we're in chat or agent mode, etc.), especially when you have to come up with the answers from the raw data yourself and perform the calculations for a final answer, as opposed to finding already completed data end results, when you're just sharing the information you found. Hopefully that makes sense.
B17: WHERE TO INCLUDE CITATIONS: Please always provide citations, URLs, etc. for where you found the information or data; however, please keep the citation information in the chat here for each applicable reply of yours, and don't include citations in the Word, Excel, images, tables, or other downloads. The exception is if I request the citations in a download, or if you suspect I may want citations in the download, then if you ask if I want the citation in the download before producing the download, and I confirm that I do want the citations in the download then provide them there as well.
B19: WORD DOC FORMATTING: Also, when you provide tables, Excel sheets, or table-like images for me, unless I ask for something otherwise, then please make the table header highlight color as Hex Code #E2EFDA. And if you are providing me information in a Word document, then currently please use Calibri 11 point font with 1.15 line spacing with text justified to fill left and right margins in the Word doc. Also, in these Word docs, please use bold font for headings of sections, bold font for the name of an item in a list or bullets, and the headings of any included tables. If Word tables are included in the document you provide for me to download, then those Word table headers should have the headers highlighted in the same Hex Code #E2EFDA.
B21: EXCEL & TABLE FORMATTING: When you provide an Excel spreadsheet or a table, please also use Calibri font, but this time in 10 point font with the headers highlighted in the same Hex Code #E2EFDA. For Excel, make the column widths set or adjusted so that all text or data is viewable in its cell, row, or column without me altering it afterwards. I would like the formatting in the cells to be for percentages, currency, text, or whichever is appropriate for the date to be formatted to their proper function and type. Left justify text in cells generally and center heading text in cells with the exception of the farthest left column header being left justified. Then center in the cells for numerical data generally.
B23: BULLET LISTS: Some prompts or requests will ask for bullets specifically in the reply you give. Bullets should generally be numbered bullets with the item name in each numbered bullet in bold font, then the other information or description written after the item name should be unbold in the font I've specified.
... B35: WRITING STYLE / VOICE / TONE: The writing style in chat replies, documents, and Excel worksheets / tabs is professional and neutral, suitable for use in investment-grade reports. The AI writing and replies maintain a consistent and organized output format, clearly labeling sections and subsections numerically and in bold as specified or included in this or later updated or provided style guide(s). The AI asks for clarification only when necessary, defaulting to common interpretations when unsure.

Sheet AUTHOR AI REPORT REVIEW
A1: Author's AI Report Review Help | D1: ↓ ADDITIONAL INSTRUCTIONS / STEPS / INFO BELOW ↓ | E1: YOUR PROJECT NOTES (For Sections on Left):
A2: Author's AI Report Review Prompt (Run this prompt prior to submitting the report to the reviewer)
B3: Training Video Link (Date Video Last Updated 0/0/0):
B4: *AUTHOR: USE THE CHATGPT CHAT BOX + SIGN TO SELECT "DEEP RESEARCH" MODE IN CHAT GPT, & THEN USE THE + SIGN TO UPLOAD REPORT PDF IN THE SAME MESSAGE IN THE AI CHAT BOX WITH THE PROMPT BELOW
C5: AI, Please perform a review of this PDF, which is my finished draft of the [TYPE STUDY TYPE: MARKET STUDY, REVENUE PROJECTION, FEASIBILITY STUDY] for the [TYPE PROJECT NAME] that we have been discussing in this project folder. Look for any spelling and / or grammatical errors, inconsistencies throughout, any mismatched or inconsistent same or similar information, any mathematical errors, and issues in the tables and projections where inflation or growth of expenses, revenue, ADR, or occupancy may be incorrect or a bit off. Check the headers to be sure the section name in the header matches the section title in the text portion, check the footers to be sure the pages numbers show and that the graphic bar is the appropriate width for the inside width of the margins of both portrait and landscape oriented pages. Be sure to check every single cell of every table, all narrative writing, bullets, and other charts / graphs / etc. In other words, be sure to check every single part of the document. Let me know if you find any other problematic issues. Please create a list that is easy for a human to view and check off any items you find that need to be addressed, adjusted, corrected, or edited. Identify for each item the PDF page number and also the Sage document page number and paragraph or sentence number or location on the page, table name / location / page, or another way for the User to quickly and easily locate the item to fix. Place your findings into priority groups from Highest to Lowest, and in each group be sure the items to be addressed are listed in order from occurring first in the report order to last by page number.

Sheet GENERAL TRAINING & REFERENCE

Sheet INITIAL REPORT SECTIONS

Sheet EXEC. SUMM. & SWOT

Sheet PROJ. OVERVIEW
A1: PROJECT OVERVIEW (REFERENCE & TRAINING) | D1: ↓ ADDITIONAL INSTRUCTIONS / STEPS / INFO BELOW ↓ | E1: YOUR PROJECT NOTES (For Sections on Left):
A2: Table from Excel ToT (Table of Totals) Intake Form
C3: In Excel Select in the ToT Table from Property down through Additional Development, Improvements, & Amenities, Then In Word place cursor in appropriate location for Table, then Click Word Paste Special, Click Paste Link, Select Microsoft Excel Worksheet Object, Click Ok, Adjust Table size to the page, Save.
A4: Guest Experience Write Up
C5: Utilize the Client Data form / ToT Attractions Info of who will come and why, and other discussion info with client on who they want there clients to be, or make recommendations if they were unsure.
A6: SITE IMPROVEMENTS
B7: Sites / Units Write Up
B9: Building Improvements
B11: Additional Amenities
B13: Add & Cite Images
C14: Client Provided Renderings, Site Visit Images, Site Plan, Aerial Site Google Maps, Etc.
A15: SITE ANALYSIS
B16: Update List of Site Qualities starting with Shape
C17: Add Zoning GIS Map, search for local and county GIS.
B18: Flood Map / Write Up
C19: https://msc.fema.gov/portal/home
B20: Wetlands Map / Write Up
C21: https://fwsprimary.wim.usgs.gov/wetlands/apps/wetlands-mapper/
B22: Wildfire Loss Potential Map / Write Up | D22: Wildfire Map Steps
B23: Use FEMA Wildfire EAL (Expected Annual Loss) Report Info / Map (Link Below) | D23: 1) Click the Link to Left or Paste and Bookmark https://hazards.fema.gov/nri/map 2) In the 2nd link of Dropdown Menus: Click "Expected Annual Loss", then Scroll down and Select Wildfire 3) In the Search Field: Type the City, County, or Address of the Subject - Hit Enter 4) Once the County is Highlighted with Light Blue, then zoom out enough to show all contiguous surrounding counties at minimum 5) Take a Screenshot Selection: Include only the Wildfire EAL Legend and the Counties on screen surrounding the Subject County 6) Save the Screenshot to your Project's Market Research Folder or other appropriate folder 7) Paste the Screenshot Selection of the Legend and Map into your Project Word Doc in the appropriate area
C24: https://hazards.fema.gov/nri/map
C25: NOTE: FEMA defines Wildfire Expected Annual Loss (EAL) as the average yearly loss in dollars and it is calculated by considering exposure (of life and property), annualized frequency (yearly probability of occurrence), and historic loss ratio (expected loss of assets yearly). Factors like vegetation, topography, and population density are considered. The Wildfire EAL map rating is considered "in general, year-round".
B26: Training Video Link (Date Video Last Updated 2/18/25): (Instructions =>)
C27: https://www.loom.com/share/e76c7b187a414cd3b02f070dbed6c92f?sid=50fd5cfd-9772-44ac-bdfb-c5aecbf3016c

Sheet AREA & DEMAND INDICATORS
A1: AREA ANALYSIS (REFERENCE & TRAINING) | D1: ↓ ADDITIONAL INSTRUCTIONS / STEPS / INFO BELOW ↓ | E1: YOUR PROJECT NOTES (For Sections on Left):
A2: Map Creation Training Video (Regional & Local)
B3: Training Video Link (Date Video Last Updated 0/0/0):
A5: Area & Demand Full Write-up Tool (ALL-IN-ONE) for the below AI Prompts for sections possible:
B6: GPT Link for ChatGPT - for All available Area & Demand Write Ups
C7: https://chatgpt.com/g/g-67fb14f8f1908191ad2df2bda899f0d5-area-and-demand-write-up-tool
B8: *OR Separate Prompts for each separate write-up section possible for Area & Demand are below
A10: Write Ups Chat GPT How-To (State, County, Local)
B11: State
B12: Example Chat GPT Summary Prompt Text (Copy & Paste):
C13: Write up a 3 paragraph overview of the state of [TYPE STATE] including geography, economy, population and transportation data.
B14: County
B15: Example Chat GPT Summary Prompt Text (Copy & Paste):
C16: Write up a 3 paragraph overview of the county of [TYPE COUNTY, STATE] including geography, economy, population and transportation data.
B17: Local
B18: Example Chat GPT Summary Prompt Text (Copy & Paste):
C19: Write up a 3 paragraph overview of [TYPE CITY, STATE] including geography, economy, population and transportation data.
A21: DEMAND INDICATORS
A22: Weather | B22: https://weatherspark.com/
B23: Training Video Link (Date Video Last Updated 0/0/0):
A26: Tourism Trends
B27: State
B28: Example Chat GPT Summary Prompt Text (Copy & Paste):
C29: Write up 3 paragraphs on state of [TYPE STATE] tourism development and statistics. Please cite your findings and include any graphic charts, tables, or graphs that also represent the statistics you find.
B30: Local / Area Attractions & Events
B31: Example Chat GPT Summary Prompt Text (Copy & Paste):
C32: WRITE UP: Write up 3 paragraphs on both the city and county of [TYPE CITY, COUNTY in STATE] tourism development and statistics. Please cite your findings and include any graphic charts, tables, or graphs that also represent the statistics you find.
C33: LIST OF ATTRACTIONS & EVENTS: Create separate lists for both the city and county of [TYPE CITY, COUNTY, OR OTHER GEOGRAPHIC AREA, IN STATE] with the lists further separating for each geographic area, the area attractions from the area events which are in or near the city or county. Make these lists exhaustive with any and all possibilities that exist. Please cite your findings.
A35: What's In My Community (STDB) (*Instructions to Right =>) | D35: STDB HOW-TO (Multiple Parts as outlined on left)
B36: Training Video Link (Date Video Last Updated 0/0/0): | D36: STDB = Site to do Business (uses credits for each report / request) STEP 1: Be sure no one else is on STDB... if No one is on, then Post to the whole Team 1st that you're "On STDB" LOGIN as Subscriber to STDB - * Select / Click Business Analyst Button NEXT INITIAL STDB MULTI-PART PROJECT STEPS: Click Maps, Click Define Areas, In the Left Dropdown's Search Bar, Enter Location / Address, or Click the Pin Button by search bar then Select a Location on the Map What's In My Community Infographic Steps 1) Select Drive Time, Type 15, Select Minutes, Click Apply, Click Finish 2) Click Run Infographics, Click Box in menu for What's In My Community? 3) In Right Side Box that populated: Click Run Now - for your preferred location 4) Once Infographic Populates: Export it as an Image (or take screenshot selection of it), Save in your Market Research Folder for the Project 5) Copy and Paste Infographic Image into the appropriate section of your report doc Traffic Count Map Steps 1) Click Maps, On Left Pop-Up Menu Click Back Button/Arrow, Click Rings 2) Type 1, 3, 5, Select Miles, Click Apply, Click Finish 3) In the Pop Up Menu on the Right, Click Run Reports 4) Scroll to and Click Box in the next menu for Traffic Count Map 5) In Right Side Box that populated: Click Run Now - for your preferred location 6) Once processed: Click Download in left side box, then Save the Downloaded Traffic Count Map PDF in your Market Research Folder for the Project 7) Open PDF, Export as an Image, Copy and Paste Image into the appropriate section of your report doc
B37: https://www.stdb.com/
B38: National Parks - NOTE: if park is > 2 hour drive from subject, then could omit that park(s)
B39: Example Chat GPT Summary Prompt Text (Copy & Paste):
C40: Create an exhaustive list of all national parks, monuments, or memorials that are within the state of [TYPE STATE] with some information about them and include both their distance in miles and drive time from [TYPE SUBJECT'S TOWN, GPS COORDINATES, OR ADDRESS]. Prioritize finding ones that are within approximately a 2 hour drive time from the most finite location provided. List them from closest to farthest. Also, if you can access the latest year's number of annual visitors, please provide that too and cite where that information was found for all parks or each park.
B41: State Parks - NOTE: if park is > 90 minutes drive from subject, then could omit that park(s)
B42: Example Chat GPT Summary Prompt Text (Copy & Paste):
C43: Create an exhaustive list of all state parks, state recreation areas, state memorials, or state monuments that are within the state of [TYPE STATE] and are also within approximately 90 minutes or less drive time from [TYPE SUBJECT'S TOWN, GPS COORDINATES, OR ADDRESS]. List them from closest to farthest. Include a short summary about each of them. Include the number of annual visitors for each during [TYPE YEAR], and include both the distance in miles and drive time from [TYPE SUBJECT'S TOWN, GPS COORDINATES, OR ADDRESS] to each park. Please cite where the annual visitor numbers or statistics were found.
B44: Other Special Major Attractions?
A46: Transportation
B48: Highway and Road Access - Traffic Count Map (STDB) (*Instructions to Right =>)
B49: https://www.stdb.com/
B50: Training Video Link (Date Video Last Updated 0/0/0):
A52: Demographic Market Profile (*Instructions to Right =>)
B54: Drive-Time Radius Demographics Map (STDB)
B55: https://www.stdb.com/
B56: Training Video Link (Date Video Last Updated 0/0/0):
B57: One, Two & Three-Hour Drive Time Demographics Table (STDB) | D57: Drive Time Radius Map 60 120 180 Steps 1) Click Maps, On Left Pop-Up Menu Click Back Button/Arrow, Select Drive Time, Type 60 120 180, Select Minutes, Click Apply, Don't click Finish, just take a Screenshot selection of Drive Time Map 2) Save Drive Time Radius Map image in your Market Research Folder for the Project 3) Copy and Paste the Map Image in the appropriate location in your Project Word Doc Drive Time Radius Market Profile Steps 1) Click Reports, Click Market Profile, Select Excel in Right Side Box, Click Run Now in left box for your preferred location, Once processed: Click Download 2) Save Market Profile Report Excel in your Market Research Folder for the Project 3) LOG OFF STDB, Then Post to the whole Team that you are "OFF STDB" 4) Open the Excel File, Copy and Paste the Market Profile Section from the Excel Download into the 60 Min 120 Min 180 Min Sheet / Tab of your Project's Excel Spreadsheet 5) Verify that the Data appears correct in the Market Profile Sheet / Tab of the project Excel 6) If so, then Insert the Market Profile Excel Sheet Table in the appropriate location of your project Word Doc and Save
B58: https://www.stdb.com/
C59: Training Video for Market Profile Excel Sheets / Tabs (Last Updated 0/0/0)
B61: Demand Indicators Guidelines (Summary Bullet Points) #'s / Terms
C62: 3 Hour Drive Radius: *3,000,000 population or more is “very favorable” *2,000,000 population give or take is “favorable” *1,000,000 population give or take is “a neutral demand factor” (unless there is National Park high visitation or other special draw) *Under 1,000,000 population is "not favorable" 2 Hour Drive Radius: *2,000,000 population or more is “very favorable” *1,340,000 population give or take is “favorable” *660,000 population give or take is “a neutral demand factor” (unless there is National Park high visitation or other special draw) *Under 660,000 population is "not favorable" 1 Hour Drive Radius: *1,000,000 population or more is “very favorable” *670,000 population give or take is “favorable” *330,000 population give or take is “a neutral demand factor” (unless there is National Park high visitation or other special draw) *Under 330,000 population is "not favorable"
B63: Most Influential Cities
B64: Example Chat GPT Summary Prompt Text (Copy & Paste):
C65: Write up a one paragraph summary from a non-biased view point about [TYPE CITY, STATE] including population, economy, transportation, and any other information that stands out about the city.
B66: Demand Analysis Conclusion
B67: Training Video Link (Date Video Last Updated 0/0/0):
C69: Key Competitive Advantages for Demand Analysis Conclusion
C70: Example Chat GPT Summary Prompt Text (Copy & Paste):
C71: Summarize in a short paragraph the key competitive advantages for a [TYPE GLAMPING, RV, OR RV & GLAMPING] resort in the area of [TYPE CITY, COUNTY, STATE, REGION, ETC. AS APPROPRIATE].

Sheet Market Profile
AH2: Annual Growth | AI2: Years | AJ2: 5 | AL2: User Can Change
AH3: Projected Growth Years (Population and Household) | AJ3: 5 | AL3: User Can Change
D4: MARKET PROFILE | AH4: Projected Growth Years (Income) | AJ4: 5
A5: Miles or Minutes will pull from the excel | F5: ='60 Min 120 Min 180 Min'!B10 -> 60 minutes | I5: ='60 Min 120 Min 180 Min'!C10 -> 120 minutes | L5: ='60 Min 120 Min 180 Min'!D10 -> 180 minutes | O5: City | R5: County | U5: MSA | X5: USA
D7: Population | AH7: Get Market Profile in Excel (Miles or Drive Time, City, County, MSA) USA Info is Current
D8: 2020 Population | F8: ='60 Min 120 Min 180 Min'!B12 -> 1708977 | I8: ='60 Min 120 Min 180 Min'!C12 -> 5890181 | L8: ='60 Min 120 Min 180 Min'!D12 -> 6396575 | O8: =City!B10 -> 26785 | R8: =County!B10 -> 425264 | U8: =MSA!B10 -> 4845832 | X8: =USA!B10 -> 331449281 | AH8: Go to Cell A1 in the STDB Spreadsheet Download
D9: 2025 Population | F9: ='60 Min 120 Min 180 Min'!B14 -> 1844100 | I9: ='60 Min 120 Min 180 Min'!C14 -> 6290418 | L9: ='60 Min 120 Min 180 Min'!D14 -> 6818085 | O9: =City!B12 -> 28129 | R9: =County!B12 -> 492312 | U9: =MSA!B12 -> 5215050 | X9: =USA!B12 -> 339887819 | AH9: Ctrl A (select all) then Ctrl C (copy)
D10: 2030 Projected Population | F10: ='60 Min 120 Min 180 Min'!B16 -> 1948548 | I10: ='60 Min 120 Min 180 Min'!C16 -> 6584040 | L10: ='60 Min 120 Min 180 Min'!D16 -> 7130239 | O10: =City!B14 -> 30132 | R10: =County!B14 -> 555032 | U10: =MSA!B14 -> 5491123 | X10: =USA!B14 -> 347149422 | AH10: Then go to the appropriate spreadsheet (60 min, 120 min, 180 min, City, County, MSA)
D11: Annual Growth Rate 2010 to 2025 | F11: =(1-(F8/F9))/AJ2 -> 0.014654628 | I11: =(1-(I8/I9))/AJ2 -> 0.012725291 | L11: =(1-(L8/L9))/AJ2 -> 0.012364469 | O11: =(1-(O8/O9))/AJ2 -> 0.0095559743 | R11: =(1-(R8/R9))/AJ2 -> 0.027238012 | U11: =(1-(U8/U9))/AJ2 -> 0.014159711 | X11: =(1-(X8/X9))/AJ2 -> 0.0049654842 | AH11: Go to Cell A1 and hit Paste (Ctrl V)
D12: Projected Annual Growth Rate 2025 to 2030 | F12: =(1-(F9/F10))/AJ3 -> 0.010720598 | I12: =(1-(I9/I10))/AJ3 -> 0.0089192046 | L12: =(1-(L9/L10))/AJ3 -> 0.0087557794 | O12: =(1-(O9/O10))/AJ3 -> 0.013294836 | R12: =(1-(R9/R10))/AJ3 -> 0.022600499 | U12: =(1-(U9/U10))/AJ3 -> 0.010055247 | X12: =(1-(X9/X10))/AJ3 -> 0.0041835605
D13: Households
D14: 2020 Households | F14: ='60 Min 120 Min 180 Min'!B25 -> 625018 | I14: ='60 Min 120 Min 180 Min'!D23 -> 2121584 | L14: ='60 Min 120 Min 180 Min'!D25 -> 2429092 | O14: =City!B23 -> 4866 | R14: =County!B23 -> 146663 | U14: =MSA!B23 -> 1790242 | X14: =USA!B23 -> 126817580
D15: 2025 Households | F15: ='60 Min 120 Min 180 Min'!B27 -> 687370 | I15: ='60 Min 120 Min 180 Min'!D27 -> 2634592 | L15: ='60 Min 120 Min 180 Min'!D27 -> 2634592 | O15: =City!B25 -> 6164 | R15: =County!B25 -> 175296 | U15: =MSA!B25 -> 1959001 | X15: =USA!B25 -> 132422916
D16: 2025 Average Household Size | F16: ='60 Min 120 Min 180 Min'!B28 -> 2.64 | I16: ='60 Min 120 Min 180 Min'!D28 -> 2.54 | L16: ='60 Min 120 Min 180 Min'!D26 -> 2.58 | O16: =City!B26 -> 2.31 | R16: =MSA!C25 -> 0 | U16: =MSA!B26 -> 2.61 | X16: =USA!B26 -> 2.5
D17: 2030 Projected Households | F17: ='60 Min 120 Min 180 Min'!B29 -> 733275 | I17: ='60 Min 120 Min 180 Min'!D29 -> 2785885 | L17: ='60 Min 120 Min 180 Min'!D29 -> 2785885 | O17: =City!B27 -> 7097 | R17: =County!B27 -> 201050 | U17: =MSA!B27 -> 2085679 | X17: =USA!B27 -> 136716884
D18: 2030 Average Household Size | F18: ='60 Min 120 Min 180 Min'!B30 -> 2.61 | I18: ='60 Min 120 Min 180 Min'!D30 -> 2.51 | L18: ='60 Min 120 Min 180 Min'!D30 -> 2.51 | O18: =City!B28 -> 2.29 | R18: =County!B28 -> 2.66 | U18: =MSA!B28 -> 2.59 | X18: =USA!B28 -> 2.48
D19: Annual Growth Rate 2010 to 2025 | F19: =(1-(F14/F15))/AJ2 -> 0.018142194 | I19: =(1-(I14/I15))/AJ2 -> 0.038944019 | L19: =(1-(L14/L15))/AJ2 -> 0.015600138 | O19: =(1-(O14/O15))/AJ2 -> 0.042115509 | R19: =(1-(R14/R15))/AJ2 -> 0.032668173 | U19: =(1-(U14/U15))/AJ2 -> 0.017229088 | X19: =(1-(X14/X15))/AJ2 -> 0.0084658096
D20: Projected Annual Growth Rate 2025 to 2030 | F20: =(1-(F15/F17))/AJ3 -> 0.012520541 | I20: =(1-(I15/I17))/AJ3 -> 0.010861396 | L20: =(1-(L15/L17))/AJ3 -> 0.010861396 | O20: =(1-(O15/O17))/AJ3 -> 0.0262928 | R20: =(1-(R15/R17))/AJ3 -> 0.025619498 | U20: =(1-(U15/U17))/AJ3 -> 0.012147411 | X20: =(1-(X15/X17))/AJ3 -> 0.0062815475
D21: Income
D22: 2025 Median Household Income | F22: ='60 Min 120 Min 180 Min'!B39 -> 97574 | I22: ='60 Min 120 Min 180 Min'!C39 -> 88369 | L22: ='60 Min 120 Min 180 Min'!D39 -> 85928 | O22: =City!B37 -> 76645 | R22: =County!B37 -> 79828 | U22: =MSA!B37 -> 92045 | X22: =USA!B37 -> 81624
D23: 2030 Projected Median Household Income | F23: ='60 Min 120 Min 180 Min'!B40 -> 109859 | I23: ='60 Min 120 Min 180 Min'!C40 -> 102985 | L23: ='60 Min 120 Min 180 Min'!D40 -> 100739 | O23: =City!B38 -> 82271 | R23: =County!B38 -> 88591 | U23: =MSA!B38 -> 105919 | X23: =USA!B38 -> 92476
D24: Projected Annual Growth Rate 2025 to 2030 | F24: =(1-(F22/F23))/AJ4 -> 0.022365032 | I24: =(1-(I22/I23))/AJ4 -> 0.028384716 | L24: =(1-(L22/L23))/AJ4 -> 0.029404699 | O24: =(1-(O22/O23))/AJ4 -> 0.013676751 | R24: =(1-(R22/R23))/AJ4 -> 0.019783048 | U24: =(1-(U22/U23))/AJ4 -> 0.026197377 | X24: =(1-(X22/X23))/AJ4 -> 0.023469873
A25: You Can Hide | D25: 2025 Percentage of Households Earning Over $200,000 | F25: ='60 Min 120 Min 180 Min'!B63+'60 Min 120 Min 180 Min'!B64+'60 Min 120 Min 180 Min'!B65+'60 Min 120 Min 180 Min'!B66+'60 Min 120 Min 180 Min'!B67 -> 0.1609 | I25: ='60 Min 120 Min 180 Min'!C63+'60 Min 120 Min 180 Min'!C64+'60 Min 120 Min 180 Min'!C65+'60 Min 120 Min 180 Min'!C66+'60 Min 120 Min 180 Min'!C67 -> 0.1456 | L25: ='60 Min 120 Min 180 Min'!D63+'60 Min 120 Min 180 Min'!D64+'60 Min 120 Min 180 Min'!D65+'60 Min 120 Min 180 Min'!D66+'60 Min 120 Min 180 Min'!D67 -> 0.1398 | O25: =City!B61+City!B62+City!B63+City!B64+City!B65 -> 0.0911 | R25: =County!B61+County!B62+County!B63+County!B64+County!B65 -> 0.0747 | U25: =MSA!B61+MSA!B62+MSA!B63+MSA!B64+MSA!B65 -> 0.155 | X25: =USA!B61+USA!B62+USA!B63+USA!B64+USA!B65 -> 0.1396
D26: Home Values
D27: 2025 Median Home Value | F27: ='60 Min 120 Min 180 Min'!B76 -> 463802 | I27: ='60 Min 120 Min 180 Min'!C76 -> 448870 | L27: ='60 Min 120 Min 180 Min'!D76 -> 442098 | O27: =City!B74 -> 370831 | R27: =County!B74 -> 380767 | U27: =MSA!B74 -> 472406 | X27: =USA!B74 -> 370578
D28: 2025 Average Home Value | F28: ='60 Min 120 Min 180 Min'!B94 -> 513053 | I28: ='60 Min 120 Min 180 Min'!C94 -> 521774 | L28: ='60 Min 120 Min 180 Min'!D94 -> 512217 | O28: =City!B92 -> 373729 | R28: =County!B92 -> 403103 | U28: =MSA!B92 -> 552860 | X28: =USA!B92 -> 476461
D29: Housing Unit Summary
D30: Owner Occupied Housing Units | F30: ='60 Min 120 Min 180 Min'!B106 -> 0.7284 | I30: ='60 Min 120 Min 180 Min'!C106 -> 0.6746 | L30: ='60 Min 120 Min 180 Min'!D106 -> 0.6821 | O30: =City!B104 -> 0.8616 | R30: =County!B104 -> 0.8342 | U30: =MSA!B104 -> 0.6746 | X30: =USA!B104 -> 0.6423
D31: Renter Occupied Housing Units | F31: ='60 Min 120 Min 180 Min'!B107 -> 0.2716 | I31: ='60 Min 120 Min 180 Min'!C107 -> 0.3254 | L31: ='60 Min 120 Min 180 Min'!D107 -> 0.3179 | O31: =City!B105 -> 0.1384 | R31: =County!B105 -> 0.1658 | U31: =MSA!B105 -> 0.3254 | X31: =USA!B105 -> 0.3577
D32: Vacant Housing Units | F32: ='60 Min 120 Min 180 Min'!B108 -> 0.0984 | I32: ='60 Min 120 Min 180 Min'!C108 -> 0.0916 | L32: ='60 Min 120 Min 180 Min'!D108 -> 0.1014 | O32: =City!B106 -> 0.2205 | R32: =County!B106 -> 0.1411 | U32: =MSA!B106 -> 0.0937 | X32: =USA!B106 -> 0.0979
D33: 2023 Unemployment Rate | F33: =#REF!/100 -> #REF! | I33: =#REF!/100 -> #REF! | L33: =#REF!/100 -> #REF! | O33: =#REF!/100 -> #REF! | R33: =#REF!/100 -> #REF! | U33: =#REF!/100 -> #REF! | X33: =#REF!/100 -> #REF! | AH33: You Can Hide
D34: 2025 Consumer Spending
D35: 2025 Average Household Entertainment / Recreation Spending | F35: ='60 Min 120 Min 180 Min'!B239 -> 4500.88 | I35: ='60 Min 120 Min 180 Min'!C239 -> 4263.24 | L35: ='60 Min 120 Min 180 Min'!D239 -> 4182.35 | O35: =City!B237 -> 3580.16 | R35: =County!B237 -> 3537.64 | U35: =MSA!B237 -> 4403.74 | X35: =USA!B237 -> 4108.79
D36: Spending Potential Index | F36: ='60 Min 120 Min 180 Min'!B240 -> 110 | I36: ='60 Min 120 Min 180 Min'!C240 -> 104 | L36: ='60 Min 120 Min 180 Min'!D240 -> 102 | O36: =City!B238 -> 87 | R36: =County!B244 -> 85 | U36: =MSA!B247 -> 107 | X36: =USA!B238 -> 100
D37: 2025 Average Household Travel Spending | F37: ='60 Min 120 Min 180 Min'!B265 -> 3987.52 | I37: ='60 Min 120 Min 180 Min'!C265 -> 3746.05 | L37: ='60 Min 120 Min 180 Min'!D265 -> 3666.63 | O37: =City!B263 -> 3224.6 | R37: =County!B263 -> 3061 | U37: =MSA!B263 -> 3890.29 | X37: =USA!B263 -> 3608.4
D38: Spending Potential Index | F38: ='60 Min 120 Min 180 Min'!B266 -> 111 | I38: ='60 Min 120 Min 180 Min'!C266 -> 104 | L38: ='60 Min 120 Min 180 Min'!D266 -> 102 | O38: =City!B264 -> 89 | R38: =County!B264 -> 85 | U38: =MSA!B264 -> 108 | X38: =USA!B267 -> 100
D40: Source: Market Profile Derived From ESRI
D41: Data Note: The Spending Potential Index represents the amount spent in the area relative to a national average of 100.

Sheet 60 Min 120 Min 180 Min
A2: Market Profile
A3: Prepared by Esri
A4: 1140 W Butte Ave, Florence, Arizona, 85132 (60 minutes, 120 minutes, 180 minutes)
A5: 1140 W Butte Ave, Florence, Arizona, 85132 (60 minutes), 1140 W Butte Ave, Florence, Arizona, 85132 (120 minutes), 1140 W Butte Ave, Florence, Arizona, 85132 (180 minutes)
A6: Drive time: 60, 120, 180 minute radii
A7: Latitude: 33.03182
A8: Longitude: -111.40332
A10: Population Summary | B10: 60 minutes | C10: 120 minutes | D10: 180 minutes
A11: 2010 Total Population | B11: 1459417 | C11: 5174419 | D11: 5659182
A12: 2020 Total Population | B12: 1708977 | C12: 5890181 | D12: 6396575
A13: 2020 Group Quarters | B13: 33259 | C13: 120391 | D13: 130025
A14: 2025 Total Population | B14: 1844100 | C14: 6290418 | D14: 6818085
A15: 2025 Group Quarters | B15: 32239 | C15: 125337 | D15: 133772
A16: 2030 Total Population | B16: 1948548 | C16: 6584040 | D16: 7130239
A17: 2025-2030 Annual Rate | B17: 0.0111 | C17: 0.0092 | D17: 0.009
A18: 2025 Total Daytime Population | B18: 1701951 | C18: 6233107 | D18: 6749181
A19: Workers | B19: 763295 | C19: 3018959 | D19: 3213087
A20: Residents | B20: 938656 | C20: 3214148 | D20: 3536094
A22: Household Summary
A23: 2010 Total Households | B23: 532077 | C23: 1926443 | D23: 2121584
A24: 2010 Average Household Size | B24: 2.68 | C24: 2.63 | D24: 2.61
A25: 2020 Total Households | B25: 625018 | C25: 2217267 | D25: 2429092
A26: 2020 Average Household Size | B26: 2.68 | C26: 2.6 | D26: 2.58
A27: 2025 Total Households | B27: 687370 | C27: 2410317 | D27: 2634592
A28: 2025 Average Household Size | B28: 2.64 | C28: 2.56 | D28: 2.54
A29: 2030 Total Households | B29: 733275 | C29: 2551646 | D29: 2785885
A30: 2030 Average Household Size | B30: 2.61 | C30: 2.53 | D30: 2.51
A31: 2025-2030 Annual Rate | B31: 0.013 | C31: 0.0115 | D31: 0.0112
A32: 2025 Families | B32: 471113 | C32: 1548506 | D32: 1689128
A33: 2025 Average Family Size | B33: 3.15 | C33: 3.15 | D33: 3.13
A34: 2030 Families | B34: 502258 | C34: 1631981 | D34: 1778102
... A36: 2025-2030 Growth Rate | B36: 0.0129 | C36: 0.0106 | D36: 0.0103
A38: Median Household Income
A39: 2025 | B39: 97574 | C39: 88369 | D39: 85928
A40: 2030 | B40: 109859 | C40: 102985 | D40: 100739
A42: Per Capita Income | B42: 60 minutes | C42: 120 minutes | D42: 180 minutes
A43: 2025 | B43: 47788 | C43: 46730 | D43: 46065
A44: 2030 | B44: 53733 | C44: 53093 | D44: 52335
A46: 2025 Households by Income
A47: Household Income Base | B47: 687343 | C47: 2410216 | D47: 2634477
A48: <$10,000 | B48: 0.0426 | C48: 0.0482 | D48: 0.0495
A49: $10,000-14,999 | B49: 0.0183 | C49: 0.0237 | D49: 0.025
A50: $15,000-19,999 | B50: 0.0167 | C50: 0.0198 | D50: 0.0211
A51: $20,000-24,999 | B51: 0.0191 | C51: 0.0266 | D51: 0.0279
A52: $25,000-29,999 | B52: 0.0216 | C52: 0.0263 | D52: 0.0275
A53: $30,000-34,999 | B53: 0.0245 | C53: 0.0294 | D53: 0.0309
A54: $35,000-39,999 | B54: 0.0265 | C54: 0.0285 | D54: 0.0294
A55: $40,000-44,999 | B55: 0.03 | C55: 0.0349 | D55: 0.0356
A56: $45,000-49,999 | B56: 0.0314 | C56: 0.0333 | D56: 0.0338
A57: $50,000-59,999 | B57: 0.0614 | C57: 0.0647 | D57: 0.0658
A58: $60,000-74,999 | B58: 0.0867 | C58: 0.089 | D58: 0.0901
... A68: Average Household Income | B68: 128003 | C68: 121725 | D68: 119002
A70: 2025 Affordability, Mortgage and Wealth
A71: Housing Affordability Index | B71: 84 | C71: 78 | D71: 77
A72: Percent of Income for Mortgage | B72: 0.298 | C72: 0.318 | D72: 0.322
A73: Wealth Index | B73: 115 | C73: 110 | D73: 109
A75: Median Home Value
A76: 2025 | B76: 463802 | C76: 448870 | D76: 442098
A77: 2030 | B77: 564434 | C77: 554556 | D77: 545988
A79: 2025 Home Value | B79: 60 minutes | C79: 120 minutes | D79: 180 minutes
A80: Total Owner Occupied Housing Units | B80: 500628 | C80: 1625662 | D80: 1796635
A81: <$50,000 | B81: 0.0437 | C81: 0.0393 | D81: 0.0413
A82: $50,000 - $99,999 | B82: 0.0202 | C82: 0.019 | D82: 0.0217
A83: $100,000 - $149,999 | B83: 0.0168 | C83: 0.0202 | D83: 0.0228
A84: $150,000 - $199,999 | B84: 0.0197 | C84: 0.0293 | D84: 0.0325
A85: $200,000 - $249,999 | B85: 0.0271 | C85: 0.0429 | D85: 0.0474
A86: $250,000 - $299,999 | B86: 0.0412 | C86: 0.0529 | D86: 0.0565
A87: $300,000 - $399,999 | B87: 0.1872 | C87: 0.1961 | D87: 0.1935
A88: $400,000 - $499,999 | B88: 0.2258 | C88: 0.2052 | D88: 0.2004
A89: $500,000 - $749,999 | B89: 0.2867 | C89: 0.2466 | D89: 0.2393
A90: $750,000 - $999,999 | B90: 0.0901 | C90: 0.0884 | D90: 0.087
A91: $1,000,000 - $1,499,999 | B91: 0.0277 | C91: 0.0342 | D91: 0.0331
... A94: Average Home Value | B94: 513053 | C94: 521774 | D94: 512217
A96: Housing Unit Summary
A97: 2010 Total Housing Units | B97: 623453 | C97: 2239709 | D97: 2493673
A98: Owner Occupied Housing Units | B98: 0.6955 | C98: 0.6515 | D98: 0.6574
A99: Renter Occupied Housing Units | B99: 0.3045 | C99: 0.3485 | D99: 0.3426
A100: Vacant Housing Units | B100: 0.1466 | C100: 0.1399 | D100: 0.1492
A101: 2020 Housing Units | B101: 699607 | C101: 2455843 | D101: 2722729
A102: Owner Occupied Housing Units | B102: 0.695 | C102: 0.6421 | D102: 0.6496
A103: Renter Occupied Housing Units | B103: 0.305 | C103: 0.3579 | D103: 0.3504
A104: Vacant Housing Units | B104: 0.1065 | C104: 0.0972 | D104: 0.1079
A105: 2025 Housing Units | B105: 762417 | C105: 2653254 | D105: 2931896
A106: Owner Occupied Housing Units | B106: 0.7284 | C106: 0.6746 | D106: 0.6821
A107: Renter Occupied Housing Units | B107: 0.2716 | C107: 0.3254 | D107: 0.3179
A108: Vacant Housing Units | B108: 0.0984 | C108: 0.0916 | D108: 0.1014
... A112: Vacant Housing Units | B112: 0.0989 | C112: 0.09 | D112: 0.0994
A114: 2025 Population by Sex | B114: 60 minutes | C114: 120 minutes | D114: 180 minutes
A115: Males | B115: 922514 | C115: 3137980 | D115: 3399959
A116: Females | B116: 921586 | C116: 3152438 | D116: 3418126
A118: Median Age
A119: 2010 | B119: 35.2 | C119: 35.2 | D119: 35.8
A120: 2020 | B120: 38.4 | C120: 38.1 | D120: 38.8
A121: 2025 | B121: 39.2 | C121: 38.9 | D121: 39.5
A122: 2030 | B122: 40.1 | C122: 39.7 | D122: 40.4
A124: 2025 Population by Age
A125: Total | B125: 1844101 | C125: 6290419 | D125: 6818084
A126: 0 - 4 | B126: 0.0563 | C126: 0.0549 | D126: 0.0542
A127: 5 - 9 | B127: 0.0608 | C127: 0.0579 | D127: 0.0571
A128: 10 - 14 | B128: 0.0654 | C128: 0.0614 | D128: 0.0607
...

Sheet City
A2: Market Profile
A3: Prepared by Esri
A4: Florence Town, AZ (Florence town...)
A5: Florence Town, AZ (0423760)
A6: Geography: Place
A8: Population Summary | B8: Florence town...
A9: 2010 Total Population | B9: 25539
A10: 2020 Total Population | B10: 26785
A11: 2020 Group Quarters | B11: 15355
A12: 2025 Total Population | B12: 28129
A13: 2025 Group Quarters | B13: 13913
A14: 2030 Total Population | B14: 30132
A15: 2025-2030 Annual Rate | B15: 0.0139
A16: 2025 Total Daytime Population | B16: 20632
A17: Workers | B17: 10612
A18: Residents | B18: 10020
A20: Household Summary
A21: 2010 Total Households | B21: 3330
A22: 2010 Average Household Size | B22: 2.35
A23: 2020 Total Households | B23: 4866
A24: 2020 Average Household Size | B24: 2.35
A25: 2025 Total Households | B25: 6164
A26: 2025 Average Household Size | B26: 2.31
A27: 2030 Total Households | B27: 7097
A28: 2030 Average Household Size | B28: 2.29
A29: 2025-2030 Annual Rate | B29: 0.0286
A30: 2025 Families | B30: 4263
A31: 2025 Average Family Size | B31: 2.73
A32: 2030 Families | B32: 4972
... A34: 2025-2030 Growth Rate | B34: 0.0312
A36: Median Household Income
A37: 2025 | B37: 76645
A38: 2030 | B38: 82271
A40: Per Capita Income | B40: Florence town...
A41: 2025 | B41: 24811
A42: 2030 | B42: 28891
A44: 2025 Households by Income
A45: Household Income Base | B45: 6157
A46: <$10,000 | B46: 0.0799
A47: $10,000-14,999 | B47: 0.0151
A48: $15,000-19,999 | B48: 0.025
A49: $20,000-24,999 | B49: 0.0162
A50: $25,000-29,999 | B50: 0.0206
A51: $30,000-34,999 | B51: 0.0252
A52: $35,000-39,999 | B52: 0.0455
A53: $40,000-44,999 | B53: 0.0346
A54: $45,000-49,999 | B54: 0.0473
A55: $50,000-59,999 | B55: 0.0713
A56: $60,000-74,999 | B56: 0.1044
... A66: Average Household Income | B66: 100522
A68: 2025 Affordability, Mortgage and Wealth
A69: Housing Affordability Index | B69: 81
A70: Percent of Income for Mortgage | B70: 0.303
A71: Wealth Index | B71: 108
A73: Median Home Value
A74: 2025 | B74: 370831
A75: 2030 | B75: 468138
A77: 2025 Home Value | B77: Florence town...
A78: Total Owner Occupied Housing Units | B78: 5308
A79: <$50,000 | B79: 0.0458
A80: $50,000 - $99,999 | B80: 0.0433
A81: $100,000 - $149,999 | B81: 0.0396
A82: $150,000 - $199,999 | B82: 0.0518
A83: $200,000 - $249,999 | B83: 0.0418
A84: $250,000 - $299,999 | B84: 0.0544
A85: $300,000 - $399,999 | B85: 0.3152
A86: $400,000 - $499,999 | B86: 0.2419
A87: $500,000 - $749,999 | B87: 0.1494
A88: $750,000 - $999,999 | B88: 0.0079
A89: $1,000,000 - $1,499,999 | B89: 0.0081
... A92: Average Home Value | B92: 373729
A94: Housing Unit Summary
A95: 2010 Total Housing Units | B95: 5232
A96: Owner Occupied Housing Units | B96: 0.7589
A97: Renter Occupied Housing Units | B97: 0.2411
A98: Vacant Housing Units | B98: 0.3635
A99: 2020 Housing Units | B99: 6463
A100: Owner Occupied Housing Units | B100: 0.8309
A101: Renter Occupied Housing Units | B101: 0.1691
A102: Vacant Housing Units | B102: 0.2471
A103: 2025 Housing Units | B103: 7908
A104: Owner Occupied Housing Units | B104: 0.8616
A105: Renter Occupied Housing Units | B105: 0.1384
A106: Vacant Housing Units | B106: 0.2205
... A110: Vacant Housing Units | B110: 0.2011
A112: 2025 Population by Sex | B112: Florence town...
A113: Males | B113: 20422
A114: Females | B114: 7707
A116: Median Age
A117: 2010 | B117: 36.3
A118: 2020 | B118: 41.1
A119: 2025 | B119: 41.6
A120: 2030 | B120: 42
A122: 2025 Population by Age
A123: Total | B123: 28129
A124: 0 - 4 | B124: 0.0242
A125: 5 - 9 | B125: 0.0249
A126: 10 - 14 | B126: 0.0267
A127: 15 - 24 | B127: 0.098
A128: 25 - 34 | B128: 0.198
...

Sheet County
A2: Market Profile
A3: Prepared by Esri
A4: Pinal County, AZ (Pinal County,...)
A5: Pinal County, AZ (04021)
A6: Geography: County
A8: Population Summary | B8: Pinal County,...
A9: 2010 Total Population | B9: 375770
A10: 2020 Total Population | B10: 425264
A11: 2020 Group Quarters | B11: 22770
A12: 2025 Total Population | B12: 492312
A13: 2025 Group Quarters | B13: 20632
A14: 2030 Total Population | B14: 555032
A15: 2025-2030 Annual Rate | B15: 0.0243
A16: 2025 Total Daytime Population | B16: 413892
A17: Workers | B17: 122891
A18: Residents | B18: 291001
A20: Household Summary
A21: 2010 Total Households | B21: 125590
A22: 2010 Average Household Size | B22: 2.78
A23: 2020 Total Households | B23: 146663
A24: 2020 Average Household Size | B24: 2.74
A25: 2025 Total Households | B25: 175296
A26: 2025 Average Household Size | B26: 2.69
A27: 2030 Total Households | B27: 201050
A28: 2030 Average Household Size | B28: 2.66
A29: 2025-2030 Annual Rate | B29: 0.0278
A30: 2025 Families | B30: 126003
A31: 2025 Average Family Size | B31: 3.14
A32: 2030 Families | B32: 143951
... A34: 2025-2030 Growth Rate | B34: 0.027
A36: Median Household Income
A37: 2025 | B37: 79828
A38: 2030 | B38: 88591
A40: Per Capita Income | B40: Pinal County,...
A41: 2025 | B41: 35490
A42: 2030 | B42: 40098
A44: 2025 Households by Income
A45: Household Income Base | B45: 175286
A46: <$10,000 | B46: 0.0588
A47: $10,000-14,999 | B47: 0.0252
A48: $15,000-19,999 | B48: 0.0238
A49: $20,000-24,999 | B49: 0.0174
A50: $25,000-29,999 | B50: 0.0326
A51: $30,000-34,999 | B51: 0.0285
A52: $35,000-39,999 | B52: 0.0317
A53: $40,000-44,999 | B53: 0.0283
A54: $45,000-49,999 | B54: 0.0426
A55: $50,000-59,999 | B55: 0.0752
A56: $60,000-74,999 | B56: 0.0957
... A66: Average Household Income | B66: 99187
A68: 2025 Affordability, Mortgage and Wealth
A69: Housing Affordability Index | B69: 83
A70: Percent of Income for Mortgage | B70: 0.299
A71: Wealth Index | B71: 88
A73: Median Home Value
A74: 2025 | B74: 380767
A75: 2030 | B75: 466030
A77: 2025 Home Value | B77: Pinal County,...
A78: Total Owner Occupied Housing Units | B78: 146226
A79: <$50,000 | B79: 0.057
A80: $50,000 - $99,999 | B80: 0.04
A81: $100,000 - $149,999 | B81: 0.0375
A82: $150,000 - $199,999 | B82: 0.0391
A83: $200,000 - $249,999 | B83: 0.0448
A84: $250,000 - $299,999 | B84: 0.0632
A85: $300,000 - $399,999 | B85: 0.2704
A86: $400,000 - $499,999 | B86: 0.2264
A87: $500,000 - $749,999 | B87: 0.1634
A88: $750,000 - $999,999 | B88: 0.0416
A89: $1,000,000 - $1,499,999 | B89: 0.0112
... A92: Average Home Value | B92: 403103
A94: Housing Unit Summary
A95: 2010 Total Housing Units | B95: 159224
A96: Owner Occupied Housing Units | B96: 0.7614
A97: Renter Occupied Housing Units | B97: 0.2386
A98: Vacant Housing Units | B98: 0.2112
A99: 2020 Housing Units | B99: 172878
A100: Owner Occupied Housing Units | B100: 0.796
A101: Renter Occupied Housing Units | B101: 0.204
A102: Vacant Housing Units | B102: 0.1516
A103: 2025 Housing Units | B103: 204091
A104: Owner Occupied Housing Units | B104: 0.8342
A105: Renter Occupied Housing Units | B105: 0.1658
A106: Vacant Housing Units | B106: 0.1411
... A110: Vacant Housing Units | B110: 0.1325
A112: 2025 Population by Sex | B112: Pinal County,...
A113: Males | B113: 252036
A114: Females | B114: 240276
A116: Median Age
A117: 2010 | B117: 35.3
A118: 2020 | B118: 40.4
A119: 2025 | B119: 40.8
A120: 2030 | B120: 41.6
A122: 2025 Population by Age
A123: Total | B123: 492312
A124: 0 - 4 | B124: 0.0577
A125: 5 - 9 | B125: 0.0603
A126: 10 - 14 | B126: 0.0638
A127: 15 - 24 | B127: 0.122
A128: 25 - 34 | B128: 0.123
...

Sheet MSA
A2: Market Profile
A3: Prepared by Esri
A4: Phoenix-Mesa-Chandler, AZ Metropolitan Statistical Area (Phoenix-Mesa-...)
A5: Phoenix-Mesa-Chandler, AZ Metropolitan Statistical Area (38060)
A6: Geography: CBSA
A8: Population Summary | B8: Phoenix-Mesa-...
A9: 2010 Total Population | B9: 4192887
A10: 2020 Total Population | B10: 4845832
A11: 2020 Group Quarters | B11: 92800
A12: 2025 Total Population | B12: 5215050
A13: 2025 Group Quarters | B13: 98282
A14: 2030 Total Population | B14: 5491123
A15: 2025-2030 Annual Rate | B15: 0.0104
A16: 2025 Total Daytime Population | B16: 5165796
A17: Workers | B17: 2533342
A18: Residents | B18: 2632454
A20: Household Summary
A21: 2010 Total Households | B21: 1537173
A22: 2010 Average Household Size | B22: 2.68
A23: 2020 Total Households | B23: 1790242
A24: 2020 Average Household Size | B24: 2.65
A25: 2025 Total Households | B25: 1959001
A26: 2025 Average Household Size | B26: 2.61
A27: 2030 Total Households | B27: 2085679
A28: 2030 Average Household Size | B28: 2.59
A29: 2025-2030 Annual Rate | B29: 0.0126
A30: 2025 Families | B30: 1280511
A31: 2025 Average Family Size | B31: 3.19
A32: 2030 Families | B32: 1357196
... A34: 2025-2030 Growth Rate | B34: 0.0117
A36: Median Household Income
A37: 2025 | B37: 92045
A38: 2030 | B38: 105919
A40: Per Capita Income | B40: Phoenix-Mesa-...
A41: 2025 | B41: 47465
A42: 2030 | B42: 53778
A44: 2025 Households by Income
A45: Household Income Base | B45: 1958915
A46: <$10,000 | B46: 0.0463
A47: $10,000-14,999 | B47: 0.0215
A48: $15,000-19,999 | B48: 0.0182
A49: $20,000-24,999 | B49: 0.0225
A50: $25,000-29,999 | B50: 0.0233
A51: $30,000-34,999 | B51: 0.0276
A52: $35,000-39,999 | B52: 0.0274
A53: $40,000-44,999 | B53: 0.0335
A54: $45,000-49,999 | B54: 0.0337
A55: $50,000-59,999 | B55: 0.0632
A56: $60,000-74,999 | B56: 0.0882
... A66: Average Household Income | B66: 126118
A68: 2025 Affordability, Mortgage and Wealth
A69: Housing Affordability Index | B69: 78
A70: Percent of Income for Mortgage | B70: 0.321
A71: Wealth Index | B71: 113
A73: Median Home Value
A74: 2025 | B74: 472406
A75: 2030 | B75: 579594
A77: 2025 Home Value | B77: Phoenix-Mesa-...
A78: Total Owner Occupied Housing Units | B78: 1321353
A79: <$50,000 | B79: 0.035
A80: $50,000 - $99,999 | B80: 0.0161
A81: $100,000 - $149,999 | B81: 0.0158
A82: $150,000 - $199,999 | B82: 0.0232
A83: $200,000 - $249,999 | B83: 0.0343
A84: $250,000 - $299,999 | B84: 0.0422
A85: $300,000 - $399,999 | B85: 0.1778
A86: $400,000 - $499,999 | B86: 0.2149
A87: $500,000 - $749,999 | B87: 0.273
A88: $750,000 - $999,999 | B88: 0.0988
A89: $1,000,000 - $1,499,999 | B89: 0.0389
... A92: Average Home Value | B92: 552860
A94: Housing Unit Summary
A95: 2010 Total Housing Units | B95: 1798503
A96: Owner Occupied Housing Units | B96: 0.6544
A97: Renter Occupied Housing Units | B97: 0.3456
A98: Vacant Housing Units | B98: 0.1453
A99: 2020 Housing Units | B99: 1985705
A100: Owner Occupied Housing Units | B100: 0.6439
A101: Renter Occupied Housing Units | B101: 0.3561
A102: Vacant Housing Units | B102: 0.0984
A103: 2025 Housing Units | B103: 2161610
A104: Owner Occupied Housing Units | B104: 0.6746
A105: Renter Occupied Housing Units | B105: 0.3254
A106: Vacant Housing Units | B106: 0.0937
... A110: Vacant Housing Units | B110: 0.0922
A112: 2025 Population by Sex | B112: Phoenix-Mesa-...
A113: Males | B113: 2604258
A114: Females | B114: 2610792
A116: Median Age
A117: 2010 | B117: 34.7
A118: 2020 | B118: 37.5
A119: 2025 | B119: 38.3
A120: 2030 | B120: 39.2
A122: 2025 Population by Age
A123: Total | B123: 5215050
A124: 0 - 4 | B124: 0.0563
A125: 5 - 9 | B125: 0.0593
A126: 10 - 14 | B126: 0.0629
A127: 15 - 24 | B127: 0.136
A128: 25 - 34 | B128: 0.142
...

Sheet USA
A2: Market Profile
A3: Prepared by Esri
A4: United States 12 (United States)
A5: United States (01)
A6: Geography: USA
A8: Population Summary | B8: United States
A9: 2010 Total Population | B9: 308745538
A10: 2020 Total Population | B10: 331449281
A11: 2020 Group Quarters | B11: 8239016
A12: 2025 Total Population | B12: 339887819
A13: 2025 Group Quarters | B13: 8216660
A14: 2030 Total Population | B14: 347149422
A15: 2025-2030 Annual Rate | B15: 0.0042
A16: 2025 Total Daytime Population | B16: 338218372
A17: Workers | B17: 165993009
A18: Residents | B18: 172225363
A20: Household Summary
A21: 2010 Total Households | B21: 116716292
A22: 2010 Average Household Size | B22: 2.58
A23: 2020 Total Households | B23: 126817580
A24: 2020 Average Household Size | B24: 2.55
A25: 2025 Total Households | B25: 132422916
A26: 2025 Average Household Size | B26: 2.5
A27: 2030 Total Households | B27: 136716884
A28: 2030 Average Household Size | B28: 2.48
A29: 2025-2030 Annual Rate | B29: 0.0064
A30: 2025 Families | B30: 84464295
A31: 2025 Average Family Size | B31: 3.13
A32: 2030 Families | B32: 86759582
... A34: 2025-2030 Growth Rate | B34: 0.0054
A36: Median Household Income
A37: 2025 | B37: 81624
A38: 2030 | B38: 92476
A40: Per Capita Income | B40: United States
A41: 2025 | B41: 45360
A42: 2030 | B42: 50744
A44: 2025 Households by Income
A45: Household Income Base | B45: 132419468
A46: <$10,000 | B46: 0.0502
A47: $10,000-14,999 | B47: 0.0327
A48: $15,000-19,999 | B48: 0.0276
A49: $20,000-24,999 | B49: 0.0318
A50: $25,000-29,999 | B50: 0.0293
A51: $30,000-34,999 | B51: 0.0335
A52: $35,000-39,999 | B52: 0.0323
A53: $40,000-44,999 | B53: 0.0346
A54: $45,000-49,999 | B54: 0.0314
A55: $50,000-59,999 | B55: 0.0645
A56: $60,000-74,999 | B56: 0.0918
... A66: Average Household Income | B66: 116179
A68: 2025 Affordability, Mortgage and Wealth
A69: Housing Affordability Index | B69: 79
A70: Percent of Income for Mortgage | B70: 0.284
A71: Wealth Index | B71: 100
A73: Median Home Value
A74: 2025 | B74: 370578
A75: 2030 | B75: 440921
A77: 2025 Home Value | B77: United States
A78: Total Owner Occupied Housing Units | B78: 85033704
A79: <$50,000 | B79: 0.0439
A80: $50,000 - $99,999 | B80: 0.0496
A81: $100,000 - $149,999 | B81: 0.0554
A82: $150,000 - $199,999 | B82: 0.0736
A83: $200,000 - $249,999 | B83: 0.0815
A84: $250,000 - $299,999 | B84: 0.0832
A85: $300,000 - $399,999 | B85: 0.1599
A86: $400,000 - $499,999 | B86: 0.1239
A87: $500,000 - $749,999 | B87: 0.1742
A88: $750,000 - $999,999 | B88: 0.0795
A89: $1,000,000 - $1,499,999 | B89: 0.0412
... A92: Average Home Value | B92: 476461
A94: Housing Unit Summary
A95: 2010 Total Housing Units | B95: 131704730
A96: Owner Occupied Housing Units | B96: 0.651
A97: Renter Occupied Housing Units | B97: 0.349
A98: Vacant Housing Units | B98: 0.1138
A99: 2020 Housing Units | B99: 140498736
A100: Owner Occupied Housing Units | B100: 0.6312
A101: Renter Occupied Housing Units | B101: 0.3688
A102: Vacant Housing Units | B102: 0.0974
A103: 2025 Housing Units | B103: 146800552
A104: Owner Occupied Housing Units | B104: 0.6423
A105: Renter Occupied Housing Units | B105: 0.3577
A106: Vacant Housing Units | B106: 0.0979
... A110: Vacant Housing Units | B110: 0.0973
A112: 2025 Population by Sex | B112: United States
A113: Males | B113: 168818360
A114: Females | B114: 171069459
A116: Median Age
A117: 2010 | B117: 37.1
A118: 2020 | B118: 38.8
A119: 2025 | B119: 39.6
A120: 2030 | B120: 40.5
A122: 2025 Population by Age
A123: Total | B123: 339887819
A124: 0 - 4 | B124: 0.054
A125: 5 - 9 | B125: 0.0575
A126: 10 - 14 | B126: 0.0598
A127: 15 - 24 | B127: 0.132
A128: 25 - 34 | B128: 0.136
...

Sheet State Parks
B3: # | C3: Name | D3: Address | E3: Miles from Subject | F3: 2022-2023 Annual Visitors
B4: 1 | C4: South Cumberland State Park, TN | E4: 28 Miles | F4: 571681
B5: 2 | C5: Cloudland Canyon State Park, GA | E5: 26 Miles | F5: 302309
E7: Total | F7: =SUM(F4:F6) -> 873990
D15: =SUM(I22,J22,K22,S22,T22) -> 0 | H15: Parks | I15: JAN | J15: FEB | K15: MAR | L15: APR | M15: MAY | N15: JUN | O15: JUL | P15: AUG | Q15: SEP | R15: OCT | S15: NOV | T15: DEC | U15: Total
D16: =SUM(L22,M22,Q22,R22) -> 0 | U16: 204424
D17: =SUM(N22:P22) -> 0 | U17: 103213
D18: =SUM(M22:R22) -> 0 | U18: 201331
U19: 131263
U20: 2467245
H21: Sum | I21: =SUM(I16:I20) -> 0 | J21: =SUM(J16:J20) -> 0 | K21: =SUM(K16:K20) -> 0 | L21: =SUM(L16:L20) -> 0 | M21: =SUM(M16:M20) -> 0 | N21: =SUM(N16:N20) -> 0 | O21: =SUM(O16:O20) -> 0 | P21: =SUM(P16:P20) -> 0 | ... U21: =SUM(U16:U20) -> 3107476
H22: % of Total | I22: =I21/$U$21 -> 0 | J22: =J21/$U$21 -> 0 | K22: =K21/$U$21 -> 0 | L22: =L21/$U$21 -> 0 | M22: =M21/$U$21 -> 0 | N22: =N21/$U$21 -> 0 | O22: =O21/$U$21 -> 0 | P22: =P21/$U$21 -> 0 | ... T22: =T21/$U$21 -> 0 | U22: 1
H23: % of July | I23: =I21/$O$21 -> #DIV/0! | J23: =J21/$O$21 -> #DIV/0! | K23: =K21/$O$21 -> #DIV/0! | L23: =L21/$O$21 -> #DIV/0! | M23: =M21/$O$21 -> #DIV/0! | N23: =N21/$O$21 -> #DIV/0! | O23: =O21/$O$21 -> #DIV/0! | P23: =P21/$O$21 -> #DIV/0! | ... T23: =T21/$O$21 -> #DIV/0! | U23: 1

Sheet Nat. Parks
C1: Visitation by park=> | D1: https://irma.nps.gov/STATS/SSRSReports/Park%20Specific%20Reports/Visitation%20by%20Month?Park=MNRR
C2: Map of parks => | D2: https://irma.nps.gov/STATS/
B4: # | C4: Name | D4: Time to Subject | E4: 2022 Annual Visitors
B5: 1 | C5: =G11 -> Indianna Dunes NP | D5: 2 hrs | E5: =T13 -> 2834180
B6: 2 | C6: =G29 -> George Rogers Clark NHP | D6: 2 hrs 45 min | E6: =T31 -> 123229
B7: 3 | C7: =G47 -> Lincoln Boyhood NMEM | D7: 3 hrs | E7: =T49 -> 105819
D9: Total | E9: =SUM(E5:E8) -> 3063228
G11: Indianna Dunes NP
C12: Seasonal Demand | H12: JAN | I12: FEB | J12: MAR | K12: APR | L12: MAY | M12: JUN | N12: JUL | O12: AUG | P12: SEP | Q12: OCT | R12: NOV | S12: DEC | T12: Annual Total | U12: YoY % Change
C13: Low Season (Nov-March) | D13: =SUM(H25,I25,J25,R25,S25) -> 0.19263811 | G13: 2022 | H13: 71633 | I13: 74372 | J13: 127431 | K13: 141437 | L13: 234403 | M13: 438727 | N13: 575495 | O13: 470160 | P13: 271515 | Q13: 232067 | R13: 108278 | S13: 88662 | T13: 2834180 | U13: -0.108
C14: Shoulder Season (Apr, May, Sept, Oct) | D14: =SUM(K25,L25,P25,Q25) -> 0.32390823 | G14: 2021 | H14: 86065 | I14: 93430 | J14: 171050 | K14: 234442 | L14: 396362 | M14: 319611 | N14: 594272 | O14: 437313 | P14: 343696 | Q14: 253640 | R14: 144881 | S14: 102448 | T14: 3177210 | U14: 0.386
C15: Peak Season (June - Aug) | D15: =SUM(M25:O25) -> 0.48345366 | G15: 2020 | H15: 82444 | I15: 87813 | J15: 93273 | K15: 91272 | L15: 154428 | M15: 341505 | N15: 427408 | O15: 389689 | P15: 225594 | Q15: 227773 | R15: 78893 | S15: 93014 | T15: 2293106 | U15: 0.074
C16: May - Oct | D16: =SUM(L25:Q25) -> 0.75352812 | G16: 2019 | H16: 69916 | I16: 85702 | J16: 219070 | K16: 107862 | L16: 142403 | M16: 302203 | N16: 449968 | O16: 290469 | P16: 206226 | Q16: 105984 | R16: 79674 | S16: 74808 | T16: 2134285 | U16: 0.215
G17: 2018 | H17: 70652 | I17: 70450 | J17: 128682 | K17: 93585 | L17: 143790 | M17: 240295 | N17: 421553 | O17: 204010 | P17: 167089 | Q17: 132862 | R17: 52878 | S17: 30233 | T17: 1756079 | U17: -0.186
G18: 2017 | H18: 60576 | I18: 85561 | J18: 90620 | K18: 102570 | L18: 149426 | M18: 247641 | N18: 319946 | O18: 462357 | P18: 405688 | Q18: 82494 | R18: 87193 | S18: 64399 | T18: 2158471 | U18: 0.271
G19: 2016 | H19: 56588 | I19: 73072 | J19: 90653 | K19: 99945 | L19: 175447 | M19: 242632 | N19: 308792 | O19: 219929 | P19: 179245 | Q19: 115180 | R19: 82775 | S19: 53965 | T19: 1698223 | U19: 0.035
G20: 2015 | H20: 55607 | I20: 47594 | J20: 93170 | K20: 93419 | L20: 141525 | M20: 174125 | N20: 362197 | O20: 262479 | P20: 169403 | Q20: 101082 | R20: 75316 | S20: 64278 | T20: 1640195 | U20: 0.056
G21: 2014 | H21: 40701 | I21: 51423 | J21: 85786 | K21: 89324 | L21: 161258 | M21: 215070 | N21: 283291 | O21: 255908 | P21: 144874 | Q21: 102336 | R21: 64236 | S21: 59165 | T21: 1553372 | U21: -0.076
G22: 2013 | H22: 54937 | I22: 47432 | J22: 77032 | K22: 101281 | L22: 144046 | M22: 219493 | N22: 357123 | O22: 304087 | P22: 190536 | Q22: 78671 | R22: 62707 | S22: 44350 | T22: 1681695 | U22: -0.11
G23: 2012 | H23: 58521 | I23: 51948 | J23: 106271 | K23: 73145 | L23: 194496 | M23: 270881 | N23: 361124 | O23: 260821 | P23: 160416 | Q23: 228117 | R23: 67680 | S23: 55961 | T23: 1889381 | U23: 0.027
G24: Average | H24: =AVERAGE(H13:H23) -> 64330.909 | I24: =AVERAGE(I13:I23) -> 69890.636 | J24: =AVERAGE(J13:J23) -> 116639.82 | K24: =AVERAGE(K13:K23) -> 111662 | L24: =AVERAGE(L13:L23) -> 185234.91 | M24: =AVERAGE(M13:M23) -> 273834.82 | N24: =AVERAGE(N13:N23) -> 405560.82 | O24: =AVERAGE(O13:O23) -> 323383.82 | ... S24: =AVERAGE(S13:S23) -> 66480.273 | T24: =SUM(H24:S24) -> 2074199.7 | U24: =AVERAGE(U13:U23) -> 0.053090909
G25: % Total | H25: =H24/$T$24 -> 0.031014809 | I25: =I24/$T$24 -> 0.03369523 | J25: =J24/$T$24 -> 0.056233648 | K25: =K24/$T$24 -> 0.053833774 | L25: =L24/$T$24 -> 0.089304278 | M25: =M24/$T$24 -> 0.1320195 | N25: =N24/$T$24 -> 0.19552641 | O25: =O24/$T$24 -> 0.15590775 | ... S25: =S24/$T$24 -> 0.032051047 | T25: =SUM(H25:S25) -> 1
G26: % July | H26: =H24/$N$24 -> 0.1586221 | I26: =I24/$N$24 -> 0.17233084 | J26: =J24/$N$24 -> 0.2876013 | K26: =K24/$N$24 -> 0.27532739 | L26: =L24/$N$24 -> 0.45673768 | M26: =M24/$N$24 -> 0.67520038 | N26: =N24/$N$24 -> 1 | O26: =O24/$N$24 -> 0.79737441 | ... S26: =S24/$N$24 -> 0.16392183
G29: George Rogers Clark NHP
C30: Seasonal Demand | H30: JAN | I30: FEB | J30: MAR | K30: APR | L30: MAY | M30: JUN | N30: JUL | O30: AUG | P30: SEP | Q30: OCT | R30: NOV | S30: DEC | T30: Annual Total | U30: YoY % Change
C31: Low Season (Nov-March) | D31: =SUM(H43,I43,J43,R43,S43) -> 0.1770633 | G31: 2022 | H31: 2101 | I31: 2439 | J31: 5189 | K31: 8533 | L31: 29727 | M31: 10862 | N31: 25280 | O31: 12347 | P31: 7360 | Q31: 11846 | R31: 4078 | S31: 3467 | T31: 123229 | U31: 0.062
C32: Shoulder Season (Apr, May, Sept, Oct) | D32: =SUM(K43,L43,P43,Q43) -> 0.4615135 | G32: 2021 | H32: 2268 | I32: 2486 | J32: 5534 | K32: 6147 | L32: 26402 | M32: 9019 | N32: 27354 | O32: 12432 | P32: 9305 | Q32: 6750 | R32: 4522 | S32: 3869 | T32: 116088 | U32: 1.069
C33: Peak Season (June - Aug) | D33: =SUM(M43:O43) -> 0.3614232 | G33: 2020 | H33: 2407 | I33: 3139 | J33: 2471 | K33: 3800 | L33: 4100 | M33: 6819 | N33: 6914 | O33: 6549 | P33: 6491 | Q33: 7098 | R33: 4297 | S33: 2023 | T33: 56108 | U33: -0.6
C34: May - Oct | D34: =SUM(L43:Q43) -> 0.7653696 | G34: 2019 | H34: 633 | I34: 2404 | J34: 4104 | K34: 11845 | L34: 36257 | M34: 8702 | N34: 28453 | O34: 15558 | P34: 10039 | Q34: 9856 | R34: 5608 | S34: 6671 | T34: 140130 | U34: 0.156
G35: 2018 | H35: 1844 | I35: 2504 | J35: 4877 | K35: 5832 | L35: 36995 | M35: 7603 | N35: 19710 | O35: 10544 | P35: 12826 | Q35: 4923 | R35: 10144 | S35: 3385 | T35: 121187 | U35: 0.033
G36: 2017 | H36: 2029 | I36: 2771 | J36: 4633 | K36: 6406 | L36: 36198 | M36: 7028 | N36: 22815 | O36: 12948 | P36: 6911 | Q36: 5480 | R36: 6442 | S36: 3607 | T36: 117268 | U36: -0.07
G37: 2016 | H37: 2204 | I37: 2967 | J37: 4805 | K37: 7534 | L37: 37742 | M37: 7440 | N37: 28558 | O37: 10923 | P37: 7678 | Q37: 6783 | R37: 3612 | S37: 5849 | T37: 126095 | U37: -0.072
G38: 2015 | H38: 2162 | I38: 2195 | J38: 4246 | K38: 5920 | L38: 37813 | M38: 7114 | N38: 40128 | O38: 13059 | P38: 8046 | Q38: 5824 | R38: 2916 | S38: 6433 | T38: 135856 | U38: 0.085
G39: 2014 | H39: 1764 | I39: 2608 | J39: 4269 | K39: 6683 | L39: 42414 | M39: 11087 | N39: 23196 | O39: 11079 | P39: 9450 | Q39: 5688 | R39: 2954 | S39: 4026 | T39: 125218 | U39: -0.026
G40: 2013 | H40: 2398 | I40: 2808 | J40: 4640 | K40: 6989 | L40: 41436 | M40: 6803 | N40: 23704 | O40: 6257 | P40: 9639 | Q40: 3148 | R40: 13360 | S40: 7349 | T40: 128531 | U40: 0.02
G41: 2012 | H41: 2243 | I41: 2863 | J41: 4493 | K41: 6051 | L41: 32387 | M41: 9683 | N41: 18486 | O41: 7064 | P41: 7640 | Q41: 7213 | R41: 25399 | S41: 2450 | T41: 125972 | U41: -0.135
G42: Average | H42: =AVERAGE(H31:H41) -> 2004.8182 | I42: =AVERAGE(I31:I41) -> 2653.0909 | J42: =AVERAGE(J31:J41) -> 4478.2727 | K42: =AVERAGE(K31:K41) -> 6885.4545 | L42: =AVERAGE(L31:L41) -> 32861 | M42: =AVERAGE(M31:M41) -> 8378.1818 | N42: =AVERAGE(N31:N41) -> 24054.364 | O42: =AVERAGE(O31:O41) -> 10796.364 | ... S42: =AVERAGE(S31:S41) -> 4466.2727 | T42: =SUM(H42:S42) -> 119607.45 | U42: =AVERAGE(U31:U41) -> 0.047454545
G43: % Total | H43: =H42/$T$42 -> 0.016761649 | I43: =I42/$T$42 -> 0.022181652 | J43: =J42/$T$42 -> 0.037441418 | K43: =K42/$T$42 -> 0.057567102 | L43: =L42/$T$42 -> 0.2747404 | M43: =M42/$T$42 -> 0.070047321 | N43: =N42/$T$42 -> 0.20111091 | O43: =O42/$T$42 -> 0.090264973 | ... T43: =T42/$T$42 -> 1
G44: % July | H44: =H42/$N$42 -> 0.083345301 | I44: =I42/$N$42 -> 0.11029562 | J44: =J42/$N$42 -> 0.18617299 | K44: =K42/$N$42 -> 0.28624555 | L44: =L42/$N$42 -> 1.3661139 | M44: =M42/$N$42 -> 0.34830195 | N44: =N42/$N$42 -> 1 | O44: =O42/$N$42 -> 0.44883181 | ... S44: =S42/$N$42 -> 0.18567412 | T44: 1
G47: Lincoln Boyhood NMEM
C48: Seasonal Demand | H48: JAN | I48: FEB | J48: MAR | K48: APR | L48: MAY | M48: JUN | N48: JUL | O48: AUG | P48: SEP | Q48: OCT | R48: NOV | S48: DEC | T48: Annual Total | U48: YoY % Change
C49: Low Season (Nov-March) | D49: =SUM(H61,I61,J61,R61,S61) -> 0.090820739 | G49: 2022 | H49: 1248 | I49: 1418 | J49: 2330 | K49: 4651 | L49: 7243 | M49: 23648 | N49: 41882 | O49: 3834 | P49: 10819 | Q49: 2670 | R49: 4374 | S49: 1702 | T49: 105819 | U49: -0.075
C50: Shoulder Season (Apr, May, Sept, Oct) | D50: =SUM(K61,L61,P61,Q61) -> 0.27340207 | G50: 2021 | H50: 103 | I50: 528 | J50: 1249 | K50: 1708 | L50: 5070 | M50: 26450 | N50: 55524 | O50: 5885 | P50: 11052 | Q50: 2387 | R50: 2681 | S50: 1716 | T50: 114353 | U50: 0.033
C51: Peak Season (June - Aug) | D51: =SUM(M61:O61) -> 0.63577719 | G51: 2020 | H51: 115 | I51: 1479 | J51: 4936 | K51: 1676 | L51: 3828 | M51: 24871 | N51: 47775 | O51: 6804 | P51: 14174 | Q51: 2028 | R51: 1546 | S51: 1460 | T51: 110692 | U51: -0.202
C52: May - Oct | D52: =SUM(L61:Q61) -> 0.86088343 | G52: 2019 | H52: 37 | I52: 1123 | J52: 2383 | K52: 4782 | L52: 11453 | M52: 28179 | N52: 60560 | O52: 7913 | P52: 18719 | Q52: 1724 | R52: 1492 | S52: 349 | T52: 138714 | U52: 0.036
G53: 2018 | H53: 1259 | I53: 892 | J53: 1553 | K53: 3795 | L53: 13059 | M53: 26014 | N53: 55178 | O53: 6035 | P53: 15953 | Q53: 2374 | R53: 6731 | S53: 1007 | T53: 133850 | U53: -0.068
G54: 2017 | H54: 1733 | I54: 1847 | J54: 1463 | K54: 6531 | L54: 12956 | M54: 26430 | N54: 53579 | O54: 12285 | P54: 15251 | Q54: 1919 | R54: 7768 | S54: 1889 | T54: 143651 | U54: 0.144
G55: 2016 | H55: 1234 | I55: 1757 | J55: 1642 | K55: 6869 | L55: 12873 | M55: 26589 | N55: 42612 | O55: 7460 | P55: 15287 | Q55: 1868 | R55: 5695 | S55: 1676 | T55: 125562 | U55: 0.124
G56: 2015 | H56: 1964 | I56: 1154 | J56: 1187 | K56: 6332 | L56: 11506 | M56: 22415 | N56: 35631 | O56: 8344 | P56: 14096 | Q56: 1660 | R56: 5759 | S56: 1663 | T56: 111711 | U56: 0.119
G57: 2014 | H57: 757 | I57: 1063 | J57: 611 | K57: 6565 | L57: 12079 | M57: 21928 | N57: 27986 | O57: 8580 | P57: 13716 | Q57: 977 | R57: 4742 | S57: 791 | T57: 99795 | U57: -0.202
G58: 2013 | H58: 3049 | I58: 1342 | J58: 815 | K58: 10877 | L58: 11594 | M58: 31173 | N58: 29994 | O58: 9014 | P58: 15928 | Q58: 1326 | R58: 9634 | S58: 323 | T58: 125069 | U58: -0.064
G59: 2012 | H59: 3893 | I59: 875 | J59: 2452 | K59: 11064 | L59: 14987 | M59: 30711 | N59: 27968 | O59: 10449 | P59: 18237 | Q59: 3452 | R59: 8228 | S59: 1234 | T59: 133550 | U59: 0.232
G60: Average | H60: =AVERAGE(H49:H59) -> 1399.2727 | I60: =AVERAGE(I49:I59) -> 1225.2727 | J60: =AVERAGE(J49:J59) -> 1874.6364 | K60: =AVERAGE(K49:K59) -> 5895.4545 | L60: =AVERAGE(L49:L59) -> 10604.364 | M60: =AVERAGE(M49:M59) -> 26218.909 | N60: =AVERAGE(N49:N59) -> 43517.182 | O60: =AVERAGE(O49:O59) -> 7873 | ... S60: =AVERAGE(S49:S59) -> 1255.4545 | T60: =SUM(H60:S60) -> 122069.64 | U60: =AVERAGE(U49:U59) -> 0.007
G61: % Total | H61: =H60/$T$60 -> 0.011462906 | I61: =I60/$T$60 -> 0.01003749 | J61: =J60/$T$60 -> 0.015357106 | K61: =K60/$T$60 -> 0.048295831 | L61: =L60/$T$60 -> 0.086871428 | M61: =M60/$T$60 -> 0.21478649 | N61: =N60/$T$60 -> 0.35649473 | O61: =O60/$T$60 -> 0.064495973 | ... S61: =S60/$T$60 -> 0.010284741 | T61: 1
G62: % July | H62: =H60/$N$60 -> 0.032154489 | I62: =I60/$N$60 -> 0.028156068 | J62: =J60/$N$60 -> 0.043078074 | K62: =K60/$N$60 -> 0.13547418 | L62: =L60/$N$60 -> 0.24368222 | M62: =M60/$N$60 -> 0.60249557 | N62: =N60/$N$60 -> 1 | O62: =O60/$N$60 -> 0.18091705 | ... S62: =S60/$N$60 -> 0.028849629 | T62: 1

Sheet Sheet1

Sheet SUPPLY & COMPS
A1: SUPPLY & COMPETITION ANALYSIS (REFERENCE & TRAINING) | D1: ↓ ADDITIONAL INSTRUCTIONS / STEPS / INFO BELOW ↓ | E1: YOUR PROJECT NOTES (For Sections on Left):
A2: Glamping Unit or RV Site Analysis (Database Excel Pivot Tables and Write Ups)
B3: Sage Database Search: Training Video Link (Date Video Last Updated 0/0/0):
B4: Excel Pivot Tables: Training Video Link (Date Video Last Updated 7/11/23):
C5: https://www.dropbox.com/scl/fi/jzncpyhi34ryci25nj897/Database-Training-Pivot-Tables?rlkey=pvaid9z7esq8b4fshf4hz0vcw&st=g74he5jc&dl=0
A7: Emerging Competitors
B8: EMERG. COMP. Call & Info Notes Template / Questions Example (@ End of this Column)
B9: Example Chat GPT Search and Summary Prompt (Copy & Paste):
C10: Perform an exhaustive search for and then list any campgrounds, rv parks, rv resorts, landscape hotels, landscape resorts, or glamping resorts which are new, under contruction, expanding, or in the approval or permitting process in [PROJECT STATE(S), REGION, OR COUNTY & STATE] during the past 2 years. Please cite where any information was located.
A12: Area Competitors
B13: Selecting Area Competitors: Training Video Link (Date Video Last Updated 0/0/0):
B14: Example Chat GPT Search and Summary Prompt (Copy & Paste):
C15: Perform an exhaustive search for and then create numbered and bulletized lists of each by the following types of any campgrounds, RV parks, RV resorts, landscape hotels, landscape resorts, or glamping resorts which are within [TYPE DRIVE TIME] of [TYPE PROJECT STATE(S), REGION, OR COUNTY & STATE]. Please include any data available about each business's number of lodging units or RV sites, types of units, price ranges, and a brief description of the resort. In the bullets for each property please separate the number of RV sites, lodging, units, or glamping units by their type, such as by cabins, domes, RV sites, casitas, safari tents, etc. along with any other availale information for that unit type or site. Please cite where any information was located.
A17: COMPARABLES
B18: Selecting Best Comparables: Training Video Link (Date Video Last Updated 0/0/0):
B20: BEST COMP TABLES / Write-ups / Info
B21: (*This is a start point Only: verify, FACT CHECK IT, edit, add, remove, research further, etc.)
B22: RV Sites & amenities AI prompt
C23: Create a sentence and list (separating by commas) for [TYPE RESORT NAME, ADDRESS, CITY, STATE] the total number of RV sites, number of back-in and pull-thru RV sites, RV hook-ups available (20/30/50 amp electricity, water, sewer), RV site surface paved/gravel/etc., and list RV site amenities (picnic table/seating, fire pit, etc.), Wi-Fi, and average RV site dimensions (such as 40' x 70').
B25: Units & unit amenities AI prompt
C26: Create a sentence and list (separating by commas) for [TYPE RESORT NAME, ADDRESS, CITY, STATE] the total number of lodging units, type of units with number of rooms/bedrooms and quanitity of each unit type, in-unit amenities (private bathroom or shared bathhouse, full kitchen or kitchenette, bed sizes/types, loft), parking at unit or walking distance, and list at-unit amenities (picnic table/seating, fire pit, etc.), Wi-Fi, TV, and any available average information on size, number of guests the unit sleeps, and/or number of bedrooms for that unit type (such as sleeps 4 guests, 400 SF, or 2 bedroom).
B28: Property AI prompt
C29: Create a sentence and list (separating by commas) for [TYPE RESORT NAME, ADDRESS, CITY, STATE] the property characteristics to include number of acres, terrain (flat vs. hilly), mature trees or not, wooded or field, any ponds/lake/creek/river, walking trails, modern or classic style, paved/gravel/dirt roads, walkway surface type, quality overall and how well maintained if known, new or old build, etc.
B31: Resort amenities AI prompt
C32: Create a sentence and list (separating by commas) for [TYPE RESORT NAME, ADDRESS, CITY, STATE] the property/resort amenities that are for communal use. For example: 10,600-square-foot clubhouse with spa and fitness amenities, covered porte-cochère, wash stations, shared restrooms and shower facilities, picnic pavilions, an off-leash dog park, playgrounds, fire pits, a one-mile interpretive trail, pickleball courts, and landscaped recreation areas.
B34: Location AI prompt
C35: Write a very brief paragraph / sentence(s) listing with commas, for [TYPE RESORT NAME, ADDRESS, CITY, STATE] about its location as it relates to the setting (remote, rural, urban), road access, and driving times in minutes to the nearest city/town/census-designated place, nearest large city, nearest international airport, nearest full grocery store, nearest gas station, restaurants, bars, coffee shops, unique shopping, and important attractions of any sort that would draw guests to this type of resort (especially outdoor focused attractions, such as lakes, national or state parks, a ski area, etc.).
B37: Brand strength AI prompt
C38: Write a very brief paragraph / sentence(s) listing with commas, for [TYPE RESORT NAME, ADDRESS, CITY, STATE] the information that helps represent the business's brand strength, including ratings as applicable for Good Sam: (the 3 rated areas out of 10 each i.e., 10/10/10), Tripadvisor ratings (number score/stars out of 5, and total number of reviews/ratings, i.e. 4.5 of 342 reviews), Google ratings/reviews: (number score/stars out of 5, and total number of reviews/ratings, , i.e. 4.5 of 342 reviews), quality of website/photography/videos/booking platform, any major affiliated/parent company brand, awards won, and whether they are new or established, etc.
B40: Occupancy (look at their booking platform and call the resort to interview staff)
A43: Overview
B44: *Select photos / maps / diagrams for each "best comp" similar to Word template examples
A46: Best Comparables Information / Descriptions (Table In "Best Comps" Excel Sheet)
B47: Comparables Descriptions How-To: Training Video Link (Date Video Last Updated 0/0/0):
B48: *Guidance/How-To/?'s is in the "Best Comps" Excel Sheet next to the table sections
B49: Best Comps Occupancy Info & % Reference Sheet Based on Call Convo
B50: Call & Info Link to Sample How-To Sheet Link
B52: *Make Notes: Template for Occupancy Calls to Properties in "Best Comps" Excel Sheet/Tab
A54: Subject Quality Score Excel Table (Table In "Best Comps" Excel Sheet)
B55: Subject Quality Score How-To: Training Video Link (Date Video Last Updated 0/0/0):
A57: Summary
B58: Table of All of the Best Comparables Quality Scores (In "All Comps" Excel Sheet)
B59: *Guidance is in the "All Comps" Sheet next to the table sections
B60: Table of All of the Best Comparables Rates & Occupancies (In "All Comps" Excel Sheet)
B61: *Guidance is in the "All Comps" Sheet next to the table sections
B62: Summary Write Up for All Best Comparables
B63: Summary Write Up How-To: Training Video Link (Date Video Last Updated 0/0/0):
B64: Example Chat GPT Summary Prompt Using Rates & Occupancy Table (Copy & Paste): " "
A67: EMERGING COMPETITORS INTERNAL NOTES: | D67: EMERGING COMPETITORS TEMPLATES, SAMPLE ?'s, INTRO
A69: 1. (Add Name & Location of Agency Contacted Here): | D69: EMERGING COMPETITORS - TEMPLATE & SAMPLE INTRO / QUESTIONS: CALL INTRO (OR MESSAGE) EXAMPLE: “Hi [THEIR NAME], this is [YOUR NAME] and I’m performing a study in the area and had a couple questions I hoped to ask. [Allow Them To Reply] Great! Are there any (campgrounds, glamping resorts Or RV parks/resorts) in any phases of planning, permitting, special permits/zoning changes, or that are approved, under contruction, or more recently opened?” (NOTES & FINDINGS IN LEFT BOX) (INCLUDE - Your Notes: about reaching them/voicemails, emails, texts sent & when) EMERGING COMPETITOR QUESTIONS • HOW MANY - emerging competitors in this county / city / town? • WHAT TYPE - of competitors (RV, glamping, combination of both)? • WHAT STAGE IN THE PROCESS – planning, approved, requesting zoning changes/permits, under construction, opened in the last year or so? • NOTES FOR THE ABOVE PLUS OTHER INFO IN LEFT BOX - Any other details gleaned or shared? (All This Information Noted - Can help you, your project manager, or other authors)
A93: 2. (Add Name & Location of Agency Contacted Here): | D93: EMERGING COMPETITORS - TEMPLATE & SAMPLE INTRO / QUESTIONS: CALL INTRO (OR MESSAGE) EXAMPLE: “Hi [THEIR NAME], this is [YOUR NAME] and I’m performing a study in the area and had a couple questions I hoped to ask. [Allow Them To Reply] Great! Are there any (campgrounds, glamping resorts Or RV parks/resorts) in any phases of planning, permitting, special permits/zoning changes, or that are approved, under contruction, or more recently opened?” (NOTES & FINDINGS IN LEFT BOX) (INCLUDE - Your Notes: about reaching them/voicemails, emails, texts sent & when) EMERGING COMPETITOR QUESTIONS • HOW MANY - emerging competitors in this county / city / town? • WHAT TYPE - of competitors (RV, glamping, combination of both)? • WHAT STAGE IN THE PROCESS – planning, approved, requesting zoning changes/permits, under construction, opened in the last year or so? • NOTES FOR THE ABOVE PLUS OTHER INFO IN LEFT BOX - Any other details gleaned or shared? (All This Information Noted - Can help you, your project manager, or other authors)
A117: 3. (Add Name & Location of Agency Contacted Here): | D117: EMERGING COMPETITORS - TEMPLATE & SAMPLE INTRO / QUESTIONS: CALL INTRO (OR MESSAGE) EXAMPLE: “Hi [THEIR NAME], this is [YOUR NAME] and I’m performing a study in the area and had a couple questions I hoped to ask. [Allow Them To Reply] Great! Are there any (campgrounds, glamping resorts Or RV parks/resorts) in any phases of planning, permitting, special permits/zoning changes, or that are approved, under contruction, or more recently opened?” (NOTES & FINDINGS IN LEFT BOX) (INCLUDE - Your Notes: about reaching them/voicemails, emails, texts sent & when) EMERGING COMPETITOR QUESTIONS • HOW MANY - emerging competitors in this county / city / town? • WHAT TYPE - of competitors (RV, glamping, combination of both)? • WHAT STAGE IN THE PROCESS – planning, approved, requesting zoning changes/permits, under construction, opened in the last year or so? • NOTES FOR THE ABOVE PLUS OTHER INFO IN LEFT BOX - Any other details gleaned or shared? (All This Information Noted - Can help you, your project manager, or other authors)
A141: 4. (Add Name & Location of Agency Contacted Here): | D141: EMERGING COMPETITORS - TEMPLATE & SAMPLE INTRO / QUESTIONS: CALL INTRO (OR MESSAGE) EXAMPLE: “Hi [THEIR NAME], this is [YOUR NAME] and I’m performing a study in the area and had a couple questions I hoped to ask. [Allow Them To Reply] Great! Are there any (campgrounds, glamping resorts Or RV parks/resorts) in any phases of planning, permitting, special permits/zoning changes, or that are approved, under contruction, or more recently opened?” (NOTES & FINDINGS IN LEFT BOX) (INCLUDE - Your Notes: about reaching them/voicemails, emails, texts sent & when) EMERGING COMPETITOR QUESTIONS • HOW MANY - emerging competitors in this county / city / town? • WHAT TYPE - of competitors (RV, glamping, combination of both)? • WHAT STAGE IN THE PROCESS – planning, approved, requesting zoning changes/permits, under construction, opened in the last year or so? • NOTES FOR THE ABOVE PLUS OTHER INFO IN LEFT BOX - Any other details gleaned or shared? (All This Information Noted - Can help you, your project manager, or other authors)

Sheet Unit Type #1 Data
A1: Avg. Rate (Next 12 Months) | B1: (Multiple Items)
A2: Avg. Retail Daily Rate 2024 | B2: (Multiple Items)
A3: Toilet | B3: Yes
A4: Shower | B4: Yes
A5: Cooking equipment | B5: Yes
A6: Occupancy rate 2024 | B6: (Multiple Items)
A8: Location | B8: Average Retail Daily Rate 2024 | C8: Average Rate (Next 12 Months) | D8: Average of Low Rate (Next 12 Months) | E8: Average of High Rate (Next 12 Months) | F8: Average of Occupancy rate 2024
A9: Minnesota | B9: 210.27778 | C9: 229.16667 | D9: 218.66667 | E9: 240.88889 | F9: 0.63222222
A10: Braham | B10: 100 | C10: 100 | D10: 100 | E10: 100 | F10: 0.13
A11: Deerwood | B11: 323 | C11: 358 | D11: 336 | E11: 378 | F11: 0.28
A12: Duluth | B12: 132 | C12: 110 | D12: 100 | E12: 130 | F12: 0.21
A13: Fergus Falls | B13: 266 | C13: 295.8 | D13: 277 | E13: 313.4 | F13: 0.926
A14: Hinckley | B14: 268 | C14: 295 | D14: 292.5 | E14: 297.5 | F14: 0.5825
A15: Ogema | B15: 195 | C15: 215 | D15: 194 | E15: 244 | F15: 0.59
A16: Outing | B16: 118 | C16: 152 | D16: 152 | E16: 152 | F16: 0.93
A17: Pine City | B17: 113.66667 | C17: 114 | D17: 105 | E17: 127 | F17: 0.63333333
A18: Winona | B18: 174 | C18: 189 | D18: 184 | E18: 194 | F18: 0.38
A19: Wisconsin | B19: 222.5 | C19: 228.25 | D19: 224.41667 | E19: 231.83333 | F19: 0.59166667
A20: Black River Falls | B20: 311 | C20: 337 | D20: 304 | E20: 367 | F20: 0.69
... A31: Grand Total | B31: 215.16667 | C31: 228.8 | D31: 220.96667 | E31: 237.26667 | F31: 0.616

Sheet Unit Type #2 Data
A1: Avg. Retail Daily Rate 2024 | B1: (Multiple Items)
A2: Occupancy rate 2024 | B2: (Multiple Items)
A3: Toilet | B3: Yes
A4: Shower | B4: (Multiple Items)
A5: Cooking equipment | B5: (Multiple Items)
A7: Location | B7: Average Retail Daily Rate 2024 | C7: Average Rate (Next 12 Months) | D7: Average of Low Rate (Next 12 Months) | E7: Average of High Rate (Next 12 Months) | F7: Average of Occupancy rate 2024
A8: Alabama | B8: 181 | C8: 103 | D8: 92 | E8: 131 | F8: 0.95
A9: Arizona | B9: 135.66667 | C9: 138.33333 | D9: 133 | E9: 143.66667 | F9: 0.51333333
A10: California | B10: 269.15789 | C10: 296.73684 | D10: 277.73684 | E10: 314.94737 | F10: 0.57263158
A11: Colorado | B11: 119 | C11: 119 | D11: 119 | E11: 120 | F11: 0.8
A12: Georgia | B12: 379 | C12: 379 | D12: 379 | E12: 379 | F12: 0.89
A13: Hawaii | B13: 248.5 | C13: 215.5 | D13: 214.5 | E13: 217 | F13: 0.515
A14: Iowa | B14: 101 | C14: 107 | D14: 101 | E14: 113 | F14: 0.54
A15: Maine | B15: 120 | C15: 195 | D15: 162 | E15: 236 | F15: 0.875
A16: Michigan | B16: 145 | C16: 141 | D16: 136 | E16: 145 | F16: 0.77
A17: New Hampshire | B17: 171 | C17: 178 | D17: 167 | E17: 188 | F17: 0.68
A18: New Mexico | B18: 214.4 | C18: 223.8 | D18: 214.2 | E18: 233 | F18: 0.578
A19: New York | B19: 292.5 | C19: 317 | D19: 293.5 | E19: 338 | F19: 0.195
... A26: Grand Total | B26: 232.18182 | C26: 242.28788 | D26: 227.43939 | E26: 257.10606 | F26: 0.56833333

Sheet Unit Type #3 Data
A1: Avg. Retail Daily Rate 2024 | B1: (Multiple Items)
A2: Occupancy rate 2024 | B2: (Multiple Items)
A3: Toilet | B3: Yes
A4: Shower | B4: (Multiple Items)
A5: Cooking equipment | B5: (Multiple Items)
A7: Location | B7: Average Retail Daily Rate 2024 | C7: Average Rate (Next 12 Months) | D7: Average of Low Rate (Next 12 Months) | E7: Average of High Rate (Next 12 Months) | F7: Average of Occupancy rate 2024
A8: Alabama | B8: 151 | C8: 149 | D8: 144.5 | E8: 153 | F8: 0.25
A9: Arkansas | B9: 145 | C9: 152 | D9: 147 | E9: 156 | F9: 0.51
A10: California | B10: 162 | C10: 188.66667 | D10: 178.66667 | E10: 198 | F10: 0.58666667
A11: Florida | B11: 215 | C11: 210 | D11: 210 | E11: 210 | F11: 0.99
A12: Georgia | B12: 234.5 | C12: 262 | D12: 251.5 | E12: 271.75 | F12: 0.495
A13: Hawaii | B13: 207.5 | C13: 207.5 | D13: 207.5 | E13: 207.5 | F13: 0.855
A14: Idaho | B14: 202.66667 | C14: 260 | D14: 248.33333 | E14: 270.33333 | F14: 0.69
A15: Indiana | B15: 198 | C15: 213 | D15: 196 | E15: 228 | F15: 0.67
A16: Kentucky | B16: 262.33333 | C16: 265.33333 | D16: 260.33333 | E16: 269.66667 | F16: 0.52666667
A17: Maine | B17: 137 | C17: 130 | D17: 130 | E17: 130 | F17: 0.71
A18: Michigan | B18: 106 | C18: 119 | D18: 114 | E18: 124 | F18: 0.23
A19: New Mexico | B19: 185.66667 | C19: 219.33333 | D19: 203.66667 | E19: 235.66667 | F19: 0.61666667
... A29: Grand Total | B29: 235.11538 | C29: 250.57692 | D29: 239.07692 | E29: 263.26923 | F29: 0.6

Sheet Unit Type #4 Data

Sheet Best Comps
B1: → OCCUPANCY CALL QUESTION EXAMPLES / INFO TO GATHER - FAR RIGHT → | R1: ↓ OCCUPANCY CALL QUESTION EXAMPLES / INFO TO COLLECT - BELOW ↓
F2: INTERNAL - SUBJECT PROPERTY NOTES (Add Property Name): | R2: CALL QUESTION EXAMPLES / INFO TO COLLECT:
B3: Subject | C3: 4.25 | D3: Description | R3: (YOUR NOTES: about reaching them or voicemails, emails, or texts sent and when) • BUSIEST TIMES & HOW FULL: When are the busiest times of year? How full are weekends each season vs. How full are weekdays each season? (totally full, half full, mostly empty) • SLOWEST TIMES & HOW FULL: Quietest times? Weekend vs. Weekday how full when slow? • CLOSED WHEN: Do you close for periods? If so, when are you closed? • BOOK HOW FAR OUT: When busy, how far in advance should I book to get a spot? • AREA ATTRACTIONS: What are the biggest draws for people to the area? • ON-SITE AMENITIES: Double check for all on-site amenities (per unit and communal use)? • RATES – HIGHEST & LOWEST: - What are the busy time rates or highest rates (if not already obtained)? - Slow time rates or lowest rates (if not already obtained)?
B4: Unit Type(s) | D4: 17 small treehouses, 4 large treehouses, 10 small domes, 4 large domes, 15 mirrored cabins, and 1 luxury signature unit.
B5: Unit Amenities | D5: Very high quality furnishings with full bath, bedroom, living area, hot tubs at large treehouses, large dome, signature treehouse, and mirrored cabins. Each unit will have outdoor seating and deck with grill and fire pit.
B6: Property | D6: Forested 500 acres, very high quality, brand new, dirt roads with gravel walkways, and has a small pond on site.
B7: Property Amenities | D7: Limited F&B in lodge which includes a fitness center, meeting area, and business center. Communal hot tub, sauna, and pool.
B8: Location | D8: 70 minutes north of Kansas City, adjacent to a waterfront marina, and located on Nickajack Lake with access to the lake via the adjacent marina. Near restaurants, gas station, and grocery store.
B9: Brand Strength | D9: Assumed to be strong in Year 5 with high quality and professional photos, videos, website, and booking platform, plus good social media and reviews.
F11: INTERNAL - OCCUPANCY CALL NOTES (Add Property Name): | R11: CALL QUESTION EXAMPLES / INFO TO COLLECT:
B12: Bolt Farm Treehouses | C12: 3.75 | D12: Description | R12: (YOUR NOTES: about reaching them or voicemails, emails, or texts sent and when) • • BUSIEST TIMES & HOW FULL: When are the busiest times of year? How full are weekends each season vs. How full are weekdays each season? (totally full, half full, mostly empty) • SLOWEST TIMES & HOW FULL: Quietest times? Weekend vs. Weekday how full when slow? • CLOSED WHEN: Do you close for periods? If so, when are you closed? • BOOK HOW FAR OUT: When busy, how far in advance should I book to get a spot? • AREA ATTRACTIONS: What are the biggest draws for people to the area? • ON-SITE AMENITIES: Double check for all on-site amenities (per unit and communal use)? • RATES – HIGHEST & LOWEST: - What are the busy time rates or highest rates (if not already obtained)? - Slow time rates or lowest rates (if not already obtained)?
B13: Unit Type(s) | D13: Lodge rooms/suites, cabins, Conestoga wagons, and tipis.
B14: Unit Amenities | D14: Wagons and tipis have detached private bathroom, ac, Wi-Fi, coffee maker; cabins have en suite bathroom, kitchen, seating area, grill, deck; lodge rooms have microwave, mini fridge, and patio seating.
B15: Property | D15: 58 acre resort, has a small pond with fishing, treed property, parking is a 2 minute walk from the units, and has dirt roads leading to the property.
B16: Property Amenities | D16: Clubhouse with bar, restaurant, spa, swimming pool, communal fire pit, lawn games, fitness center with sauna, mini-golf, pedal boats, canoes and kayaks, lazy river, paved trails, and playground.
B17: Location | D17: Situated in the mountains, right outside Capitol Reef National Park. After November 1st the local restaurants and stores close down. Near a town with easy access to the local amenities including grocery store, gas stataion and gas. A 15 minute drive to the nearest highway with the interstate 40 minutes away.
B18: Brand Strength | D18: Tripadvisor reviews 4.0 of 2,057: Google reviews: 4.3 of 1,572, high quality website, photography. Mixed reviews with the negative reviews stating that the resort is a glorified motel.
B19: Occupancy Notes | D19: At the time of our research the units were almost completely booked out for the first few months of the year. There is a waiting list for their units.
F21: INTERNAL - OCCUPANCY CALL NOTES (Add Property Name): | R21: CALL QUESTION EXAMPLES / INFO TO COLLECT:
B22: ReTreet Glamping Resort | C22: 4.5 | D22: Description | R22: (YOUR NOTES: about reaching them or voicemails, emails, or texts sent and when) • • BUSIEST TIMES & HOW FULL: When are the busiest times of year? How full are weekends each season vs. How full are weekdays each season? (totally full, half full, mostly empty) • SLOWEST TIMES & HOW FULL: Quietest times? Weekend vs. Weekday how full when slow? • CLOSED WHEN: Do you close for periods? If so, when are you closed? • BOOK HOW FAR OUT: When busy, how far in advance should I book to get a spot? • AREA ATTRACTIONS: What are the biggest draws for people to the area? • ON-SITE AMENITIES: Double check for all on-site amenities (per unit and communal use)? • RATES – HIGHEST & LOWEST: - What are the busy time rates or highest rates (if not already obtained)? - Slow time rates or lowest rates (if not already obtained)?
B23: Unit Type(s) | D23: Lodge rooms/suites, cabins, Conestoga wagons & tipis.
B24: Unit Amenities | D24: Wagons and tipis have detached private bathroom, ac, Wi-Fi, coffee maker; cabins have en suite bathroom, kitchen, seating area, grill, deck; lodge rooms have microwave, mini fridge, and patio seating.
B25: Property | D25: 58 acre resort, has a creek running through, and has a moderate amount of trees. Roads are paved.
B26: Property Amenities | D26: Clubhouse with bar, restaurant, spa, swimming pool, beach area, outdoor games, fitness center, mini-golf, pedal boats, canoes and kayaks, lazy river, paved trails, and playground.
B27: Location | D27: Situated in the mountains near multiple national and state parks. Restaurants and stores are 20 minutes drive away and are only open during the summer high season. A 45 minute drive to interstate access.
B28: Brand Strength | D28: Tripadvisor reviews 4.0 of 2,057: Google reviews: 4.3 of 1,572, high quality website, photography. Mixed reviews with the negative reviews stating that the resort is a glorified motel.
B29: Occupancy Notes | D29: At the time of our research before the 4th of July there were a lot of units available. Front desk manager stated that they were having a slow summer. New to this year is extending the season for the tipis and wagons through the beginning of October. Lodge and cabins are available year-round.
F31: INTERNAL - OCCUPANCY CALL NOTES (Add Property Name): | R31: CALL QUESTION EXAMPLES / INFO TO COLLECT:
B32: ReTreet Glamping Resort | C32: 4.5 | D32: Description | R32: (YOUR NOTES: about reaching them or voicemails, emails, or texts sent and when) • • BUSIEST TIMES & HOW FULL: When are the busiest times of year? How full are weekends each season vs. How full are weekdays each season? (totally full, half full, mostly empty) • SLOWEST TIMES & HOW FULL: Quietest times? Weekend vs. Weekday how full when slow? • CLOSED WHEN: Do you close for periods? If so, when are you closed? • BOOK HOW FAR OUT: When busy, how far in advance should I book to get a spot? • AREA ATTRACTIONS: What are the biggest draws for people to the area? • ON-SITE AMENITIES: Double check for all on-site amenities (per unit and communal use)? • RATES – HIGHEST & LOWEST: - What are the busy time rates or highest rates (if not already obtained)? - Slow time rates or lowest rates (if not already obtained)?
B33: Unit Type(s) | D33: Lodge rooms/suites, cabins, Conestoga wagons & tipis.
B34: Unit Amenities | D34: Wagons and tipis have detached private bathroom, ac, Wi-Fi, coffee maker; cabins have en suite bathroom, kitchen, seating area, grill, deck; lodge rooms have microwave, mini fridge, and patio seating.
B35: Property | D35: 58 acre resort, has a creek running through, and has a moderate amount of trees. Roads are paved.
B36: Property Amenities | D36: Clubhouse with bar, restaurant, spa, swimming pool, beach area, outdoor games, fitness center, mini-golf, pedal boats, canoes and kayaks, lazy river, paved trails, and playground.
B37: Location | D37: Situated in the mountains near multiple national and state parks. Restaurants and stores are 20 minutes drive away and are only open during the summer high season. A 45 minute drive to interstate access.
B38: Brand Strength | D38: Tripadvisor reviews 4.0 of 2,057: Google reviews: 4.3 of 1,572, high quality website, photography. Mixed reviews with the negative reviews stating that the resort is a glorified motel.
B39: Occupancy Notes | D39: At the time of our research before the 4th of July there were a lot of units available. Front desk manager stated that they were having a slow summer. New to this year is extending the season for the tipis and wagons through the beginning of October. Lodge and cabins are available year-round.
D44: LOCATION: Things to consider when writing up location: Drive time to major highway or interstate, major city or cities. Drive time to restaurants, full grocery store, and gas station. Drive time to any major attractions or draws, to nearest major airport. Are there adjacent neighbors or not.

Sheet Comps Summ.
B2: Name | C2: Overview | D2: Amenity Comparison | E2: Distance (mi) | F2: Total Sites | G2: Quality Score
B3: ='Best Comps'!B12 -> Bolt Farm Treehouses | C3: Treehouses, domes & mirror cabins | D3: More and higher quality than subject property | E3: 26 | F3: 19 | G3: ='Best Comps'!C12 -> 3.75
B4: ='Best Comps'!B22 -> ReTreet Glamping Resort | C4: Treehouses, glamping tents & tiny cottages | D4: Less than but similar quality level as subject property | E4: 58 | F4: 17 | G4: ='Best Comps'!C22 -> 4.5
B5: ='Best Comps'!B32 -> ReTreet Glamping Resort | C5: 2 sizes of domes | D5: Similar to subject property | E5: 195 | F5: 8 | G5: ='Best Comps'!C32 -> 4.5
B6: Hunters Lodge | D6: Clubhouse with lots of offerings | F6: 50 | G6: ='Best Comps'!#REF! -> #REF!
B7: Lamplighter | C7: 55+ senior MHC + RV Park | D7: Clubhouse | F7: 275 | G7: 3.1
B8: Houston Creek | C8: 55+ senior MHC + RV Park | F8: 70
I11: INSERT TABLE ONLY FOR A MARKET ANALYSIS
I13: Name | J13: Type | K13: Total # of Sites | L13: Low Daily Retail Rate | M13: Peak Daily Retail Rate | N13: Low Monthly Rate | O13: Peak Monthly Rate | P13: Low Occ. | Q13: Peak Occ. | R13: Quality Score
I14: =B3 -> Bolt Farm Treehouses | J14: Treehouse (Sleeps 2) | K14: 5 | L14: 795 | M14: 895.5 | N14: 440 | O14: 440 | P14: 0.6 | Q14: 0.95 | R14: =G3 -> 3.75
I15: =I14 -> Bolt Farm Treehouses | J15: Friends & Family Treehouse (Sleeps 6) | K15: 1 | L15: 719 | M15: 719 | P15: 0.99 | Q15: 0.99 | R15: =R14 -> 3.75
I16: =I14 -> Bolt Farm Treehouses | J16: Dome (Sleeps 2) | K16: 8 | L16: 565 | M16: 736 | N16: 650 | O16: 650 | P16: 0.7 | Q16: 0.95 | R16: =R15 -> 3.75
I17: =I16 -> Bolt Farm Treehouses | J17: Mirror Cabin (Sleeps 2) | K17: 5 | L17: 496 | M17: 577.5 | P17: 0.7 | Q17: 0.95 | R17: =R16 -> 3.75
I18: =B4 -> ReTreet Glamping Resort | J18: Treehouse (Sleeps 3-4) | K18: 6 | L18: 195 | M18: 195 | N18: 575 | O18: 575 | P18: 0.75 | Q18: 0.95 | R18: =G4 -> 4.5
I19: =I18 -> ReTreet Glamping Resort | J19: Glamping Tent (Sleeps 3-4) | K19: 6 | L19: 215 | M19: 225 | P19: 0.75 | Q19: 0.95 | R19: =R18 -> 4.5
I20: =I19 -> ReTreet Glamping Resort | J20: Tiny Cottage (Sleeps 2) | K20: 5 | L20: 150 | M20: 150 | N20: 650 | O20: 650 | P20: 0.75 | Q20: 0.95 | R20: =G4 -> 4.5
I21: =B5 -> ReTreet Glamping Resort | J21: Large Dome (Sleeps 5-7) | K21: 5 | L21: 130 | M21: 422 | N21: 500 | O21: 500 | P21: 0.6 | Q21: 0.95 | R21: =G5 -> 4.5
I22: =I21 -> ReTreet Glamping Resort | J22: Small Dome (Sleeps 2) | K22: 3 | L22: 123 | M22: 422 | N22: 525 | O22: 525 | P22: 0.6 | Q22: 0.95 | R22: =G5 -> 4.5
J24: Minimum: | K24: =MIN(K14:K23) -> 1 | L24: =MIN(L14:L23) -> 123 | M24: =MIN(M14:M23) -> 150 | N24: =MIN(N14:N23) -> 440 | O24: =MIN(O14:O23) -> 440 | P24: =MIN(P14:P23) -> 0.6 | Q24: =MIN(Q14:Q23) -> 0.95 | R24: =MIN(R14:R23) -> 3.75
J25: Average: | K25: =AVERAGE(K14:K23) -> 4.8888889 | L25: =AVERAGE(L14:L23) -> 376.44444 | M25: =AVERAGE(M14:M23) -> 482.44444 | N25: =AVERAGE(N14:N23) -> 556.66667 | O25: =AVERAGE(O14:O23) -> 556.66667 | P25: =AVERAGE(P14:P23) -> 0.71555556 | Q25: =AVERAGE(Q14:Q23) -> 0.95444444 | R25: =AVERAGE(R14:R23) -> 4.1666667
J26: Max: | K26: =MAX(K14:K23) -> 8 | L26: =MAX(L14:L23) -> 795 | M26: =MAX(M14:M23) -> 895.5 | N26: =MAX(N14:N22) -> 650 | O26: =MAX(O14:O22) -> 650 | P26: =MAX(P14:P23) -> 0.99 | Q26: =MAX(Q14:Q23) -> 0.99 | R26: =MAX(R14:R23) -> 4.5

Sheet ToT (Intake Form)
B2: PROPERTY AND BUSINESS OVERVIEW
B3: Report Type | C3: Glamping Resort Feasibility Study
B5: Owner Summary
B6: Owner Name
B7: Phone Number
B8: Legal Business Name
B9: Owner / Business Address
B10: Purpose of the report?
B12: Property
B13: Resort Name
B14: Resort Type
B15: Resort Full Address
B16: Resort County
B17: Lot Size (Acres)
B18: Lot Size (SF) | C18: =C17*43560 -> 435600
B19: Parcel Number(s)
B22: Units / Sites
B23: Unit A Type | E23: Please specify if cabins are stick built, modular or park model
B24: Unit A Quantity | C24: 0
B25: Unit A Description
B26: Unit B Type
B27: Unit B Quantity | C27: 0
B28: Unit B Description
B29: Unit C Type
B30: Unit C Quantity | C30: 0
B31: Unit C Description
B32: Unit D Type
B33: Unit D Quantity | C33: 0
B34: Unit D Description
B35: Unit E Type
B36: Unit E Quantity | C36: 0
B37: Unit E Description
B38: Unit F Type
B39: Unit F Quantity | C39: 0
B40: Unit F Description
B41: Unit G Type
B42: Unit G Quantity | C42: 0
B43: Unit G Description
B44: Total Units / Sites | C44: =C24+C27+C30+C33+C36+C39+C42 -> 39
B46: Additional Development, Improvements, Amenities
B47: What amenities are planned for the property / guest experience?
B49: Is any of this going to be broken out into a phase 2 or 3 development?
B50: If yes, how many years after will the next phase start?
B51: What stage is the planning / approval process? Having any approvals or permits been issued so far?
B52: What stage is the engineering / design plans? Are there any site layouts or unit designs to date? If yes, please send them to us.
B53: Is there a budget for your project? Please share as much detail as available.
B56: Financing Details
B57: Year Property Purchased
B58: Purchase Price | C58: =47/432.3*20000000 -> 2174415.9
B59: Land Cost Basis (if different): | C59: 2200000
B60: Development Construction Cost: | C60: =C61-C59 -> 13692192
B61: Total Project Cost: | C61: ='Total Proj. Cost'!D16 -> 15892192
B62: % Of Project Cost Financed: | C62: 0.75
B63: Loan Amount Towards Project Cost: | C63: =C62*C61 -> 11919144
B64: Equity Amount Toward Project Cost: | C64: =C61-C63 -> 3973047.9
B65: Interest Rate (Annual): | C65: 0.095
B66: Term of the Loan (Years): | C66: 25
B68: Utilities / Site Infrastructure
B69: Water: What is the status of water access on the property? Is there existing municipal water connections? Or an existing well? If no, have any estimates been gathered to bring water to the site?
B70: Power: What is the status of power / electrical access on the property? Is there existing municipal power source or connection? Will this be an off grid / solar site? If no, have any estimates been gathered to connect power to the site?
B71: Sewer / Septic: What is the status of sewer / septic access on the property? Is there existing municipal water connections? Or an existing well? If no, have any estimates been gathered to bring water access to the site?
B72: Grading: Are there any plans for site grading or earth moving?
B73: Roads / Walkways: Are there any plans you could share for onsite roads, dimensions, parking, walkways?
B75: Attractions
B76: What type of customer demographic are you targeting with your offering?
B77: What is your understanding about why people visit the area? What are the attractions? Why do people visit?
B78: Who do you consider your biggest local or regional competition?
B79: When calling around to local municipalities and competition do you want to keep your site confidential?
B81: Other Revenue Streams
B83: Other Notes

Sheet RATES & OCC. PROJ.
A1: RATES & OCCUPANCY ANALYSIS (REFERENCE & TRAINING) | D1: ↓ ADDITIONAL INSTRUCTIONS / STEPS / INFO BELOW ↓ | E1: YOUR PROJECT NOTES (For Sections on Left): | G1: AI RATES SAMPLE TABLE BELOW
A2: Rates Analysis
B3: Searching for Competitor $ Rates: Training Video Link (Date Video Last Updated 0/0/0):
B4: Example AI (ChatGPT AGENT MODE) Search and Summary Prompt (Copy & Paste):
C5: $ RATES RESEARCH AI PROMPT | D5: $ RATES RESEARCH AI PROMPT
C6: $ RATES PRICING RESEARCH PROMPT: The following prompt should be applied this time to: [TYPE / EDIT FOR - LODGING / GLAMPING UNITS ONLY, RV SITES ONLY, BOTH LODGING / GLAMPING UNITS & RV SITES]. Please go to the [TYPE RESORT NAME] booking website at [TYPE OR PASTE BOOKING WEBSITE URL] and search the main webpage for pricing / rates to compare at [TYPE OR PASTE MAIN WEBSITE URL], then use the booking platform URL to enter dates and view and log nightly rates for mid-week, weekend, and major U.S. holiday's / holiday weekends (such as Labor day, Thanksgiving, Christmas, New Year's, President's Weekend, Memorial Day, July 4th, etc.) throughout all four seasons of the year. For Monday holidays (e.g., Presidents Day, Memorial Day, Labor Day), search Friday–Sunday or Saturday–Monday stays and record the nightly rates reflecting any holiday premium. Do not use Monday night–Tuesday checkout rates unless the resort explicitly applies a holiday premium to that night. If no distinct holiday premium is observed versus standard weekend pricing, note that the resort does not apply a holiday uplift.There may be requirements at times for minimum of multi-night stays to book and see the rates, and in those cases you will get search for multiple nights when requred, but then if the multi-night pricing does not show as a single night price go ahead and divide the total cost for multiple nights by the number of nights scheduled to report back to the User with a single night rate in your output. Additionally, sometimes you may find that the chosen sample date selection is booked in certain seasons, be sure to choose another date set that simlarly represents the season, time of week, and/or holiday for that season, do not leave empty dates if possible, and do not fabricate or estimate rates unless the User instructs you to provide and estimate based on other real rates you located (you must inform the User of any of these items). And you can average across the peak season months to get the most common or average rates for mid-week, weekend, and holiday of that peak season, and you can average across the low season months to get the most common or average rates for mid-week, weekend, and holiday of that low season. Also, search for monthly rates during each of the four seasons of the year (please be sure to try selecting at least 30 nights or so on any online booking calendar to determine whether the monthly rate is different and majorly discounted from their nightly / daily rates there vs. what their main website or other websites show for a monthly rate. NOTE: If searching for RV info; most RV parks / resorts give approximately a 50% or more discount per night compared to what the total would be for the usual daily rate for a month's or 30 days or so worth of nights, so if you see rates that don't reasonably meet this criteria, then report back the discrepancy and don't use the rate that is near the usual daily rate X 30 nights). If you are searching for lodging / glamping units, or for the same in addition to RV information, be sure to view all unit types and different bedroom configurations for all specified times and time periods, as rates may vary. If you are searching for RV $ rates some sites will require you to enter other details, enter values, or select dropdown menu options before you can view accurate rates (when this occurs select van if available, or travel trailer if not, then use dimensions of a length of approximately 20 feet, width of approximately 8 feet, and No slideouts, otherwise you may not see all available sites and rates). If there is ever a screen that appears like you must enter a name or email address, there is usually also a button or text on the screen (not usually very obvious) that you can click to "skip this step" and move forward to the booking platform without entering name, email, phone, etc., so skip that part and keep going. You may also reference other reputable sites or obtain documents, etc., that provide accurate information as requested regarding this particular property, or be creative in finding a way to obtain the requested rate information. Next, provide a table showing the rates you find for the categories and time frames I shared. Please cite your findings. For more complicated cases that require extrapolation or calculation, show your work to support your conclusions. | D6: FOR ADDING THE PROMPT TO THE AI's SAVED MEMORY: Please add the following prompt to your Saved Memory for later use. Any items that are in all Capital Letters and in Brackets are the information I should provide you for that particular resort at the time the prompt is requested for use, and if I do not provide that information, then please ask me to do so. This prompt will be called the Rates Pricing Research Prompt. FOR ADDING THE RATES INPUT EXCEL TABLE SAMPLE FOR THE AI: Please also save in your "Saved Memory" the Excel table that I provided to use with the Rates Pricing Research Prompt. When providing your findings on the rates please provide them in the chat as usual, but then also provide them in an Excel spreadsheet using my Style Guide basics previously provided to your saved memory, but then enter the information for each RV Site Type or Glamping / Lodging Unit Type, with labeling by site / unit type such as Standard RV Back-in, Premium RV Pull Thru, Cabin 1 BR (Sleeps 2-4), Safari Tent (Sleeps 2-6), for what the resort offers. Place the rates samples you obtain in duplicate versions, as many as needed for each site / unit type, of the table example I have included in this message for you to also include in your Saved Memory. This table format I provided to you will allow me to copy and paste your results directly into the Excel workbook for my particular project for that resort, and by each unit / site type and rates samples you've obtained to meet the criteria of the Excel table I provided with this message. You will provide in this table format for each site / unit type in the appropriate cells the resort name as shown (use general cell format), the unit / site type name (text cell format), and each rate dollar amount (use currency cell format), such as Mid-week, Weekend, Holiday, and for Low Season (rate sample times predicted to have lower occupancy) or Peak Season (rates sample times predicted to have higher occupancy) in each of the appropriate table cells as indicated in the row headers corresponding to the neighboring cells.
C7: AI PROMPT INSTRUCTIONS TO PACKAGE THE INFO IT PROVIDED FROM THE RATES $ RESEARCH AI PROMPT ABOVE THIS ONE: Can you please now place the rates the AI in Agent Mode has gathered and replied with organized in the appropriate cells using the exact format, layout, and formulas in this Excel and have each unit type, and site type have its own Excel sheet tab, within the Excel overall worksheet that the AI replies with for me to download. There is a Word doc that explains the style guide for the AI to follow as well for Excel. [NOTE: Author needs to upload to the AI / ChatGPT with this message both the Sage Word Doc Style Guide and Sage AI Rates Input Table Sample Excel located in the Sage Templates Folder as Template > 3.5 AI ChatGPT Resources_Uploads_Guides]
A10: Occupancy Analysis
B11: Searching for Competitor Occupancy: Training Video Link (Date Video Last Updated 0/0/0):
B12: Example AI (ChatGPT AGENT MODE) Search and Summary Prompt (Copy & Paste):
C13: % OCCUPANCY RESEARCH AI PROMPT | D13: % OCCUPANCY RESEARCH AI PROMPT
C14: % OCCUPANCY RESEARCH PROMPT: The following prompt should be applied this time to: [TYPE / EDIT FOR - LODGING / GLAMPING UNITS ONLY, RV SITES ONLY, BOTH LODGING / GLAMPING UNITS & RV SITES]. Please go to the [TYPE RESORT NAME] booking website at [TYPE OR PASTE BOOKING WEBSITE URL] and also search the main webpage for information to gather or compare at [TYPE OR PASTE MAIN WEBSITE URL], and do whatever you can do to search for and find or determine % occupancy rates for past historical data (last 1 or 2 years) and future near term data (priorities of today, next few days, next week or few weeks, month, next holiday, etc.), whether it requires you to do any or all of the following; enter dates in the booking platform, search for documents, reports, or PDFs shared online, or websites, etc. for anything you can obtain on occupancy over the past yearand / or for the next few days, weeks, or months ahead for mid-week, weekend, each month for 12 months, total occupancy for a 12 month period, and for major U.S. holiday's / holiday weekends (such as Labor day, Thanksgiving, Christmas, New Year's, President's Weekend, Memorial Day, July 4th, etc.) throughout all four seasons of the year, and also for monthly site occupancy for the entire season for each of the four seasons of the year, and provide a table showing the occupancy percentages you find for the categories and time frames I shared. If you can't find such information readily available, then attempt to use any available online booking platforms to see if you can see, either in menus or on an interactive resort or park site map, compare and determine with the static resort or park site map to help or give a basis and determine site counts by unit or RV site type and the unit or RV site totals and quality or special types, for then determining the amount of units showing available or the amount of units occupied either stated or in viewing mapping, etc. to then extrapolate and / or calculate the occupancy rate(s) for the times and time periods I have outlined. On interactive maps, they work in varied ways, which may require you to hover and / or click them to compare clickable available sites to non-clickable images that indicate unavailable units or sites, or interpret or read pop-ups when hovering that tell whether the site is available or reserved. This works mostly for looking at the current day or future days, weeks, and months, but sometimes shows even past information that can be used to determine occupancy. If you are searching for lodging / glamping units, or for the same in addition to RV sites, be sure to view all unit types and different unit bedroom configurations for all times and time periods I've specified, as those rates may vary. If you are searching for RV $ rates or using rates search to determine occupancy, some sites will require you to enter other details, enter values, or select dropdown menu options before you can view accurate rates (when this occurs select van if available, or travel trailer if not, then use dimensions of a length of approximately 20 feet, width of approximately 8 feet, and No slideouts, otherwise you may not see all available sites and rates). If there is ever a screen that appears like you must enter a name or email address, there is usually also a button or text on the screen (not usually very obvious) that you can click to "skip this step" and move forward to the booking platform without entering name, email, phone, etc., so skip that part and keep going. You may also reference other reputable sites or obtain documents, etc., that provide accurate information as requested regarding this particular property, or be creative in finding a way to obtain the requested occupancy information. Next, provide a table showing the occupancy percentages you find or determine for the categories and time frames I shared. Please cite your findings. For more complicated cases that require extrapolation or calculation, show your work to support your conclusions. | D14: FOR ADDING THE PROMPT TO THE AI's SAVED MEMORY: Please add the following prompt to your Saved Memory for later use. Any items that are in all Capital Letters and in Brackets are the information I should provide you for that particular resort at the time the prompt is requested for use, and if I do not provide that information, then please ask me to do so. This prompt will be called the Occupancy Research Prompt.
G16: Best / Area Comp Name: | H16: Enter Resort Name Here
G17: Site/Unit Name & Type: | H17: Enter Site or Unit Type Name Here
H18: LOW Season Rates | I18: PEAK Season Rates
G19: Mid-week Rate 1 | H19: 0 | I19: 0
G20: Mid-week Rate 2 | H20: 0 | I20: 0
G21: Weekend Rate 1 | H21: 0 | I21: 0
G22: Weekend Rate 2 | H22: 0 | I22: 0
G23: Holiday Rate for Season | H23: 0 | I23: 0

Sheet Rates Proj
B1: CALCULATOR FOR - AVERAGE SEASONAL DAILY RETAIL RATES TO RIGHT & DOWN AT R60:
B2: 1ST Unit Type
B3: Cabin Retail Rate Indicators | C3: Low | D3: Peak | E3: Avg. | F3: Quality
B4: Sage Dataset Cabins | C4: =GETPIVOTDATA("Average of Low Rate (Next 12 Months)",'Unit Type #1 Data'!$A$8) -> 220.96667 | D4: =GETPIVOTDATA("Average of High Rate (Next 12 Months)",'Unit Type #1 Data'!$A$8) -> 237.26667 | E4: =GETPIVOTDATA("Average Rate (Next 12 Months)",'Unit Type #1 Data'!$A$8) -> 228.8 | F4: 4
B5: =R66 -> Comp 1 Name Cabin (Sleeps 2) | C5: =R73 -> 1 | D5: =S73 -> 2 | E5: =AVERAGE(C5:D5) -> 1.5 | F5: ='Best Comps'!C12 -> 3.75 | G5: <=only list comparables that relate to subject i.e. no. of people unit sleeps
B6: =R78 -> Comp 2 Name Cabin (Sleeps 2) | C6: =R85 -> 3 | D6: =S85 -> 4 | E6: =AVERAGE(C6:D6) -> 3.5 | F6: ='Best Comps'!C22 -> 4.5
B7: =R90 -> Comp 3 Name Cabin (Sleeps 2) | C7: =R97 -> 5 | D7: =S97 -> 6 | E7: =AVERAGE(C7:D7) -> 5.5 | F7: ='Best Comps'!C23 -> 0
B8: =R102 -> Comp 4 Name Cabin (Sleeps 2) | C8: =R109 -> 7 | D8: =S109 -> 8 | E8: =AVERAGE(C8:D8) -> 7.5 | F8: ='Best Comps'!C24 -> 0
B10: Average | C10: =AVERAGE(C4:C9) -> 47.393333 | D10: =AVERAGE(D4:D9) -> 51.453333 | E10: =AVERAGE(E4:E9) -> 49.36 | F10: =AVERAGE(F4:F9) -> 2.45
B11: Subject Projected Mirror Cabin Large Rates | C11: 400 | D11: 500 | E11: =AVERAGE(C11:D11) -> 450 | F11: ='Best Comps'!C3 -> 4.25
B12: Subject Projected Mirror Cabin Rates | C12: 400 | D12: 500 | E12: =AVERAGE(C12:D12) -> 450 | F12: ='Best Comps'!C3 -> 4.25
B14: 2ND Unit Type
B15: Treehouse Retail Rate Indicators | C15: Low | D15: Peak | E15: Avg. | F15: Quality
B16: Sage Dataset Treehouses | C16: =GETPIVOTDATA("Average of Low Rate (Next 12 Months)",'Unit Type #2 Data'!$A$7) -> 227.43939 | D16: =GETPIVOTDATA("Average of High Rate (Next 12 Months)",'Unit Type #2 Data'!$A$7) -> 257.10606 | E16: =GETPIVOTDATA("Average Rate (Next 12 Months)",'Unit Type #2 Data'!$A$7) -> 242.28788 | F16: 3.5
B17: =V66 -> Comp 1 Name Treehouse (Sleeps 2) | C17: =V73 -> 10 | D17: =W73 -> 20 | E17: =AVERAGE(C17:D17) -> 15 | F17: ='Best Comps'!C12 -> 3.75 | G17: <=only list comparables that relate to subject i.e. no. of people unit sleeps
B18: =V78 -> Comp 2 Name Treehouse (Sleeps 2) | C18: =V85 -> 30 | D18: =W85 -> 40 | E18: =AVERAGE(C18:D18) -> 35 | F18: =F17 -> 3.75
B19: =V90 -> Comp 3 Name Treehouse (Sleeps 2) | C19: =V97 -> 50 | D19: =W97 -> 60 | E19: =AVERAGE(C19:D19) -> 55 | F19: ='Best Comps'!C22 -> 4.5
B20: =V102 -> Comp 4 Name Treehouse (Sleeps 2) | C20: =V109 -> 70 | D20: =W109 -> 80 | E20: =AVERAGE(C20:D20) -> 75 | F20: 0
B22: Average | C22: =AVERAGE(C16:C21) -> 77.487879 | D22: =AVERAGE(D16:D21) -> 91.421212 | E22: =AVERAGE(E16:E21) -> 84.457576 | F22: =AVERAGE(F16:F21) -> 3.1
B23: Subject Projected Small Treehouse Rates | C23: 250 | D23: 350 | E23: =AVERAGE(C23:D23) -> 300 | F23: ='Best Comps'!C3 -> 4.25
B24: Subject Projected Large Treehouse Rates | C24: 300 | D24: 400 | E24: =AVERAGE(C24:D24) -> 350 | F24: ='Best Comps'!$C$3 -> 4.25
B25: Subject Projected Signature Treehouse Rates | C25: 600 | D25: 750 | E25: =AVERAGE(C25:D25) -> 675 | F25: ='Best Comps'!$C$3 -> 4.25
B27: 3RD Unit Type
B28: Dome Retail Rate Indicators | C28: Low | D28: Peak | E28: Avg. | F28: Quality
B29: Sage Dataset Domes | C29: =GETPIVOTDATA("Average of Low Rate (Next 12 Months)",'Unit Type #3 Data'!$A$7) -> 239.07692 | D29: =GETPIVOTDATA("Average of High Rate (Next 12 Months)",'Unit Type #3 Data'!$A$7) -> 263.26923 | E29: =GETPIVOTDATA("Average Rate (Next 12 Months)",'Unit Type #3 Data'!$A$7) -> 250.57692 | F29: 3.5
B30: =Z66 -> Comp 1 Name Dome (Sleeps 2) | C30: =Z73 -> 100 | D30: =AA73 -> 200 | E30: =AVERAGE(C30:D30) -> 150 | F30: ='Best Comps'!C12 -> 3.75 | G30: <=only list comparables that relate to subject i.e. no. of people unit sleeps
B31: =Z78 -> Comp 2 Name Dome (Sleeps 2) | C31: =Z85 -> 300 | D31: =AA85 -> 400 | E31: =AVERAGE(C31:D31) -> 350 | F31: ='Best Comps'!C32 -> 4.5
B32: =Z90 -> Comp 3 Name Dome (Sleeps 2) | C32: =Z97 -> 500 | D32: =AA97 -> 600 | E32: =AVERAGE(C32:D32) -> 550 | F32: ='Best Comps'!C32 -> 4.5
B33: =Z102 -> Comp 4 Name Dome (Sleeps 2) | C33: =Z109 -> 700 | D33: =AA109 -> 800 | E33: =AVERAGE(C33:D33) -> 750 | F33: 0
B35: Average | C35: =AVERAGE(C29:C34) -> 367.81538 | D35: =AVERAGE(D29:D34) -> 452.65385 | E35: =AVERAGE(E29:E34) -> 410.11538 | F35: =AVERAGE(F29:F34) -> 3.25
B36: Subject Projected Small Dome Rates | C36: 250 | D36: 425 | E36: =AVERAGE(C36:D36) -> 337.5 | F36: ='Best Comps'!C3 -> 4.25
B37: Subject Projected Large Dome Rates | C37: 300 | D37: 500 | E37: =AVERAGE(C37:D37) -> 400 | F37: ='Best Comps'!$C$3 -> 4.25
B39: 4TH Unit Type
B40: Park Model Cabin Retail Rate Indicators | C40: Low | D40: Peak | E40: Avg. | F40: Quality
B41: Sage Dataset Park Model | C41: =E41*0.8 -> #REF! | D41: =E41*1.2 -> #REF! | E41: =GETPIVOTDATA("Avg. Price",#REF!) -> #REF! | F41: 3.5
B42: =AD66 -> Comp 1 Name Park Model Cab.(Sleeps 2) | C42: =AD73 -> 11 | D42: =AE73 -> 12 | E42: =AVERAGE(C42:D42) -> 11.5 | F42: ='Best Comps'!C22 -> 4.5 | G42: <=only list comparables that relate to subject i.e. no. of people unit sleeps
B43: =AD78 -> Comp 2 Name Park Model Cab.(Sleeps 2) | C43: =AD85 -> 13 | D43: =AE85 -> 14 | E43: =AVERAGE(C43:D43) -> 13.5 | F43: ='Best Comps'!C42 -> 0
B44: =AD90 -> Comp 3 Name Park Model Cab.(Sleeps 2) | C44: =AD97 -> 15 | D44: =AE97 -> 16 | E44: =AVERAGE(C44:D44) -> 15.5 | F44: ='Best Comps'!C42 -> 0
B45: =AD102 -> Comp 4 Name Park Model Cab.(Sleeps 2) | C45: =AD109 -> 17 | D45: =AE109 -> 18 | E45: =AVERAGE(C45:D45) -> 17.5 | F45: 0
B47: Average | C47: =AVERAGE(C41:C46) -> #REF! | D47: =AVERAGE(D41:D46) -> #REF! | E47: =AVERAGE(E41:E46) -> #REF! | F47: =AVERAGE(F41:F46) -> 1.6
B48: Subject Projected Small Dome Rates | C48: 250 | D48: 425 | E48: =AVERAGE(C48:D48) -> 337.5 | F48: ='Best Comps'!C13 -> 0
B49: Subject Projected Large Dome Rates | C49: 300 | D49: 500 | E49: =AVERAGE(C49:D49) -> 400 | F49: ='Best Comps'!$C$3 -> 4.25
L50: Daily Rate Projections (Year 1) | M50: Low | N50: Peak | O50: Yr1 Annual ADR (Occ. Weighted)
L51: ='ToT (Intake Form)'!C23 -> Mirror Cabin Large | M51: =C23 -> 250 | N51: =D23 -> 350 | O51: ='Monthly PF'!Q5 -> 296.66259
L52: ='ToT (Intake Form)'!C26 -> Mirror Cabin Small | M52: =C24 -> 300 | N52: =D24 -> 400 | O52: ='Monthly PF'!Q10 -> 355.11618
L53: ='ToT (Intake Form)'!C29 -> Dome Large | M53: =C36 -> 250 | N53: =D36 -> 425 | O53: ='Monthly PF'!Q15 -> 333.04749
L54: ='ToT (Intake Form)'!C32 -> Dome Small | M54: =C37 -> 300 | N54: =D37 -> 500 | O54: ='Monthly PF'!Q20 -> 396.16796
L55: ='ToT (Intake Form)'!C35 -> Safari Tent Large | M55: =C11 -> 400 | N55: =D11 -> 500 | O55: ='Monthly PF'!Q25 -> 451.68779
L56: ='ToT (Intake Form)'!C38 -> Safari Tent Medium | M56: =C25 -> 600 | N56: =D25 -> 750 | O56: ='Monthly PF'!Q30 -> 681.09903
L57: ='ToT (Intake Form)'!C41 -> USE FOR MONTHLY | M57: =#REF! -> #REF! | N57: =#REF! -> #REF! | O57: ='Monthly PF'!Q35 -> 0
Q60: INTERNAL - AVERAGE SEASONAL DAILY RETAIL RATES CALCULATOR: (Calculates Weighted Average Low & High Season Daily Rates Automatically)
Q62: Best / Area Comps
R63: 1ST Unit Type Column | V63: 2ND Unit Type Column | Z63: 3RD Unit Type Column | AD63: 4TH Unit Type Column
Q64: 1
Q65: Best / Area Comp Name: | R65: Comp 1 Name
L66: DIRECTIONS (Average Seasonal Daily Rates Calculator): => 1. Blue Boxes & Labeling: Fill in the blue boxes to include Comp Name box & Comp Name / Unit Name/Type/Sleeps # box (the 2nd will Autopopulate to Rate Indicators table in top left of this sheet) 2. Unit Types Organization: Keep all Units of similar type represented in each Comp in the same Vertical Column here. So that they are being categorized here as the same unit type and they go to the proper unit type Rate Indicator table to be calculated together automatically into one unit type average for your reference (and then used at the end to estimate for manual entry at top left of this sheet, your estimated low and peak rates per unit type) 3. Rates Entry & Automatic Averages: Then, fill in all the other blue boxes for rates with the real rate samples you obtain for mid-week, weekend, and holiday fo that property and unit type (the the averages from the bottom row will autopopulate to Rate Indicators table at top left of this sheet from the weighted calculation preset in the averages row for all of each comp's unit types tables here) 4. Verify Correct Data: Check the data and headings of your Rates Indicator Tables to be sure it appears correct from your entries here with all pertinent info 5. Connect to Daily Rates Projection (Year 1) Table: Next link the appropirate cells from your manually projected rates in the upper left rates indicator tables to the appropriate cells of the Daily Rates Projection Table to the lower left of the rates indicator tables NOTE (Need More?): If you need more than 4 Best Comps or more than 4 Unit Types, then copy and paste more of each needed table by column and row in the calculator on the right and then create the spaces in the rates indicators tables (top left of this sheet) as appropriate and link the calculators and rates indicator tables together for autocalculation and autopopulation | Q66: 1ST Unit Name/Type/Slps: | R66: Comp 1 Name Cabin (Sleeps 2) | U66: 2ND Unit Name/Type/Slps: | V66: Comp 1 Name Treehouse (Sleeps 2) | Y66: 3RD Unit Name/Type/Slps: | Z66: Comp 1 Name Dome (Sleeps 2) | AC66: 4TH Unit Name/Type/Slps: | AD66: Comp 1 Name Park Model Cab.(Sleeps 2)
R67: LOW Season Rates | S67: PEAK Season Rates | V67: LOW Season Rates | W67: PEAK Season Rates | Z67: LOW Season Rates | AA67: PEAK Season Rates | AD67: LOW Season Rates | AE67: PEAK Season Rates
Q68: Mid-week Rate 1 | R68: 1 | S68: 2 | U68: Mid-week Rate 1 | V68: 10 | W68: 20 | Y68: Mid-week Rate 1 | Z68: 100 | AA68: 200 | AC68: Mid-week Rate 1 | AD68: 11 | AE68: 12
Q69: Mid-week Rate 2 | R69: 1 | S69: 2 | U69: Mid-week Rate 2 | V69: 10 | W69: 20 | Y69: Mid-week Rate 2 | Z69: 100 | AA69: 200 | AC69: Mid-week Rate 2 | AD69: 11 | AE69: 12
Q70: Weekend Rate 1 | R70: 1 | S70: 2 | U70: Weekend Rate 1 | V70: 10 | W70: 20 | Y70: Weekend Rate 1 | Z70: 100 | AA70: 200 | AC70: Weekend Rate 1 | AD70: 11 | AE70: 12
Q71: Weekend Rate 2 | R71: 1 | S71: 2 | U71: Weekend Rate 2 | V71: 10 | W71: 20 | Y71: Weekend Rate 2 | Z71: 100 | AA71: 200 | AC71: Weekend Rate 2 | AD71: 11 | AE71: 12
Q72: Holiday Rate for Season | R72: 1 | S72: 2 | U72: Holiday Rate for Season | V72: 10 | W72: 20 | Y72: Holiday Rate for Season | Z72: 100 | AA72: 200 | AC72: Holiday Rate for Season | AD72: 11 | AE72: 12
Q73: AVERAGES | R73: =((R68+R69)/2*0.65)+((R70+R71)/2*0.25)+(R72*0.1) -> 1 | S73: =((S68+S69)/2*0.65)+((S70+S71)/2*0.25)+(S72*0.1) -> 2 | U73: AVERAGES | V73: =((V68+V69)/2*0.65)+((V70+V71)/2*0.25)+(V72*0.1) -> 10 | W73: =((W68+W69)/2*0.65)+((W70+W71)/2*0.25)+(W72*0.1) -> 20 | Y73: AVERAGES | Z73: =((Z68+Z69)/2*0.65)+((Z70+Z71)/2*0.25)+(Z72*0.1) -> 100 | AA73: =((AA68+AA69)/2*0.65)+((AA70+AA71)/2*0.25)+(AA72*0.1) -> 200 | AC73: AVERAGES | AD73: =((AD68+AD69)/2*0.65)+((AD70+AD71)/2*0.25)+(AD72*0.1) -> 11 | AE73: =((AE68+AE69)/2*0.65)+((AE70+AE71)/2*0.25)+(AE72*0.1) -> 12
Q76: 2
Q77: Best / Area Comp Name: | R77: Comp 2 Name
Q78: 1ST Unit Name/Type/Slps: | R78: Comp 2 Name Cabin (Sleeps 2) | U78: 2ND Unit Name/Type/Slps: | V78: Comp 2 Name Treehouse (Sleeps 2) | Y78: 3RD Unit Name/Type/Slps: | Z78: Comp 2 Name Dome (Sleeps 2) | AC78: 4TH Unit Name/Type/Slps: | AD78: Comp 2 Name Park Model Cab.(Sleeps 2)
R79: LOW Season Rates | S79: PEAK Season Rates | V79: LOW Season Rates | W79: PEAK Season Rates | Z79: LOW Season Rates | AA79: PEAK Season Rates | AD79: LOW Season Rates | AE79: PEAK Season Rates
Q80: Mid-week Rate 1 | R80: 3 | S80: 4 | U80: Mid-week Rate 1 | V80: 30 | W80: 40 | Y80: Mid-week Rate 1 | Z80: 300 | AA80: 400 | AC80: Mid-week Rate 1 | AD80: 13 | AE80: 14
Q81: Mid-week Rate 2 | R81: 3 | S81: 4 | U81: Mid-week Rate 2 | V81: 30 | W81: 40 | Y81: Mid-week Rate 2 | Z81: 300 | AA81: 400 | AC81: Mid-week Rate 2 | AD81: 13 | AE81: 14
Q82: Weekend Rate 1 | R82: 3 | S82: 4 | U82: Weekend Rate 1 | V82: 30 | W82: 40 | Y82: Weekend Rate 1 | Z82: 300 | AA82: 400 | AC82: Weekend Rate 1 | AD82: 13 | AE82: 14
Q83: Weekend Rate 2 | R83: 3 | S83: 4 | U83: Weekend Rate 2 | V83: 30 | W83: 40 | Y83: Weekend Rate 2 | Z83: 300 | AA83: 400 | AC83: Weekend Rate 2 | AD83: 13 | AE83: 14
Q84: Holiday Rate for Season | R84: 3 | S84: 4 | U84: Holiday Rate for Season | V84: 30 | W84: 40 | Y84: Holiday Rate for Season | Z84: 300 | AA84: 400 | AC84: Holiday Rate for Season | AD84: 13 | AE84: 14
Q85: AVERAGES | R85: =((R80+R81)/2*0.65)+((R82+R83)/2*0.25)+(R84*0.1) -> 3 | S85: =((S80+S81)/2*0.65)+((S82+S83)/2*0.25)+(S84*0.1) -> 4 | U85: AVERAGES | V85: =((V80+V81)/2*0.65)+((V82+V83)/2*0.25)+(V84*0.1) -> 30 | W85: =((W80+W81)/2*0.65)+((W82+W83)/2*0.25)+(W84*0.1) -> 40 | Y85: AVERAGES | Z85: =((Z80+Z81)/2*0.65)+((Z82+Z83)/2*0.25)+(Z84*0.1) -> 300 | AA85: =((AA80+AA81)/2*0.65)+((AA82+AA83)/2*0.25)+(AA84*0.1) -> 400 | AC85: AVERAGES | AD85: =((AD80+AD81)/2*0.65)+((AD82+AD83)/2*0.25)+(AD84*0.1) -> 13 | AE85: =((AE80+AE81)/2*0.65)+((AE82+AE83)/2*0.25)+(AE84*0.1) -> 14
Q88: 3
Q89: Best / Area Comp Name: | R89: Comp 3 Name
Q90: 1ST Unit Name/Type/Slps: | R90: Comp 3 Name Cabin (Sleeps 2) | U90: 2ND Unit Name/Type/Slps: | V90: Comp 3 Name Treehouse (Sleeps 2) | Y90: 3RD Unit Name/Type/Slps: | Z90: Comp 3 Name Dome (Sleeps 2) | AC90: 4TH Unit Name/Type/Slps: | AD90: Comp 3 Name Park Model Cab.(Sleeps 2)
R91: LOW Season Rates | S91: PEAK Season Rates | V91: LOW Season Rates | W91: PEAK Season Rates | Z91: LOW Season Rates | AA91: PEAK Season Rates | AD91: LOW Season Rates | AE91: PEAK Season Rates
Q92: Mid-week Rate 1 | R92: 5 | S92: 6 | U92: Mid-week Rate 1 | V92: 50 | W92: 60 | Y92: Mid-week Rate 1 | Z92: 500 | AA92: 600 | AC92: Mid-week Rate 1 | AD92: 15 | AE92: 16
Q93: Mid-week Rate 2 | R93: 5 | S93: 6 | U93: Mid-week Rate 2 | V93: 50 | W93: 60 | Y93: Mid-week Rate 2 | Z93: 500 | AA93: 600 | AC93: Mid-week Rate 2 | AD93: 15 | AE93: 16
Q94: Weekend Rate 1 | R94: 5 | S94: 6 | U94: Weekend Rate 1 | V94: 50 | W94: 60 | Y94: Weekend Rate 1 | Z94: 500 | AA94: 600 | AC94: Weekend Rate 1 | AD94: 15 | AE94: 16
Q95: Weekend Rate 2 | R95: 5 | S95: 6 | U95: Weekend Rate 2 | V95: 50 | W95: 60 | Y95: Weekend Rate 2 | Z95: 500 | AA95: 600 | AC95: Weekend Rate 2 | AD95: 15 | AE95: 16
Q96: Holiday Rate for Season | R96: 5 | S96: 6 | U96: Holiday Rate for Season | V96: 50 | W96: 60 | Y96: Holiday Rate for Season | Z96: 500 | AA96: 600 | AC96: Holiday Rate for Season | AD96: 15 | AE96: 16
Q97: AVERAGES | R97: =((R92+R93)/2*0.65)+((R94+R95)/2*0.25)+(R96*0.1) -> 5 | S97: =((S92+S93)/2*0.65)+((S94+S95)/2*0.25)+(S96*0.1) -> 6 | U97: AVERAGES | V97: =((V92+V93)/2*0.65)+((V94+V95)/2*0.25)+(V96*0.1) -> 50 | W97: =((W92+W93)/2*0.65)+((W94+W95)/2*0.25)+(W96*0.1) -> 60 | Y97: AVERAGES | Z97: =((Z92+Z93)/2*0.65)+((Z94+Z95)/2*0.25)+(Z96*0.1) -> 500 | AA97: =((AA92+AA93)/2*0.65)+((AA94+AA95)/2*0.25)+(AA96*0.1) -> 600 | AC97: AVERAGES | AD97: =((AD92+AD93)/2*0.65)+((AD94+AD95)/2*0.25)+(AD96*0.1) -> 15 | AE97: =((AE92+AE93)/2*0.65)+((AE94+AE95)/2*0.25)+(AE96*0.1) -> 16
Q100: 4
Q101: Best / Area Comp Name: | R101: Comp 4 Name
Q102: 1ST Unit Name/Type/Slps: | R102: Comp 4 Name Cabin (Sleeps 2) | U102: 2ND Unit Name/Type/Slps: | V102: Comp 4 Name Treehouse (Sleeps 2) | Y102: 3RD Unit Name/Type/Slps: | Z102: Comp 4 Name Dome (Sleeps 2) | AC102: 4TH Unit Name/Type/Slps: | AD102: Comp 4 Name Park Model Cab.(Sleeps 2)
R103: LOW Season Rates | S103: PEAK Season Rates | V103: LOW Season Rates | W103: PEAK Season Rates | Z103: LOW Season Rates | AA103: PEAK Season Rates | AD103: LOW Season Rates | AE103: PEAK Season Rates
Q104: Mid-week Rate 1 | R104: 7 | S104: 8 | U104: Mid-week Rate 1 | V104: 70 | W104: 80 | Y104: Mid-week Rate 1 | Z104: 700 | AA104: 800 | AC104: Mid-week Rate 1 | AD104: 17 | AE104: 18
Q105: Mid-week Rate 2 | R105: 7 | S105: 8 | U105: Mid-week Rate 2 | V105: 70 | W105: 80 | Y105: Mid-week Rate 2 | Z105: 700 | AA105: 800 | AC105: Mid-week Rate 2 | AD105: 17 | AE105: 18
Q106: Weekend Rate 1 | R106: 7 | S106: 8 | U106: Weekend Rate 1 | V106: 70 | W106: 80 | Y106: Weekend Rate 1 | Z106: 700 | AA106: 800 | AC106: Weekend Rate 1 | AD106: 17 | AE106: 18
Q107: Weekend Rate 2 | R107: 7 | S107: 8 | U107: Weekend Rate 2 | V107: 70 | W107: 80 | Y107: Weekend Rate 2 | Z107: 700 | AA107: 800 | AC107: Weekend Rate 2 | AD107: 17 | AE107: 18
Q108: Holiday Rate for Season | R108: 7 | S108: 8 | U108: Holiday Rate for Season | V108: 70 | W108: 80 | Y108: Holiday Rate for Season | Z108: 700 | AA108: 800 | AC108: Holiday Rate for Season | AD108: 17 | AE108: 18
Q109: AVERAGES | R109: =((R104+R105)/2*0.65)+((R106+R107)/2*0.25)+(R108*0.1) -> 7 | S109: =((S104+S105)/2*0.65)+((S106+S107)/2*0.25)+(S108*0.1) -> 8 | U109: AVERAGES | V109: =((V104+V105)/2*0.65)+((V106+V107)/2*0.25)+(V108*0.1) -> 70 | W109: =((W104+W105)/2*0.65)+((W106+W107)/2*0.25)+(W108*0.1) -> 80 | Y109: AVERAGES | Z109: =((Z104+Z105)/2*0.65)+((Z106+Z107)/2*0.25)+(Z108*0.1) -> 700 | AA109: =((AA104+AA105)/2*0.65)+((AA106+AA107)/2*0.25)+(AA108*0.1) -> 800 | AC109: AVERAGES | AD109: =((AD104+AD105)/2*0.65)+((AD106+AD107)/2*0.25)+(AD108*0.1) -> 17 | AE109: =((AE104+AE105)/2*0.65)+((AE106+AE107)/2*0.25)+(AE108*0.1) -> 18
Q112: 5
Q113: Best / Area Comp Name: | R113: Comp 5 Name
Q114: 1ST Unit Name/Type/Slps: | R114: Comp 5 Name Cabin (Sleeps 2) | U114: 2ND Unit Name/Type/Slps: | V114: Comp 5 Name Treehouse (Sleeps 2) | Y114: 3RD Unit Name/Type/Slps: | Z114: Comp 5 Name Dome (Sleeps 2) | AC114: 4TH Unit Name/Type/Slps: | AD114: Comp 5 Name Park Model Cab.(Sleeps 2)
R115: LOW Season Rates | S115: PEAK Season Rates | V115: LOW Season Rates | W115: PEAK Season Rates | Z115: LOW Season Rates | AA115: PEAK Season Rates | AD115: LOW Season Rates | AE115: PEAK Season Rates
Q116: Mid-week Rate 1 | U116: Mid-week Rate 1 | Y116: Mid-week Rate 1 | AC116: Mid-week Rate 1
Q117: Mid-week Rate 2 | U117: Mid-week Rate 2 | Y117: Mid-week Rate 2 | AC117: Mid-week Rate 2
Q118: Weekend Rate 1 | U118: Weekend Rate 1 | Y118: Weekend Rate 1 | AC118: Weekend Rate 1
...

Sheet Occ. Proj
B2: Occupancy Indicators | C2: Low | D2: Peak | E2: Avg.
B3: Sage Dataset Cabins | E3: =GETPIVOTDATA("Average of Occupancy rate 2024",'Unit Type #1 Data'!$A$8) -> 0.616
B4: Sage Dataset Treehouses | E4: =GETPIVOTDATA("Average of Occupancy rate 2024",'Unit Type #2 Data'!$A$7) -> 0.56833333
B5: Sage Dataset Domes | E5: =GETPIVOTDATA("Average of Occupancy rate 2024",'Unit Type #3 Data'!$A$7) -> 0.6
B6: Local AirDNA STVR Occupancy | C6: 0.45 | D6: 0.67 | E6: =AVERAGE(C6:D6) -> 0.56
B7: Local Hotel Occupancy | C7: 0.4 | D7: 0.72 | E7: =AVERAGE(C7:D7) -> 0.56
B8: ='Comps Summ.'!I14 -> Bolt Farm Treehouses | C8: ='Comps Summ.'!P14 -> 0.6 | D8: ='Comps Summ.'!Q14 -> 0.95 | E8: =AVERAGE(C8:D8) -> 0.775
B9: ='Comps Summ.'!I18 -> ReTreet Glamping Resort | C9: ='Comps Summ.'!P18 -> 0.75 | D9: ='Comps Summ.'!Q18 -> 0.95 | E9: =AVERAGE(C9:D9) -> 0.85
B10: ='Comps Summ.'!I21 -> ReTreet Glamping Resort | C10: ='Comps Summ.'!P21 -> 0.6 | D10: ='Comps Summ.'!Q21 -> 0.95 | E10: =AVERAGE(C10:D10) -> 0.775
B13: Average | C13: =AVERAGE(C3:C12) -> 0.56 | D13: =AVERAGE(D3:D12) -> 0.848 | E13: =AVERAGE(E3:E12) -> 0.66304167
B14: Subject Projected Standard Rates | C14: 0.45 | D14: 0.8 | E14: =AVERAGE(C14:D14) -> 0.625
H15: Stabilized Occupancy (Year 5) | I15: Low | J15: Peak | K15: Yr 5+ Occupancy (Weighted) | M15: Annual Avg.
H16: # of Months | I16: 4 | J16: 8 | K16: 12 | M16: =K16 -> 12
H17: ='Rates Proj'!L51 -> Mirror Cabin Large | I17: =C14 -> 0.45 | J17: 0.78 | K17: ='Monthly PF'!BU6 -> 0.65016438 | M17: =AVERAGE(I17:J17) -> 0.615
H18: ='Rates Proj'!L52 -> Mirror Cabin Small | I18: =I17 -> 0.45 | J18: 0.85 | K18: ='Monthly PF'!BU11 -> 0.67205479 | M18: =AVERAGE(I18:J18) -> 0.65
H19: ='Rates Proj'!L53 -> Dome Large | I19: =I18 -> 0.45 | J19: 0.78 | K19: ='Monthly PF'!BU16 -> 0.65016438 | M19: =AVERAGE(I19:J19) -> 0.615
H20: ='Rates Proj'!L54 -> Dome Small | I20: =I19 -> 0.45 | J20: 0.85 | K20: ='Monthly PF'!BU21 -> 0.67205479 | M20: =AVERAGE(I20:J20) -> 0.65
H21: ='Rates Proj'!L55 -> Safari Tent Large | I21: =I20 -> 0.45 | J21: 0.8 | K21: ='Monthly PF'!BU26 -> 0.65945205 | M21: =AVERAGE(I21:J21) -> 0.625
H22: ='Rates Proj'!L56 -> Safari Tent Medium | I22: 0.45 | J22: 0.9 | K22: ='Monthly PF'!BU31 -> 0.68054795 | M22: =AVERAGE(I22:J22) -> 0.675
H23: ='ToT (Intake Form)'!C41 -> USE FOR MONTHLY | I23: 0.45 | J23: 0.9 | K23: ='Monthly PF'!BU36 -> 0 | M23: =AVERAGE(I23:J23) -> 0.675
M25: (% of Year 5+ Occupancy) | N25: Year 1 | O25: Year 2 | P25: Year 3 | Q25: Year 4 | R25: Year 5
M26: =H17 -> Mirror Cabin Large | N26: 0.6 | O26: 0.75 | P26: 0.9 | Q26: 0.975 | R26: 1
M27: =H18 -> Mirror Cabin Small | N27: =N26 -> 0.6 | O27: =O26 -> 0.75 | P27: =P26 -> 0.9 | Q27: =Q26 -> 0.975 | R27: =R26 -> 1
M28: =H19 -> Dome Large | N28: =N27 -> 0.6 | O28: =O27 -> 0.75 | P28: =P27 -> 0.9 | Q28: =Q27 -> 0.975 | R28: =R27 -> 1
M29: =H20 -> Dome Small | N29: =N28 -> 0.6 | O29: =O28 -> 0.75 | P29: =P28 -> 0.9 | Q29: =Q28 -> 0.975 | R29: =R28 -> 1
M30: =H21 -> Safari Tent Large | N30: =N29 -> 0.6 | O30: =O29 -> 0.75 | P30: =P29 -> 0.9 | Q30: =Q29 -> 0.975 | R30: =R29 -> 1
M31: =H22 -> Safari Tent Medium | N31: =N30 -> 0.6 | O31: =O30 -> 0.75 | P31: =P30 -> 0.9 | Q31: =Q30 -> 0.975 | R31: =R30 -> 1
M32: ='ToT (Intake Form)'!C41 -> USE FOR MONTHLY | N32: =N31 -> 0.6 | O32: =O31 -> 0.75 | P32: =P31 -> 0.9 | Q32: =Q31 -> 0.975 | R32: =R31 -> 1
M34: Annual Occupancy Projections | N34: Year 1 Occup. | O34: Year 2 Occup. | P34: Year 3 Occup. | Q34: Year 4 Occup. | R34: Year 5+ Occup.
M35: =M26 -> Mirror Cabin Large | N35: ='10 yr PF'!D5 -> 0.39009863 | O35: ='10 yr PF'!E5 -> 0.48762329 | P35: ='10 yr PF'!F5 -> 0.58514795 | Q35: ='10 yr PF'!G5 -> 0.63391027 | R35: ='10 yr PF'!H5 -> 0.65016438
M36: =M27 -> Mirror Cabin Small | N36: ='10 yr PF'!D10 -> 0.40323288 | O36: ='10 yr PF'!E10 -> 0.5040411 | P36: ='10 yr PF'!F10 -> 0.60484932 | Q36: ='10 yr PF'!G10 -> 0.65525342 | R36: ='10 yr PF'!H10 -> 0.67205479
M37: =M28 -> Dome Large | N37: ='10 yr PF'!D15 -> 0.39009863 | O37: ='10 yr PF'!E15 -> 0.48762329 | P37: ='10 yr PF'!F15 -> 0.58514795 | Q37: ='10 yr PF'!G15 -> 0.63391027 | R37: ='10 yr PF'!H15 -> 0.65016438
M38: =M29 -> Dome Small | N38: ='10 yr PF'!D20 -> 0.40323288 | O38: ='10 yr PF'!E20 -> 0.5040411 | P38: ='10 yr PF'!F20 -> 0.60484932 | Q38: ='10 yr PF'!G20 -> 0.65525342 | R38: ='10 yr PF'!H20 -> 0.67205479
M39: =M30 -> Safari Tent Large | N39: ='10 yr PF'!D25 -> 0.39567123 | O39: ='10 yr PF'!E25 -> 0.49458904 | P39: ='10 yr PF'!F25 -> 0.59350685 | Q39: ='10 yr PF'!G25 -> 0.64296575 | R39: ='10 yr PF'!H25 -> 0.65945205
M40: =M31 -> Safari Tent Medium | N40: ='10 yr PF'!D30 -> 0.40832877 | O40: ='10 yr PF'!E30 -> 0.51041096 | P40: ='10 yr PF'!F30 -> 0.61249315 | Q40: ='10 yr PF'!G30 -> 0.66353425 | R40: ='10 yr PF'!H30 -> 0.68054795
M41: =M32 -> USE FOR MONTHLY | N41: ='10 yr PF'!D35 -> 0 | O41: ='10 yr PF'!E35 -> 0 | P41: ='10 yr PF'!F35 -> 0 | Q41: ='10 yr PF'!G35 -> 0 | R41: ='10 yr PF'!H35 -> 0

Sheet REV. PRO., TAX, EXP, PRO FORMA
A1: REV. PROJECTION, TAXES, EXPENSES, PRO FORMA (REFERENCE & TRAINING) | D1: ↓ ADDITIONAL INSTRUCTIONS / STEPS / INFO BELOW ↓ | E1: YOUR PROJECT NOTES (For Sections on Left):
A2: Revenue Projection
B3: Lodging and/or RV Site Revenue
B5: Miscellaneous Revenue
B7: Revenue Portion of 10 Year Pro Forma Table
A9: Operating Expenses
B10: Expense Section of 10 Year Pro Forma & Its Components
B12: Staffing Quantity
B13: Example AI / Chat GPT / Google Search and Summary Prompt (Copy & Paste):
C14: What would you recommend for number and type of staffing for this [TYPE QUALITY LEVEL AND NEWNESS] resort in [LOCATION: CITY, STATE], with [TYPE # RV SITES & / OR GLAMPING UNITS], and the additional structures and amenities [PASTE IN ADDL. BUILDINGS / AMENETIES LIST & OTHER DETAILS NEEDED] for management, full-time staff, and peak season part-time staff? Cite your sources, findings, and methods.
B16: Payroll / Payroll Taxes
B17: Example Chat GPT Search and Summary Prompt (Copy & Paste):
C18: What is the minimum wage in [TYPE STATE]? And what is the average wage for [TYPE STAFF POSITION] in [TYPE CITY, STATE OF SUBJECT]? Please cite your findings.
B20: General / Administrative / Credit Card Fees / Repairs & Maint.
B22: Utilities & Reference / Wi-Fi
B23: Example Chat GPT Search and Summary Prompt (Copy & Paste):
C24: What is the average cost of [ENTER UTILITY TYPE] for a home in [TYPE CITY, STATE OF SUBJECT]? Please cite your findings.
B26: Real Estate / Property Taxes
B27: Previous Year's Taxes Paid & Assessor's Market Value for Subject Property
B28: Example Chat GPT Search and Summary Prompt (Copy & Paste):
C29: Please perform an exhaustive search and provide any and all information and resources on what the taxes were, and methodology for calculating them, in the last completed fiscal year for [TYPE SUBJECT ADDRESS, TYPE PARCEL #, TYPE SUBJECT CITY/TOWN/DESIGNATED PLACE, TYPE COUNTY, TYPE STATE, TYPE TYPE OWNER NAME IF KNOWN]. Please cite your findings.
B31: Current Year / Future Tax Calculation Information for FS Projection of Subject Development
B32: Example Chat GPT Search and Summary Prompt (Copy & Paste):
C33: Please perform an exhaustive search and provide any and all information, resources, or webstes regarding taxes and methodology for calculating them including percentages and mill levy rates for the current or previous fiscal year, that are applied both for commercial and personal property tax, in [TYPE SUBJECT CITY/TOWN/DESIGNATED PLACE, TYPE COUNTY, TYPE STATE]. Please cite your findings.
B35: Personal Property Tax (For More Information - if initial Chat GPT ? did not provide all info)
B36: Example Chat GPT Search and Summary Prompt (Copy & Paste):
C37: Does [TYPE COUNTY OF SUBJECT] tax personal property, and if so, what all is considered personal property, and at what rate do they tax the owner?
B41: Insurance (If client has quotes, then use that)
B45: Reserves for Replacement

Sheet RE Taxes
B2: Estimated Property Taxes As Complete | D2: *This is laid out in a typical RE tax approach, but this will vary project to project and might need to re-do once speaking with the local assessor.
B3: Acquisition Cost / Land Cost | C3: ='ToT (Intake Form)'!C58 -> 2174415.9 | E3: <--- Utilize the highest dollar amount of: either the Assessor's Market Value, OR the Client's stated Acquisition Cost / Land Cost from the Table Of Totals (TOT).
B4: Total Hard Development Cost | C4: ='Total Proj. Cost'!D7 -> 10371826
B6: Post Development Total Assessed Value | C6: =C3+C4 -> 12546242
B7: Assessment Ratio | C7: 0.5 | E7: <--- Call Assessor to get current assessment ratio. Also, the assessment ratio may change after development, please find out.
B8: Projected Assessed Value | C8: =C7*C6 -> 6273121.2
B9: Projected Tax Rate / Mill Levy | C9: 0.0498462 | E9: <--- Obtain the most recent property tax bill or call the assessor or treasurer
B10: Post Dev. Annual RE Tax Proj. | C10: =C9*C8 -> 312691.25
B11: Personal Property Value | C11: 0 | E11: <--- Call Assessor to find out if personal property is taxed. Ask if an assessment ratio is applied and verify the tax rate. In most cases, the assessment ratio for personal property and the tax rate are the same as the real estate assessment ratio and tax rate.
B12: Personal Property Assessment Ratio | C12: 1 | E12: <--- Call Assessor to get current assessment ratio. Also, the assessment ratio may change after development, please find out.
B13: Projected Assessed Personal Property Value | C13: =C11*C12 -> 0 | E13: <---- Make sure glamping units / cabins / Park Models are handled appropriately! Depending on their type the assessor may or may not treat them as personal property.
B14: Projected Tax Rate / Mill Levy (Pers. Property) | C14: 0.0498462 | E14: <--- Obtain the most recent property tax bill or call the assessor or treasurer
B15: Post Dev. Annual Personal Property Tax Proj. | C15: =C13*C14 -> 0 | E15: <--- Call Assessor to find out if personal property is taxed
B16: Rollback Penalty | C16: 0 | E16: <--- Call Assessor, find out if there is any rollback penalty with change of Ag to Commercial zoning (If no rollback, then enter Zero and hide row)
B17: Total Projected Property Taxes (Year 2) | C17: =C10+C15+C16 -> 312691.25 | E17: *If there is a Rollback Penalty, ask the assessor to calculate it for you.
B19: If as complete taxes seem excessive then try the Tax Comps Sheet
F20: Item # | G20: Parcel No. | H20: 2024 Assessed Value | I20: Most Recent Tax Rate | J20: 2024 Taxes
F21: 1 | G21: 20-1-5 | H21: 15944 | I21: =J21/H21 -> 0.075159935 | J21: 1198.35
F22: 2 | G22: 24-1-8 | H22: 22061 | I22: =J22/H22 -> 0.075159784 | J22: 1658.1
F23: 3 | G23: 0
F24: 4 | G24: 0
F25: 5 | G25: 0
F26: 6 | G26: 0
F27: 7 | G27: 0 | L27: <--- Zero out and Hide any extra / unused parcel rows
F28: 8 | G28: 0
F29: 9 | G29: 0
F30: 10 | G30: 0
G32: Total / Average (Year 1) | H32: =SUM(H21:H30) -> 38005 | I32: =J32/H32 -> 0.075159847 | J32: =SUM(J21:J30) -> 2856.45

Sheet Misc. Expenses
B2: Estimated Payroll Costs | C2: Quantity | D2: Annual Pay Each
B3: State Minimum Wage | D3: 13.85 | F3: Insert that state or city's minimum wage here | G3: Insert that state or city's minimum wage here
B4: Talent Premium Needed | D4: 1.3 | F4: Google local job postings for similar jobs rv parks, hotel staff, (even fast food if there is nothing else). Adjust the talent premium above until expected wage matches the local wages. | G4: Google local job postings for similar jobs rv parks, hotel staff, (even fast food if there is nothing else). Adjust the talent premium above until expected wage matches the local wages.
B5: Expected Pay Wage Needed | D5: =D3*D4 -> 18.005
B6: Front Desk / Guest / Support Staff | C6: 3 | D6: =D5*40*52 -> 37450.4 | F6: Depends on the number of units and adjust up if lots of services and amenities that require staff. 10 employees for a standard RV resort with 150 sites and average amenity package. Adjust down if mostly monthly sites. Adjust up if lots of amenities that require staff. | G6: Depends on the number of units and adjust up if lots of services and amenities that require staff. 10 employees for a standard RV resort with 150 sites and average amenity package. Adjust down if mostly monthly sites. Adjust up if lots of amenities that require staff.
B7: Peak Season Support Staff | C7: 2 | D7: =D5*40*36 -> 25927.2 | F7: Look at the occupancy swings throughout the year. If they are 90% full in the summer and 30% full in the winter expect that about a third of staff will be seasonal. | G7: Look at the occupancy swings throughout the year. If they are 90% full in the summer and 30% full in the winter expect that about a third of staff will be seasonal.
B8: Full Time Manager Salary | C8: 1 | D8: 80000 | F8: $80,000 is standard amount for an average 150 site park. If it is a luxury park with lots of amenities and 250+ sites this might be $150,000. Look at salaries of local campground or hotel manager job postings to check this amount. If there is on site manager housing provided this might be $10K less. | G8: $80,000 is standard amount for an average 150 site park. If it is a luxury park with lots of amenities and 250+ sites this might be $150,000. Look at salaries of local campground or hotel manager job postings to check this amount. If there is on site manager housing provided this might be $10K less.
B9: Total Staffing Wage Pay | D9: =C6*D6+C7*D7+C8*D8 -> 244205.6
B10: Cost of Employment | C10: 0.35 | D10: =D9*C10 -> 85471.96 | F10: Adjust to 30% if employment costs are lower in the state. | G10: Adjust to 30% if employment costs are lower in the state.
B11: Subtotal | D11: =D9+D10 -> 329677.56
B12: Total Payroll Costs (Year 5)* | D12: =D11*(1+'Monthly PF'!C62)^4 -> 363902.34
B13: * Grown for inflation
G14: Room Turnover Service & Linens
G15: Time to Clean Unit (hrs) | H15: 1 | I15: This will typically be 1. Only increase to 1.5 if it is a 2BR unit and 2.0 if a 3 BR unit.
G16: Housekeeping Staff Hourly Rate | H16: =D5+1 -> 19.005
G17: Cost of Employment @35% | H17: =H16*(1+C10) -> 25.65675 | I17: Check to Make Sure Cost of Employment Matches
G18: Staff Cost Per Room Turnover | H18: =H17*H15 -> 25.65675
G19: Linens cost per Room Turnover | H19: 8
G20: Total Cost to Clean and Launder per Booking | H20: =H18+H19 -> 33.65675
G21: Year 5 Site Nights | H21: ='10 yr PF'!Q3 -> 9399.3
G22: Estimated Avg. Days per Booking | H22: 2.5
G23: Annual Room Turnovers Needed | H23: =H21/H22 -> 3759.72
G24: Subtotal | H24: =H23*H20 -> 126539.96
G25: Total Room Turnover Service Cost (Year 5)* | H25: =H23*(H20*(1+'Monthly PF'!C62)^4) -> 139676.43 | J25: Utility Cost
G26: * Grown for inflation | J26: Average Local Monthly Electricity Cost | K26: 150 | L26: Energy Sage | M26: Lookup average local household utility costs and add it here. Cite source in report.
J27: Monthly Electricity Cost p. Site | K27: =0.75*K26 -> 112.5 | M27: This number is expected to be smaller as a glamping unit is expected to be smaller than an average residential house.
J28: Monthly Wi-Fi Cost p. Site | K28: 50
J29: Monthly Trash, Water, Sewage Cost p. Site | K29: 50 | M29: This number assumes they are connected to municipal water and sewer. This will be less if the site is on well water and has a septic/sewage treatment facility on site.
J30: Monthly Utility Cost p. Site | K30: =SUM(K27:K29) -> 212.5
J31: Annual Utility Cost p. Site | K31: =K30*12 -> 2550
J32: Number of Nightly Sites | K32: =SUM('ToT (Intake Form)'!C24,'ToT (Intake Form)'!C27,'ToT (Intake Form)'!C30,'ToT (Intake Form)'!C33,'ToT (Intake Form)'!C36,'ToT (Intake Form)'!C39) -> 39
J33: All Sites Annual Utility Cost | K33: =K31*K32 -> 99450
J34: Weighted Occupancy (Excluding Monthly) | K34: ='Monthly PF'!BU88 -> 0.66029505 | M34: If you do not have monthly sites, then you will need to change this to cell BU87 in the Monthly PF
J35: All Sites Annual Utility Cost (with usage) | K35: =K33*K34 -> 65666.342
J36: Other Buildings Annual Utility Cost | K36: 4000 | M36: Not sure of the best way to estimate this. Want Utility costs to be between 4-10%
J37: Subtotal | K37: =K35+K36 -> 69666.342
J38: Total Annual Utility Cost (Year 5) | K38: =K37*(1+'Monthly PF'!C62)^4 -> 76898.607
J39: * Grown for inflation

Sheet Monthly PF
B2: Assumptions | D2: INCOME | E2: Jan | F2: Feb | G2: March | H2: Apr | I2: May | J2: Jun | K2: July | L2: Aug | M2: Sep | N2: Oct | O2: Nov | P2: Dec | Q2: Year 1 | R2: INCOME | S2: Jan | T2: Feb | U2: March | V2: Apr | W2: May | X2: Jun | Y2: July | Z2: Aug | AA2: Sep | AB2: Oct | AC2: Nov | AD2: Dec | AE2: Year 2 | AF2: INCOME | AG2: Jan | AH2: Feb | AI2: March | AJ2: Apr | AK2: May | AL2: Jun | AM2: July | AN2: Aug | AO2: Sep | AP2: Oct | AQ2: Nov | AR2: Dec | AS2: Year 3 | AT2: INCOME | AU2: Jan | AV2: Feb | AW2: March | AX2: Apr | AY2: May | AZ2: Jun | BA2: July | BB2: Aug | BC2: Sep | BD2: Oct | BE2: Nov | BF2: Dec | BG2: Year 4 | BH2: INCOME | BI2: Jan | BJ2: Feb | BK2: March | BL2: Apr | BM2: May | BN2: Jun | BO2: July | BP2: Aug | BQ2: Sep | BR2: Oct | BS2: Nov | BT2: Dec | BU2: Year 5 | BV2: INCOME
B3: ADR YoY Growth Rate | C3: 0.03 | D3: Days | E3: 31 | F3: 28 | G3: 31 | H3: 30 | I3: 31 | J3: 30 | K3: 31 | L3: 31 | M3: 30 | N3: 31 | O3: 30 | P3: 31 | Q3: =SUM(E3:P3) -> 365 | R3: Days | S3: 31 | T3: 28 | U3: 31 | V3: 30 | W3: 31 | X3: 30 | Y3: 31 | Z3: 31 | AA3: 30 | AB3: 31 | AC3: 30 | AD3: 31 | AE3: =SUM(S3:AD3) -> 365 | AF3: Days | AG3: 31 | AH3: 28 | AI3: 31 | AJ3: 30 | AK3: 31 | AL3: 30 | AM3: 31 | AN3: 31 | AO3: 30 | AP3: 31 | AQ3: 30 | AR3: 31 | AS3: =SUM(AG3:AR3) -> 365 | AT3: Days | AU3: 31 | AV3: 28 | AW3: 31 | AX3: 30 | AY3: 31 | AZ3: 30 | BA3: 31 | BB3: 31 | BC3: 30 | BD3: 31 | BE3: 30 | BF3: 31 | BG3: =SUM(AU3:BF3) -> 365 | BH3: Days | BI3: 31 | BJ3: 28 | BK3: 31 | BL3: 30 | BM3: 31 | BN3: 30 | BO3: 31 | BP3: 31 | BQ3: 30 | BR3: 31 | BS3: 30 | BT3: 31 | BU3: =SUM(BI3:BT3) -> 365
B4: STABILIZATION SCHEDULE - % OF STABILIZED: | D4: ='ToT (Intake Form)'!C23 -> Mirror Cabin Large | E4: ='ToT (Intake Form)'!C24 -> 15 | F4: =E4 -> 15 | G4: =F4 -> 15 | H4: =G4 -> 15 | I4: =H4 -> 15 | J4: =I4 -> 15 | K4: =J4 -> 15 | L4: =K4 -> 15 | M4: =L4 -> 15 | ... P4: =O4 -> 15 | Q4: =AVERAGE(E4:P4) -> 15 | R4: =$D4 -> Mirror Cabin Large | S4: =Q4 -> 15 | T4: =S4 -> 15 | U4: =T4 -> 15 | V4: =U4 -> 15 | W4: =V4 -> 15 | X4: =W4 -> 15 | Y4: =X4 -> 15 | Z4: =Y4 -> 15 | AA4: =Z4 -> 15 | ... AD4: =AC4 -> 15 | AE4: =AVERAGE(S4:AD4) -> 15 | AF4: =$D4 -> Mirror Cabin Large | AG4: =AE4 -> 15 | AH4: =AG4 -> 15 | AI4: =AH4 -> 15 | AJ4: =AI4 -> 15 | AK4: =AJ4 -> 15 | AL4: =AK4 -> 15 | AM4: =AL4 -> 15 | AN4: =AM4 -> 15 | AO4: =AN4 -> 15 | ... AR4: =AQ4 -> 15 | AS4: =AVERAGE(AG4:AR4) -> 15 | AT4: =$D4 -> Mirror Cabin Large | AU4: =AS4 -> 15 | AV4: =AU4 -> 15 | AW4: =AV4 -> 15 | AX4: =AW4 -> 15 | AY4: =AX4 -> 15 | AZ4: =AY4 -> 15 | BA4: =AZ4 -> 15 | BB4: =BA4 -> 15 | BC4: =BB4 -> 15 | ... BF4: =BE4 -> 15 | BG4: =AVERAGE(AU4:BF4) -> 15 | BH4: =$D4 -> Mirror Cabin Large | BI4: =BF4 -> 15 | BJ4: =BI4 -> 15 | BK4: =BJ4 -> 15 | BL4: =BK4 -> 15 | BM4: =BL4 -> 15 | BN4: =BM4 -> 15 | BO4: =BN4 -> 15 | BP4: =BO4 -> 15 | BQ4: =BP4 -> 15 | ... BT4: =BS4 -> 15 | BU4: =AVERAGE(BI4:BT4) -> 15 | BV4: =D4 -> Mirror Cabin Large
B5: Year 1 % Occupancy | C5: ='Occ. Proj'!N26 -> 0.6 | D5: ADR | E5: ='Rates Proj'!M51 -> 250 | F5: =E5 -> 250 | G5: =F5 -> 250 | H5: 275 | I5: 300 | J5: ='Rates Proj'!N51 -> 350 | K5: =J5 -> 350 | L5: =K5 -> 350 | M5: 300 | N5: 300 | O5: =E5 -> 250 | P5: =O5 -> 250 | Q5: =IFERROR(Q8/Q7,0) -> 296.66259 | R5: ADR | S5: =E5*(1+$C$3) -> 257.5 | T5: =F5*(1+$C$3) -> 257.5 | U5: =G5*(1+$C$3) -> 257.5 | V5: =H5*(1+$C$3) -> 283.25 | W5: =I5*(1+$C$3) -> 309 | X5: =J5*(1+$C$3) -> 360.5 | Y5: =K5*(1+$C$3) -> 360.5 | Z5: =L5*(1+$C$3) -> 360.5 | ... AD5: =P5*(1+$C$3) -> 257.5 | AE5: =IFERROR(AE8/AE7,0) -> 305.56247 | AF5: ADR | AG5: =S5*(1+$C$3) -> 265.225 | AH5: =T5*(1+$C$3) -> 265.225 | AI5: =U5*(1+$C$3) -> 265.225 | AJ5: =V5*(1+$C$3) -> 291.7475 | AK5: =W5*(1+$C$3) -> 318.27 | AL5: =X5*(1+$C$3) -> 371.315 | AM5: =Y5*(1+$C$3) -> 371.315 | AN5: =Z5*(1+$C$3) -> 371.315 | ... AR5: =AD5*(1+$C$3) -> 265.225 | AS5: =IFERROR(AS8/AS7,0) -> 314.72935 | AT5: ADR | AU5: =AG5*(1+$C$3) -> 273.18175 | AV5: =AH5*(1+$C$3) -> 273.18175 | AW5: =AI5*(1+$C$3) -> 273.18175 | AX5: =AJ5*(1+$C$3) -> 300.49993 | AY5: =AK5*(1+$C$3) -> 327.8181 | AZ5: =AL5*(1+$C$3) -> 382.45445 | BA5: =AM5*(1+$C$3) -> 382.45445 | BB5: =AN5*(1+$C$3) -> 382.45445 | ... BF5: =AR5*(1+$C$3) -> 273.18175 | BG5: =IFERROR(BG8/BG7,0) -> 324.17123 | BH5: ADR | BI5: =AU5*(1+$C$3) -> 281.3772 | BJ5: =AV5*(1+$C$3) -> 281.3772 | BK5: =AW5*(1+$C$3) -> 281.3772 | BL5: =AX5*(1+$C$3) -> 309.51492 | BM5: =AY5*(1+$C$3) -> 337.65264 | BN5: =AZ5*(1+$C$3) -> 393.92808 | BO5: =BA5*(1+$C$3) -> 393.92808 | BP5: =BB5*(1+$C$3) -> 393.92808 | ... BT5: =BF5*(1+$C$3) -> 281.3772 | BU5: =IFERROR(BU8/BU7,0) -> 333.89636 | BV5: ADR
B6: Year 2 % Occupancy | C6: ='Occ. Proj'!O26 -> 0.75 | D6: Occupancy | E6: =BI6*$C5 -> 0.27 | F6: =BJ6*$C5 -> 0.27 | G6: =BK6*$C5 -> 0.36 | H6: =BL6*$C5 -> 0.42 | I6: =BM6*$C5 -> 0.42 | J6: =BN6*$C5 -> 0.468 | K6: =BO6*$C5 -> 0.468 | L6: =BP6*$C5 -> 0.468 | ... P6: =BT6*$C5 -> 0.27 | Q6: =IFERROR(Q7/(Q4*$Q$3),0) -> 0.39009863 | R6: Occupancy | S6: =BI6*$C6 -> 0.3375 | T6: =BJ6*$C6 -> 0.3375 | U6: =BK6*$C6 -> 0.45 | V6: =BL6*$C6 -> 0.525 | W6: =BM6*$C6 -> 0.525 | X6: =BN6*$C6 -> 0.585 | Y6: =BO6*$C6 -> 0.585 | Z6: =BP6*$C6 -> 0.585 | ... AD6: =BT6*$C6 -> 0.3375 | AE6: =IFERROR(AE7/(AE4*$Q$3),0) -> 0.48762329 | AF6: Occupancy | AG6: =BI6*$C7 -> 0.405 | AH6: =BJ6*$C7 -> 0.405 | AI6: =BK6*$C7 -> 0.54 | AJ6: =BL6*$C7 -> 0.63 | AK6: =BM6*$C7 -> 0.63 | AL6: =BN6*$C7 -> 0.702 | AM6: =BO6*$C7 -> 0.702 | AN6: =BP6*$C7 -> 0.702 | ... AR6: =BT6*$C7 -> 0.405 | AS6: =IFERROR(AS7/(AS4*$Q$3),0) -> 0.58514795 | AT6: Occupancy | AU6: =BI6*$C8 -> 0.43875 | AV6: =BJ6*$C8 -> 0.43875 | AW6: =BK6*$C8 -> 0.585 | AX6: =BL6*$C8 -> 0.6825 | AY6: =BM6*$C8 -> 0.6825 | AZ6: =BN6*$C8 -> 0.7605 | BA6: =BO6*$C8 -> 0.7605 | BB6: =BP6*$C8 -> 0.7605 | ... BF6: =BT6*$C8 -> 0.43875 | BG6: =IFERROR(BG7/(BG4*$Q$3),0) -> 0.63391027 | BH6: Occupancy | BI6: ='Occ. Proj'!$I$17 -> 0.45 | BJ6: ='Occ. Proj'!$I$17 -> 0.45 | BK6: 0.6 | BL6: 0.7 | BM6: 0.7 | BN6: ='Occ. Proj'!$J$17 -> 0.78 | BO6: ='Occ. Proj'!$J$17 -> 0.78 | BP6: ='Occ. Proj'!$J$17 -> 0.78 | BQ6: 0.75 | BR6: 0.75 | BS6: 0.6 | BT6: =BI6 -> 0.45 | BU6: =IFERROR(BU7/(BU4*$Q$3),0) -> 0.65016438 | BV6: Occupancy
B7: Year 3 % Occupancy | C7: ='Occ. Proj'!P26 -> 0.9 | D7: Site Nights | E7: =E6*E3*E4 -> 125.55 | F7: =F6*F3*F4 -> 113.4 | G7: =G6*G3*G4 -> 167.4 | H7: =H6*H3*H4 -> 189 | I7: =I6*I3*I4 -> 195.3 | J7: =J6*J3*J4 -> 210.6 | K7: =K6*K3*K4 -> 217.62 | L7: =L6*L3*L4 -> 217.62 | ... P7: =P6*P3*P4 -> 125.55 | Q7: =SUM(E7:P7) -> 2135.79 | R7: Site Nights | S7: =S6*S3*S4 -> 156.9375 | T7: =T6*T3*T4 -> 141.75 | U7: =U6*U3*U4 -> 209.25 | V7: =V6*V3*V4 -> 236.25 | W7: =W6*W3*W4 -> 244.125 | X7: =X6*X3*X4 -> 263.25 | Y7: =Y6*Y3*Y4 -> 272.025 | Z7: =Z6*Z3*Z4 -> 272.025 | ... AD7: =AD6*AD3*AD4 -> 156.9375 | AE7: =SUM(S7:AD7) -> 2669.7375 | AF7: Site Nights | AG7: =AG6*AG3*AG4 -> 188.325 | AH7: =AH6*AH3*AH4 -> 170.1 | AI7: =AI6*AI3*AI4 -> 251.1 | AJ7: =AJ6*AJ3*AJ4 -> 283.5 | AK7: =AK6*AK3*AK4 -> 292.95 | AL7: =AL6*AL3*AL4 -> 315.9 | AM7: =AM6*AM3*AM4 -> 326.43 | AN7: =AN6*AN3*AN4 -> 326.43 | ... AR7: =AR6*AR3*AR4 -> 188.325 | AS7: =SUM(AG7:AR7) -> 3203.685 | AT7: Site Nights | AU7: =AU6*AU3*AU4 -> 204.01875 | AV7: =AV6*AV3*AV4 -> 184.275 | AW7: =AW6*AW3*AW4 -> 272.025 | AX7: =AX6*AX3*AX4 -> 307.125 | AY7: =AY6*AY3*AY4 -> 317.3625 | AZ7: =AZ6*AZ3*AZ4 -> 342.225 | BA7: =BA6*BA3*BA4 -> 353.6325 | BB7: =BB6*BB3*BB4 -> 353.6325 | ... BF7: =BF6*BF3*BF4 -> 204.01875 | BG7: =SUM(AU7:BF7) -> 3470.6588 | BH7: Site Nights | BI7: =BI6*BI3*BI4 -> 209.25 | BJ7: =BJ6*BJ3*BJ4 -> 189 | BK7: =BK6*BK3*BK4 -> 279 | BL7: =BL6*BL3*BL4 -> 315 | BM7: =BM6*BM3*BM4 -> 325.5 | BN7: =BN6*BN3*BN4 -> 351 | BO7: =BO6*BO3*BO4 -> 362.7 | BP7: =BP6*BP3*BP4 -> 362.7 | ... BT7: =BT6*BT3*BT4 -> 209.25 | BU7: =SUM(BI7:BT7) -> 3559.65 | BV7: Site Nights
B8: Year 4 % Occupancy | C8: ='Occ. Proj'!Q26 -> 0.975 | D8: Revenue | E8: =E5*E7 -> 31387.5 | F8: =F5*F7 -> 28350 | G8: =G5*G7 -> 41850 | H8: =H5*H7 -> 51975 | I8: =I5*I7 -> 58590 | J8: =J5*J7 -> 73710 | K8: =K5*K7 -> 76167 | L8: =L5*L7 -> 76167 | ... P8: =P5*P7 -> 31387.5 | Q8: =SUM(E8:P8) -> 633609 | R8: Revenue | S8: =S5*S7 -> 40411.406 | T8: =T5*T7 -> 36500.625 | U8: =U5*U7 -> 53881.875 | V8: =V5*V7 -> 66917.812 | W8: =W5*W7 -> 75434.625 | X8: =X5*X7 -> 94901.625 | Y8: =Y5*Y7 -> 98065.012 | Z8: =Z5*Z7 -> 98065.012 | ... AD8: =AD5*AD7 -> 40411.406 | AE8: =SUM(S8:AD8) -> 815771.59 | AF8: Revenue | AG8: =AG5*AG7 -> 49948.498 | AH8: =AH5*AH7 -> 45114.772 | AI8: =AI5*AI7 -> 66597.998 | AJ8: =AJ5*AJ7 -> 82710.416 | AK8: =AK5*AK7 -> 93237.197 | AL8: =AL5*AL7 -> 117298.41 | AM8: =AM5*AM7 -> 121208.36 | AN8: =AN5*AN7 -> 121208.36 | ... AR8: =AR5*AR7 -> 49948.498 | AS8: =SUM(AG8:AR8) -> 1008293.7 | AT8: Revenue | AU8: =AU5*AU7 -> 55734.199 | AV8: =AV5*AV7 -> 50340.567 | AW8: =AW5*AW7 -> 74312.266 | AX8: =AX5*AX7 -> 92291.039 | AY8: =AY5*AY7 -> 104037.17 | AZ8: =AZ5*AZ7 -> 130885.47 | BA8: =BA5*BA7 -> 135248.32 | BB8: =BB5*BB7 -> 135248.32 | ... BF8: =BF5*BF7 -> 55734.199 | BG8: =SUM(AU8:BF8) -> 1125087.7 | BH8: Revenue | BI8: =BI5*BI7 -> 58878.18 | BJ8: =BJ5*BJ7 -> 53180.291 | BK8: =BK5*BK7 -> 78504.239 | BL8: =BL5*BL7 -> 97497.201 | BM8: =BM5*BM7 -> 109905.94 | BN8: =BN5*BN7 -> 138268.76 | BO8: =BO5*BO7 -> 142877.72 | BP8: =BP5*BP7 -> 142877.72 | ... BT8: =BT5*BT7 -> 58878.18 | BU8: =SUM(BI8:BT8) -> 1188554.2 | BV8: Revenue
D9: ='ToT (Intake Form)'!C26 -> Mirror Cabin Small | E9: ='ToT (Intake Form)'!C27 -> 10 | F9: =E9 -> 10 | G9: =F9 -> 10 | H9: =G9 -> 10 | I9: =H9 -> 10 | J9: =I9 -> 10 | K9: =J9 -> 10 | L9: =K9 -> 10 | M9: =L9 -> 10 | ... P9: =O9 -> 10 | Q9: =AVERAGE(E9:P9) -> 10 | R9: =$D9 -> Mirror Cabin Small | S9: =Q9 -> 10 | T9: =S9 -> 10 | U9: =T9 -> 10 | V9: =U9 -> 10 | W9: =V9 -> 10 | X9: =W9 -> 10 | Y9: =X9 -> 10 | Z9: =Y9 -> 10 | AA9: =Z9 -> 10 | ... AD9: =AC9 -> 10 | AE9: =AVERAGE(S9:AD9) -> 10 | AF9: =$D9 -> Mirror Cabin Small | AG9: =AE9 -> 10 | AH9: =AG9 -> 10 | AI9: =AH9 -> 10 | AJ9: =AI9 -> 10 | AK9: =AJ9 -> 10 | AL9: =AK9 -> 10 | AM9: =AL9 -> 10 | AN9: =AM9 -> 10 | AO9: =AN9 -> 10 | ... AR9: =AQ9 -> 10 | AS9: =AVERAGE(AG9:AR9) -> 10 | AT9: =$D9 -> Mirror Cabin Small | AU9: =AS9 -> 10 | AV9: =AU9 -> 10 | AW9: =AV9 -> 10 | AX9: =AW9 -> 10 | AY9: =AX9 -> 10 | AZ9: =AY9 -> 10 | BA9: =AZ9 -> 10 | BB9: =BA9 -> 10 | BC9: =BB9 -> 10 | ... BF9: =BE9 -> 10 | BG9: =AVERAGE(AU9:BF9) -> 10 | BH9: =$D9 -> Mirror Cabin Small | BI9: =BF9 -> 10 | BJ9: =BI9 -> 10 | BK9: =BJ9 -> 10 | BL9: =BK9 -> 10 | BM9: =BL9 -> 10 | BN9: =BM9 -> 10 | BO9: =BN9 -> 10 | BP9: =BO9 -> 10 | BQ9: =BP9 -> 10 | ... BT9: =BS9 -> 10 | BU9: =AVERAGE(BI9:BT9) -> 10 | BV9: =D9 -> Mirror Cabin Small
B10: Year 1 % Occupancy | C10: ='Occ. Proj'!N27 -> 0.6 | D10: =D5 -> ADR | E10: ='Rates Proj'!M52 -> 300 | F10: =E10 -> 300 | G10: =F10 -> 300 | H10: 325 | I10: 375 | J10: ='Rates Proj'!N52 -> 400 | K10: =J10 -> 400 | L10: =K10 -> 400 | M10: 375 | N10: 375 | O10: =E10 -> 300 | P10: =O10 -> 300 | Q10: =IFERROR(Q13/Q12,0) -> 355.11618 | R10: =R5 -> ADR | S10: =E10*(1+$C$3) -> 309 | T10: =F10*(1+$C$3) -> 309 | U10: =G10*(1+$C$3) -> 309 | V10: =H10*(1+$C$3) -> 334.75 | W10: =I10*(1+$C$3) -> 386.25 | X10: =J10*(1+$C$3) -> 412 | Y10: =K10*(1+$C$3) -> 412 | Z10: =L10*(1+$C$3) -> 412 | ... AD10: =P10*(1+$C$3) -> 309 | AE10: =IFERROR(AE13/AE12,0) -> 365.76967 | AF10: =AF5 -> ADR | AG10: =S10*(1+$C$3) -> 318.27 | AH10: =T10*(1+$C$3) -> 318.27 | AI10: =U10*(1+$C$3) -> 318.27 | AJ10: =V10*(1+$C$3) -> 344.7925 | AK10: =W10*(1+$C$3) -> 397.8375 | AL10: =X10*(1+$C$3) -> 424.36 | AM10: =Y10*(1+$C$3) -> 424.36 | AN10: =Z10*(1+$C$3) -> 424.36 | ... AR10: =AD10*(1+$C$3) -> 318.27 | AS10: =IFERROR(AS13/AS12,0) -> 376.74276 | AT10: =AT5 -> ADR | AU10: =AG10*(1+$C$3) -> 327.8181 | AV10: =AH10*(1+$C$3) -> 327.8181 | AW10: =AI10*(1+$C$3) -> 327.8181 | AX10: =AJ10*(1+$C$3) -> 355.13628 | AY10: =AK10*(1+$C$3) -> 409.77263 | AZ10: =AL10*(1+$C$3) -> 437.0908 | BA10: =AM10*(1+$C$3) -> 437.0908 | BB10: =AN10*(1+$C$3) -> 437.0908 | ... BF10: =AR10*(1+$C$3) -> 327.8181 | BG10: =IFERROR(BG13/BG12,0) -> 388.04504 | BH10: =BH5 -> ADR | BI10: =AU10*(1+$C$3) -> 337.65264 | BJ10: =AV10*(1+$C$3) -> 337.65264 | BK10: =AW10*(1+$C$3) -> 337.65264 | BL10: =AX10*(1+$C$3) -> 365.79036 | BM10: =AY10*(1+$C$3) -> 422.0658 | BN10: =AZ10*(1+$C$3) -> 450.20352 | BO10: =BA10*(1+$C$3) -> 450.20352 | BP10: =BB10*(1+$C$3) -> 450.20352 | ... BT10: =BF10*(1+$C$3) -> 337.65264 | BU10: =IFERROR(BU13/BU12,0) -> 399.68639 | BV10: =BV5 -> ADR
B11: Year 2 % Occupancy | C11: ='Occ. Proj'!O27 -> 0.75 | D11: =D6 -> Occupancy | E11: =BI11*$C10 -> 0.27 | F11: =BJ11*$C10 -> 0.27 | G11: =BK11*$C10 -> 0.36 | H11: =BL11*$C10 -> 0.42 | I11: =BM11*$C10 -> 0.45 | J11: =BN11*$C10 -> 0.51 | K11: =BO11*$C10 -> 0.51 | L11: =BP11*$C10 -> 0.51 | ... P11: =BT11*$C10 -> 0.27 | Q11: =IFERROR(Q12/(Q9*$Q$3),0) -> 0.40323288 | R11: =R6 -> Occupancy | S11: =BI11*$C11 -> 0.3375 | T11: =BJ11*$C11 -> 0.3375 | U11: =BK11*$C11 -> 0.45 | V11: =BL11*$C11 -> 0.525 | W11: =BM11*$C11 -> 0.5625 | X11: =BN11*$C11 -> 0.6375 | Y11: =BO11*$C11 -> 0.6375 | Z11: =BP11*$C11 -> 0.6375 | ... AD11: =BT11*$C11 -> 0.3375 | AE11: =IFERROR(AE12/(AE9*$Q$3),0) -> 0.5040411 | AF11: =AF6 -> Occupancy | AG11: =BI11*$C12 -> 0.405 | AH11: =BJ11*$C12 -> 0.405 | AI11: =BK11*$C12 -> 0.54 | AJ11: =BL11*$C12 -> 0.63 | AK11: =BM11*$C12 -> 0.675 | AL11: =BN11*$C12 -> 0.765 | AM11: =BO11*$C12 -> 0.765 | AN11: =BP11*$C12 -> 0.765 | ... AR11: =BT11*$C12 -> 0.405 | AS11: =IFERROR(AS12/(AS9*$Q$3),0) -> 0.60484932 | AT11: =AT6 -> Occupancy | AU11: =BI11*$C13 -> 0.43875 | AV11: =BJ11*$C13 -> 0.43875 | AW11: =BK11*$C13 -> 0.585 | AX11: =BL11*$C13 -> 0.6825 | AY11: =BM11*$C13 -> 0.73125 | AZ11: =BN11*$C13 -> 0.82875 | BA11: =BO11*$C13 -> 0.82875 | BB11: =BP11*$C13 -> 0.82875 | ... BF11: =BT11*$C13 -> 0.43875 | BG11: =IFERROR(BG12/(BG9*$Q$3),0) -> 0.65525342 | BH11: =BH6 -> Occupancy | BI11: ='Occ. Proj'!$I$18 -> 0.45 | BJ11: ='Occ. Proj'!$I$18 -> 0.45 | BK11: =BK6 -> 0.6 | BL11: =BL6 -> 0.7 | BM11: 0.75 | BN11: ='Occ. Proj'!$J$18 -> 0.85 | BO11: ='Occ. Proj'!$J$18 -> 0.85 | BP11: ='Occ. Proj'!$J$18 -> 0.85 | BQ11: =BQ6 -> 0.75 | BR11: =BR6 -> 0.75 | BS11: 0.6 | BT11: =BI11 -> 0.45 | BU11: =IFERROR(BU12/(BU9*$Q$3),0) -> 0.67205479 | BV11: =BV6 -> Occupancy
B12: Year 3 % Occupancy | C12: ='Occ. Proj'!P27 -> 0.9 | D12: =D7 -> Site Nights | E12: =E11*E3*E9 -> 83.7 | F12: =F11*F3*F9 -> 75.6 | G12: =G11*G3*G9 -> 111.6 | H12: =H11*H3*H9 -> 126 | I12: =I11*I3*I9 -> 139.5 | J12: =J11*J3*J9 -> 153 | K12: =K11*K3*K9 -> 158.1 | L12: =L11*L3*L9 -> 158.1 | ... P12: =P11*P3*P9 -> 83.7 | Q12: =SUM(E12:P12) -> 1471.8 | R12: =R7 -> Site Nights | S12: =S11*S3*S9 -> 104.625 | T12: =T11*T3*T9 -> 94.5 | U12: =U11*U3*U9 -> 139.5 | V12: =V11*V3*V9 -> 157.5 | W12: =W11*W3*W9 -> 174.375 | X12: =X11*X3*X9 -> 191.25 | Y12: =Y11*Y3*Y9 -> 197.625 | Z12: =Z11*Z3*Z9 -> 197.625 | ... AD12: =AD11*AD3*AD9 -> 104.625 | AE12: =SUM(S12:AD12) -> 1839.75 | AF12: =AF7 -> Site Nights | AG12: =AG11*AG3*AG9 -> 125.55 | AH12: =AH11*AH3*AH9 -> 113.4 | AI12: =AI11*AI3*AI9 -> 167.4 | AJ12: =AJ11*AJ3*AJ9 -> 189 | AK12: =AK11*AK3*AK9 -> 209.25 | AL12: =AL11*AL3*AL9 -> 229.5 | AM12: =AM11*AM3*AM9 -> 237.15 | AN12: =AN11*AN3*AN9 -> 237.15 | ... AR12: =AR11*AR3*AR9 -> 125.55 | AS12: =SUM(AG12:AR12) -> 2207.7 | AT12: =AT7 -> Site Nights | AU12: =AU11*AU3*AU9 -> 136.0125 | AV12: =AV11*AV3*AV9 -> 122.85 | AW12: =AW11*AW3*AW9 -> 181.35 | AX12: =AX11*AX3*AX9 -> 204.75 | AY12: =AY11*AY3*AY9 -> 226.6875 | AZ12: =AZ11*AZ3*AZ9 -> 248.625 | BA12: =BA11*BA3*BA9 -> 256.9125 | BB12: =BB11*BB3*BB9 -> 256.9125 | ... BF12: =BF11*BF3*BF9 -> 136.0125 | BG12: =SUM(AU12:BF12) -> 2391.675 | BH12: =BH7 -> Site Nights | BI12: =BI11*BI3*BI9 -> 139.5 | BJ12: =BJ11*BJ3*BJ9 -> 126 | BK12: =BK11*BK3*BK9 -> 186 | BL12: =BL11*BL3*BL9 -> 210 | BM12: =BM11*BM3*BM9 -> 232.5 | BN12: =BN11*BN3*BN9 -> 255 | BO12: =BO11*BO3*BO9 -> 263.5 | BP12: =BP11*BP3*BP9 -> 263.5 | ... BT12: =BT11*BT3*BT9 -> 139.5 | BU12: =SUM(BI12:BT12) -> 2453 | BV12: =BV7 -> Site Nights
B13: Year 4 % Occupancy | C13: ='Occ. Proj'!Q27 -> 0.975 | D13: =D8 -> Revenue | E13: =E10*E12 -> 25110 | F13: =F10*F12 -> 22680 | G13: =G10*G12 -> 33480 | H13: =H10*H12 -> 40950 | I13: =I10*I12 -> 52312.5 | J13: =J10*J12 -> 61200 | K13: =K10*K12 -> 63240 | L13: =L10*L12 -> 63240 | ... P13: =P10*P12 -> 25110 | Q13: =SUM(E13:P13) -> 522660 | R13: =R8 -> Revenue | S13: =S10*S12 -> 32329.125 | T13: =T10*T12 -> 29200.5 | U13: =U10*U12 -> 43105.5 | V13: =V10*V12 -> 52723.125 | W13: =W10*W12 -> 67352.344 | X13: =X10*X12 -> 78795 | Y13: =Y10*Y12 -> 81421.5 | Z13: =Z10*Z12 -> 81421.5 | ... AD13: =AD10*AD12 -> 32329.125 | AE13: =SUM(S13:AD13) -> 672924.75 | AF13: =AF8 -> Revenue | AG13: =AG10*AG12 -> 39958.799 | AH13: =AH10*AH12 -> 36091.818 | AI13: =AI10*AI12 -> 53278.398 | AJ13: =AJ10*AJ12 -> 65165.783 | AK13: =AK10*AK12 -> 83247.497 | AL13: =AL10*AL12 -> 97390.62 | AM13: =AM10*AM12 -> 100636.97 | AN13: =AN10*AN12 -> 100636.97 | ... AR13: =AR10*AR12 -> 39958.799 | AS13: =SUM(AG13:AR13) -> 831734.99 | AT13: =AT8 -> Revenue | AU13: =AU10*AU12 -> 44587.359 | AV13: =AV10*AV12 -> 40272.454 | AW13: =AW10*AW12 -> 59449.812 | AX13: =AX10*AX12 -> 72714.152 | AY13: =AY10*AY12 -> 92890.332 | AZ13: =AZ10*AZ12 -> 108671.7 | BA13: =BA10*BA12 -> 112294.09 | BB13: =BB10*BB12 -> 112294.09 | ... BF13: =BF10*BF12 -> 44587.359 | BG13: =SUM(AU13:BF13) -> 928077.63 | BH13: =BH8 -> Revenue | BI13: =BI10*BI12 -> 47102.544 | BJ13: =BJ10*BJ12 -> 42544.233 | BK13: =BK10*BK12 -> 62803.392 | BL13: =BL10*BL12 -> 76815.976 | BM13: =BM10*BM12 -> 98130.299 | BN13: =BN10*BN12 -> 114801.9 | BO13: =BO10*BO12 -> 118628.63 | BP13: =BP10*BP12 -> 118628.63 | ... BT13: =BT10*BT12 -> 47102.544 | BU13: =SUM(BI13:BT13) -> 980430.72 | BV13: =BV8 -> Revenue
D14: ='ToT (Intake Form)'!C29 -> Dome Large | E14: ='ToT (Intake Form)'!C30 -> 5 | F14: =E14 -> 5 | G14: =F14 -> 5 | H14: =G14 -> 5 | I14: =H14 -> 5 | J14: =I14 -> 5 | K14: =J14 -> 5 | L14: =K14 -> 5 | M14: =L14 -> 5 | ... P14: =O14 -> 5 | Q14: =AVERAGE(E14:P14) -> 5 | R14: =$D14 -> Dome Large | S14: =Q14 -> 5 | T14: =S14 -> 5 | U14: =T14 -> 5 | V14: =U14 -> 5 | W14: =V14 -> 5 | X14: =W14 -> 5 | Y14: =X14 -> 5 | Z14: =Y14 -> 5 | AA14: =Z14 -> 5 | ... AD14: =AC14 -> 5 | AE14: =AVERAGE(S14:AD14) -> 5 | AF14: =$D14 -> Dome Large | AG14: =AE14 -> 5 | AH14: =AG14 -> 5 | AI14: =AH14 -> 5 | AJ14: =AI14 -> 5 | AK14: =AJ14 -> 5 | AL14: =AK14 -> 5 | AM14: =AL14 -> 5 | AN14: =AM14 -> 5 | AO14: =AN14 -> 5 | ... AR14: =AQ14 -> 5 | AS14: =AVERAGE(AG14:AR14) -> 5 | AT14: =$D14 -> Dome Large | AU14: =AS14 -> 5 | AV14: =AU14 -> 5 | AW14: =AV14 -> 5 | AX14: =AW14 -> 5 | AY14: =AX14 -> 5 | AZ14: =AY14 -> 5 | BA14: =AZ14 -> 5 | BB14: =BA14 -> 5 | BC14: =BB14 -> 5 | ... BF14: =BE14 -> 5 | BG14: =AVERAGE(AU14:BF14) -> 5 | BH14: =$D14 -> Dome Large | BI14: =BF14 -> 5 | BJ14: =BI14 -> 5 | BK14: =BJ14 -> 5 | BL14: =BK14 -> 5 | BM14: =BL14 -> 5 | BN14: =BM14 -> 5 | BO14: =BN14 -> 5 | BP14: =BO14 -> 5 | BQ14: =BP14 -> 5 | ... BT14: =BS14 -> 5 | BU14: =AVERAGE(BI14:BT14) -> 5 | BV14: =D14 -> Dome Large
B15: Year 1 % Occupancy | C15: ='Occ. Proj'!N28 -> 0.6 | D15: =D5 -> ADR | E15: ='Rates Proj'!M53 -> 250 | F15: =E15 -> 250 | G15: =F15 -> 250 | H15: 325 | I15: 350 | J15: 375 | K15: ='Rates Proj'!N53 -> 425 | L15: =K15 -> 425 | M15: 350 | N15: 350 | O15: =E15 -> 250 | P15: =O15 -> 250 | Q15: =IFERROR(Q18/Q17,0) -> 333.04749 | R15: =R5 -> ADR | S15: =E15*(1+$C$3) -> 257.5 | T15: =F15*(1+$C$3) -> 257.5 | U15: =G15*(1+$C$3) -> 257.5 | V15: =H15*(1+$C$3) -> 334.75 | W15: =I15*(1+$C$3) -> 360.5 | X15: =J15*(1+$C$3) -> 386.25 | Y15: =K15*(1+$C$3) -> 437.75 | Z15: =L15*(1+$C$3) -> 437.75 | ... AD15: =P15*(1+$C$3) -> 257.5 | AE15: =IFERROR(AE18/AE17,0) -> 343.03892 | AF15: =AF5 -> ADR | AG15: =S15*(1+$C$3) -> 265.225 | AH15: =T15*(1+$C$3) -> 265.225 | AI15: =U15*(1+$C$3) -> 265.225 | AJ15: =V15*(1+$C$3) -> 344.7925 | AK15: =W15*(1+$C$3) -> 371.315 | AL15: =X15*(1+$C$3) -> 397.8375 | AM15: =Y15*(1+$C$3) -> 450.8825 | AN15: =Z15*(1+$C$3) -> 450.8825 | ... AR15: =AD15*(1+$C$3) -> 265.225 | AS15: =IFERROR(AS18/AS17,0) -> 353.33008 | AT15: =AT5 -> ADR | AU15: =AG15*(1+$C$3) -> 273.18175 | AV15: =AH15*(1+$C$3) -> 273.18175 | AW15: =AI15*(1+$C$3) -> 273.18175 | AX15: =AJ15*(1+$C$3) -> 355.13628 | AY15: =AK15*(1+$C$3) -> 382.45445 | AZ15: =AL15*(1+$C$3) -> 409.77263 | BA15: =AM15*(1+$C$3) -> 464.40897 | BB15: =AN15*(1+$C$3) -> 464.40897 | ... BF15: =AR15*(1+$C$3) -> 273.18175 | BG15: =IFERROR(BG18/BG17,0) -> 363.92999 | BH15: =BH5 -> ADR | BI15: =AU15*(1+$C$3) -> 281.3772 | BJ15: =AV15*(1+$C$3) -> 281.3772 | BK15: =AW15*(1+$C$3) -> 281.3772 | BL15: =AX15*(1+$C$3) -> 365.79036 | BM15: =AY15*(1+$C$3) -> 393.92808 | BN15: =AZ15*(1+$C$3) -> 422.0658 | BO15: =BA15*(1+$C$3) -> 478.34124 | BP15: =BB15*(1+$C$3) -> 478.34124 | ... BT15: =BF15*(1+$C$3) -> 281.3772 | BU15: =IFERROR(BU18/BU17,0) -> 374.84788 | BV15: =BV5 -> ADR
B16: Year 2 % Occupancy | C16: ='Occ. Proj'!O28 -> 0.75 | D16: =D6 -> Occupancy | E16: =BI16*$C15 -> 0.27 | F16: =BJ16*$C15 -> 0.27 | G16: =BK16*$C15 -> 0.36 | H16: =BL16*$C15 -> 0.42 | I16: =BM16*$C15 -> 0.42 | J16: =BN16*$C15 -> 0.468 | K16: =BO16*$C15 -> 0.468 | L16: =BP16*$C15 -> 0.468 | ... P16: =BT16*$C15 -> 0.27 | Q16: =IFERROR(Q17/(Q14*$Q$3),0) -> 0.39009863 | R16: =R6 -> Occupancy | S16: =BI16*$C16 -> 0.3375 | T16: =BJ16*$C16 -> 0.3375 | U16: =BK16*$C16 -> 0.45 | V16: =BL16*$C16 -> 0.525 | W16: =BM16*$C16 -> 0.525 | X16: =BN16*$C16 -> 0.585 | Y16: =BO16*$C16 -> 0.585 | Z16: =BP16*$C16 -> 0.585 | ... AD16: =BT16*$C16 -> 0.3375 | AE16: =IFERROR(AE17/(AE14*$Q$3),0) -> 0.48762329 | AF16: =AF6 -> Occupancy | AG16: =BI16*$C17 -> 0.405 | AH16: =BJ16*$C17 -> 0.405 | AI16: =BK16*$C17 -> 0.54 | AJ16: =BL16*$C17 -> 0.63 | AK16: =BM16*$C17 -> 0.63 | AL16: =BN16*$C17 -> 0.702 | AM16: =BO16*$C17 -> 0.702 | AN16: =BP16*$C17 -> 0.702 | ... AR16: =BT16*$C17 -> 0.405 | AS16: =IFERROR(AS17/(AS14*$Q$3),0) -> 0.58514795 | AT16: =AT6 -> Occupancy | AU16: =BI16*$C18 -> 0.43875 | AV16: =BJ16*$C18 -> 0.43875 | AW16: =BK16*$C18 -> 0.585 | AX16: =BL16*$C18 -> 0.6825 | AY16: =BM16*$C18 -> 0.6825 | AZ16: =BN16*$C18 -> 0.7605 | BA16: =BO16*$C18 -> 0.7605 | BB16: =BP16*$C18 -> 0.7605 | ... BF16: =BT16*$C18 -> 0.43875 | BG16: =IFERROR(BG17/(BG14*$Q$3),0) -> 0.63391027 | BH16: =BH6 -> Occupancy | BI16: ='Occ. Proj'!$I$19 -> 0.45 | BJ16: ='Occ. Proj'!$I$19 -> 0.45 | BK16: =BK11 -> 0.6 | BL16: =BL11 -> 0.7 | BM16: 0.7 | BN16: ='Occ. Proj'!$J$19 -> 0.78 | BO16: ='Occ. Proj'!$J$19 -> 0.78 | BP16: ='Occ. Proj'!$J$19 -> 0.78 | BQ16: =BQ11 -> 0.75 | BR16: =BR11 -> 0.75 | BS16: 0.6 | BT16: =BI16 -> 0.45 | BU16: =IFERROR(BU17/(BU14*$Q$3),0) -> 0.65016438 | BV16: =BV6 -> Occupancy
B17: Year 3 % Occupancy | C17: ='Occ. Proj'!P28 -> 0.9 | D17: =D7 -> Site Nights | E17: =E16*E3*E14 -> 41.85 | F17: =F16*F3*F14 -> 37.8 | G17: =G16*G3*G14 -> 55.8 | H17: =H16*H3*H14 -> 63 | I17: =I16*I3*I14 -> 65.1 | J17: =J16*J3*J14 -> 70.2 | K17: =K16*K3*K14 -> 72.54 | L17: =L16*L3*L14 -> 72.54 | ... P17: =P16*P3*P14 -> 41.85 | Q17: =SUM(E17:P17) -> 711.93 | R17: =R7 -> Site Nights | S17: =S16*S3*S14 -> 52.3125 | T17: =T16*T3*T14 -> 47.25 | U17: =U16*U3*U14 -> 69.75 | V17: =V16*V3*V14 -> 78.75 | W17: =W16*W3*W14 -> 81.375 | X17: =X16*X3*X14 -> 87.75 | Y17: =Y16*Y3*Y14 -> 90.675 | Z17: =Z16*Z3*Z14 -> 90.675 | ... AD17: =AD16*AD3*AD14 -> 52.3125 | AE17: =SUM(S17:AD17) -> 889.9125 | AF17: =AF7 -> Site Nights | AG17: =AG16*AG3*AG14 -> 62.775 | AH17: =AH16*AH3*AH14 -> 56.7 | AI17: =AI16*AI3*AI14 -> 83.7 | AJ17: =AJ16*AJ3*AJ14 -> 94.5 | AK17: =AK16*AK3*AK14 -> 97.65 | AL17: =AL16*AL3*AL14 -> 105.3 | AM17: =AM16*AM3*AM14 -> 108.81 | AN17: =AN16*AN3*AN14 -> 108.81 | ... AR17: =AR16*AR3*AR14 -> 62.775 | AS17: =SUM(AG17:AR17) -> 1067.895 | AT17: =AT7 -> Site Nights | AU17: =AU16*AU3*AU14 -> 68.00625 | AV17: =AV16*AV3*AV14 -> 61.425 | AW17: =AW16*AW3*AW14 -> 90.675 | AX17: =AX16*AX3*AX14 -> 102.375 | AY17: =AY16*AY3*AY14 -> 105.7875 | AZ17: =AZ16*AZ3*AZ14 -> 114.075 | BA17: =BA16*BA3*BA14 -> 117.8775 | BB17: =BB16*BB3*BB14 -> 117.8775 | ... BF17: =BF16*BF3*BF14 -> 68.00625 | BG17: =SUM(AU17:BF17) -> 1156.8863 | BH17: =BH7 -> Site Nights | BI17: =BI16*BI3*BI14 -> 69.75 | BJ17: =BJ16*BJ3*BJ14 -> 63 | BK17: =BK16*BK3*BK14 -> 93 | BL17: =BL16*BL3*BL14 -> 105 | BM17: =BM16*BM3*BM14 -> 108.5 | BN17: =BN16*BN3*BN14 -> 117 | BO17: =BO16*BO3*BO14 -> 120.9 | BP17: =BP16*BP3*BP14 -> 120.9 | ... BT17: =BT16*BT3*BT14 -> 69.75 | BU17: =SUM(BI17:BT17) -> 1186.55 | BV17: =BV7 -> Site Nights
B18: Year 4 % Occupancy | C18: ='Occ. Proj'!Q28 -> 0.975 | D18: =D13 -> Revenue | E18: =E15*E17 -> 10462.5 | F18: =F15*F17 -> 9450 | G18: =G15*G17 -> 13950 | H18: =H15*H17 -> 20475 | I18: =I15*I17 -> 22785 | J18: =J15*J17 -> 26325 | K18: =K15*K17 -> 30829.5 | L18: =L15*L17 -> 30829.5 | ... P18: =P15*P17 -> 10462.5 | Q18: =SUM(E18:P18) -> 237106.5 | R18: =R13 -> Revenue | S18: =S15*S17 -> 13470.469 | T18: =T15*T17 -> 12166.875 | U18: =U15*U17 -> 17960.625 | V18: =V15*V17 -> 26361.562 | W18: =W15*W17 -> 29335.688 | X18: =X15*X17 -> 33893.437 | Y18: =Y15*Y17 -> 39692.981 | Z18: =Z15*Z17 -> 39692.981 | ... AD18: =AD15*AD17 -> 13470.469 | AE18: =SUM(S18:AD18) -> 305274.62 | AF18: =AF13 -> Revenue | AG18: =AG15*AG17 -> 16649.499 | AH18: =AH15*AH17 -> 15038.258 | AI18: =AI15*AI17 -> 22199.333 | AJ18: =AJ15*AJ17 -> 32582.891 | AK18: =AK15*AK17 -> 36258.91 | AL18: =AL15*AL17 -> 41892.289 | AM18: =AM15*AM17 -> 49060.525 | AN18: =AN15*AN17 -> 49060.525 | ... AR18: =AR15*AR17 -> 16649.499 | AS18: =SUM(AG18:AR18) -> 377319.43 | AT18: =AT13 -> Revenue | AU18: =AU15*AU17 -> 18578.066 | AV18: =AV15*AV17 -> 16780.189 | AW18: =AW15*AW17 -> 24770.755 | AX18: =AX15*AX17 -> 36357.076 | AY18: =AY15*AY17 -> 40458.9 | AZ18: =AZ15*AZ17 -> 46744.812 | BA18: =BA15*BA17 -> 54743.369 | BB18: =BB15*BB17 -> 54743.369 | ... BF18: =BF15*BF17 -> 18578.066 | BG18: =SUM(AU18:BF18) -> 421025.6 | BH18: =BH13 -> Revenue | BI18: =BI15*BI17 -> 19626.06 | BJ18: =BJ15*BJ17 -> 17726.764 | BK18: =BK15*BK17 -> 26168.08 | BL18: =BL15*BL17 -> 38407.988 | BM18: =BM15*BM17 -> 42741.197 | BN18: =BN15*BN17 -> 49381.699 | BO18: =BO15*BO17 -> 57831.456 | BP18: =BP15*BP17 -> 57831.456 | ... BT18: =BT15*BT17 -> 19626.06 | BU18: =SUM(BI18:BT18) -> 444775.76 | BV18: =BV13 -> Revenue
D19: ='ToT (Intake Form)'!C32 -> Dome Small | E19: ='ToT (Intake Form)'!C33 -> 4 | F19: =E19 -> 4 | G19: =F19 -> 4 | H19: =G19 -> 4 | I19: =H19 -> 4 | J19: =I19 -> 4 | K19: =J19 -> 4 | L19: =K19 -> 4 | M19: =L19 -> 4 | ... P19: =O19 -> 4 | Q19: =AVERAGE(E19:P19) -> 4 | R19: =$D19 -> Dome Small | S19: =Q19 -> 4 | T19: =S19 -> 4 | U19: =T19 -> 4 | V19: =U19 -> 4 | W19: =V19 -> 4 | X19: =W19 -> 4 | Y19: =X19 -> 4 | Z19: =Y19 -> 4 | AA19: =Z19 -> 4 | ... AD19: =AC19 -> 4 | AE19: =AVERAGE(S19:AD19) -> 4 | AF19: =$D19 -> Dome Small | AG19: =AE19 -> 4 | AH19: =AG19 -> 4 | AI19: =AH19 -> 4 | AJ19: =AI19 -> 4 | AK19: =AJ19 -> 4 | AL19: =AK19 -> 4 | AM19: =AL19 -> 4 | AN19: =AM19 -> 4 | AO19: =AN19 -> 4 | ... AR19: =AQ19 -> 4 | AS19: =AVERAGE(AG19:AR19) -> 4 | AT19: =$D19 -> Dome Small | AU19: =AS19 -> 4 | AV19: =AU19 -> 4 | AW19: =AV19 -> 4 | AX19: =AW19 -> 4 | AY19: =AX19 -> 4 | AZ19: =AY19 -> 4 | BA19: =AZ19 -> 4 | BB19: =BA19 -> 4 | BC19: =BB19 -> 4 | ... BF19: =BE19 -> 4 | BG19: =AVERAGE(AU19:BF19) -> 4 | BH19: =$D19 -> Dome Small | BI19: =BF19 -> 4 | BJ19: =BI19 -> 4 | BK19: =BJ19 -> 4 | BL19: =BK19 -> 4 | BM19: =BL19 -> 4 | BN19: =BM19 -> 4 | BO19: =BN19 -> 4 | BP19: =BO19 -> 4 | BQ19: =BP19 -> 4 | ... BT19: =BS19 -> 4 | BU19: =AVERAGE(BI19:BT19) -> 4 | BV19: =D19 -> Dome Small
B20: Year 1 % Occupancy | C20: ='Occ. Proj'!N29 -> 0.6 | D20: =D15 -> ADR | E20: ='Rates Proj'!M54 -> 300 | F20: =E20 -> 300 | G20: =F20 -> 300 | H20: 350 | I20: 400 | J20: ='Rates Proj'!N54 -> 500 | K20: =J20 -> 500 | L20: =K20 -> 500 | M20: 400 | N20: 400 | O20: =E20 -> 300 | P20: =O20 -> 300 | Q20: =IFERROR(Q23/Q22,0) -> 396.16796 | R20: =R15 -> ADR | S20: =E20*(1+$C$3) -> 309 | T20: =F20*(1+$C$3) -> 309 | U20: =G20*(1+$C$3) -> 309 | V20: =H20*(1+$C$3) -> 360.5 | W20: =I20*(1+$C$3) -> 412 | X20: =J20*(1+$C$3) -> 515 | Y20: =K20*(1+$C$3) -> 515 | Z20: =L20*(1+$C$3) -> 515 | ... AD20: =P20*(1+$C$3) -> 309 | AE20: =IFERROR(AE23/AE22,0) -> 408.053 | AF20: =AF15 -> ADR | AG20: =S20*(1+$C$3) -> 318.27 | AH20: =T20*(1+$C$3) -> 318.27 | AI20: =U20*(1+$C$3) -> 318.27 | AJ20: =V20*(1+$C$3) -> 371.315 | AK20: =W20*(1+$C$3) -> 424.36 | AL20: =X20*(1+$C$3) -> 530.45 | AM20: =Y20*(1+$C$3) -> 530.45 | AN20: =Z20*(1+$C$3) -> 530.45 | ... AR20: =AD20*(1+$C$3) -> 318.27 | AS20: =IFERROR(AS23/AS22,0) -> 420.29459 | AT20: =AT15 -> ADR | AU20: =AG20*(1+$C$3) -> 327.8181 | AV20: =AH20*(1+$C$3) -> 327.8181 | AW20: =AI20*(1+$C$3) -> 327.8181 | AX20: =AJ20*(1+$C$3) -> 382.45445 | AY20: =AK20*(1+$C$3) -> 437.0908 | AZ20: =AL20*(1+$C$3) -> 546.3635 | BA20: =AM20*(1+$C$3) -> 546.3635 | BB20: =AN20*(1+$C$3) -> 546.3635 | ... BF20: =AR20*(1+$C$3) -> 327.8181 | BG20: =IFERROR(BG23/BG22,0) -> 432.90342 | BH20: =BH15 -> ADR | BI20: =AU20*(1+$C$3) -> 337.65264 | BJ20: =AV20*(1+$C$3) -> 337.65264 | BK20: =AW20*(1+$C$3) -> 337.65264 | BL20: =AX20*(1+$C$3) -> 393.92808 | BM20: =AY20*(1+$C$3) -> 450.20352 | BN20: =AZ20*(1+$C$3) -> 562.75441 | BO20: =BA20*(1+$C$3) -> 562.75441 | BP20: =BB20*(1+$C$3) -> 562.75441 | ... BT20: =BF20*(1+$C$3) -> 337.65264 | BU20: =IFERROR(BU23/BU22,0) -> 445.89053 | BV20: =BV15 -> ADR
B21: Year 2 % Occupancy | C21: ='Occ. Proj'!O29 -> 0.75 | D21: =D16 -> Occupancy | E21: =BI21*$C20 -> 0.27 | F21: =BJ21*$C20 -> 0.27 | G21: =BK21*$C20 -> 0.36 | H21: =BL21*$C20 -> 0.42 | I21: =BM21*$C20 -> 0.45 | J21: =BN21*$C20 -> 0.51 | K21: =BO21*$C20 -> 0.51 | L21: =BP21*$C20 -> 0.51 | ... P21: =BT21*$C20 -> 0.27 | Q21: =IFERROR(Q22/(Q19*$Q$3),0) -> 0.40323288 | R21: =R16 -> Occupancy | S21: =BI21*$C21 -> 0.3375 | T21: =BJ21*$C21 -> 0.3375 | U21: =BK21*$C21 -> 0.45 | V21: =BL21*$C21 -> 0.525 | W21: =BM21*$C21 -> 0.5625 | X21: =BN21*$C21 -> 0.6375 | Y21: =BO21*$C21 -> 0.6375 | Z21: =BP21*$C21 -> 0.6375 | ... AD21: =BT21*$C21 -> 0.3375 | AE21: =IFERROR(AE22/(AE19*$Q$3),0) -> 0.5040411 | AF21: =AF16 -> Occupancy | AG21: =BI21*$C22 -> 0.405 | AH21: =BJ21*$C22 -> 0.405 | AI21: =BK21*$C22 -> 0.54 | AJ21: =BL21*$C22 -> 0.63 | AK21: =BM21*$C22 -> 0.675 | AL21: =BN21*$C22 -> 0.765 | AM21: =BO21*$C22 -> 0.765 | AN21: =BP21*$C22 -> 0.765 | ... AR21: =BT21*$C22 -> 0.405 | AS21: =IFERROR(AS22/(AS19*$Q$3),0) -> 0.60484932 | AT21: =AT16 -> Occupancy | AU21: =BI21*$C23 -> 0.43875 | AV21: =BJ21*$C23 -> 0.43875 | AW21: =BK21*$C23 -> 0.585 | AX21: =BL21*$C23 -> 0.6825 | AY21: =BM21*$C23 -> 0.73125 | AZ21: =BN21*$C23 -> 0.82875 | BA21: =BO21*$C23 -> 0.82875 | BB21: =BP21*$C23 -> 0.82875 | ... BF21: =BT21*$C23 -> 0.43875 | BG21: =IFERROR(BG22/(BG19*$Q$3),0) -> 0.65525342 | BH21: =BH16 -> Occupancy | BI21: ='Occ. Proj'!$I$20 -> 0.45 | BJ21: ='Occ. Proj'!$I$20 -> 0.45 | BK21: =BK16 -> 0.6 | BL21: =BL16 -> 0.7 | BM21: 0.75 | BN21: ='Occ. Proj'!$J$20 -> 0.85 | BO21: ='Occ. Proj'!$J$20 -> 0.85 | BP21: ='Occ. Proj'!$J$20 -> 0.85 | BQ21: =BQ16 -> 0.75 | BR21: =BR16 -> 0.75 | BS21: 0.6 | BT21: =BI21 -> 0.45 | BU21: =IFERROR(BU22/(BU19*$Q$3),0) -> 0.67205479 | BV21: =BV16 -> Occupancy
B22: Year 3 % Occupancy | C22: ='Occ. Proj'!P29 -> 0.9 | D22: =D7 -> Site Nights | E22: =E21*E3*E19 -> 33.48 | F22: =F21*F3*F19 -> 30.24 | G22: =G21*G3*G19 -> 44.64 | H22: =H21*H3*H19 -> 50.4 | I22: =I21*I3*I19 -> 55.8 | J22: =J21*J3*J19 -> 61.2 | K22: =K21*K3*K19 -> 63.24 | L22: =L21*L3*L19 -> 63.24 | ... P22: =P21*P3*P19 -> 33.48 | Q22: =SUM(E22:P22) -> 588.72 | R22: =R7 -> Site Nights | S22: =S21*S3*S19 -> 41.85 | T22: =T21*T3*T19 -> 37.8 | U22: =U21*U3*U19 -> 55.8 | V22: =V21*V3*V19 -> 63 | W22: =W21*W3*W19 -> 69.75 | X22: =X21*X3*X19 -> 76.5 | Y22: =Y21*Y3*Y19 -> 79.05 | Z22: =Z21*Z3*Z19 -> 79.05 | ... AD22: =AD21*AD3*AD19 -> 41.85 | AE22: =SUM(S22:AD22) -> 735.9 | AF22: =AF7 -> Site Nights | AG22: =AG21*AG3*AG19 -> 50.22 | AH22: =AH21*AH3*AH19 -> 45.36 | AI22: =AI21*AI3*AI19 -> 66.96 | AJ22: =AJ21*AJ3*AJ19 -> 75.6 | AK22: =AK21*AK3*AK19 -> 83.7 | AL22: =AL21*AL3*AL19 -> 91.8 | AM22: =AM21*AM3*AM19 -> 94.86 | AN22: =AN21*AN3*AN19 -> 94.86 | ... AR22: =AR21*AR3*AR19 -> 50.22 | AS22: =SUM(AG22:AR22) -> 883.08 | AT22: =AT7 -> Site Nights | AU22: =AU21*AU3*AU19 -> 54.405 | AV22: =AV21*AV3*AV19 -> 49.14 | AW22: =AW21*AW3*AW19 -> 72.54 | AX22: =AX21*AX3*AX19 -> 81.9 | AY22: =AY21*AY3*AY19 -> 90.675 | AZ22: =AZ21*AZ3*AZ19 -> 99.45 | BA22: =BA21*BA3*BA19 -> 102.765 | BB22: =BB21*BB3*BB19 -> 102.765 | ... BF22: =BF21*BF3*BF19 -> 54.405 | BG22: =SUM(AU22:BF22) -> 956.67 | BH22: =BH7 -> Site Nights | BI22: =BI21*BI3*BI19 -> 55.8 | BJ22: =BJ21*BJ3*BJ19 -> 50.4 | BK22: =BK21*BK3*BK19 -> 74.4 | BL22: =BL21*BL3*BL19 -> 84 | BM22: =BM21*BM3*BM19 -> 93 | BN22: =BN21*BN3*BN19 -> 102 | BO22: =BO21*BO3*BO19 -> 105.4 | BP22: =BP21*BP3*BP19 -> 105.4 | ... BT22: =BT21*BT3*BT19 -> 55.8 | BU22: =SUM(BI22:BT22) -> 981.2 | BV22: =BV7 -> Site Nights
B23: Year 4 % Occupancy | C23: ='Occ. Proj'!Q29 -> 0.975 | D23: Revenue | E23: =E20*E22 -> 10044 | F23: =F20*F22 -> 9072 | G23: =G20*G22 -> 13392 | H23: =H20*H22 -> 17640 | I23: =I20*I22 -> 22320 | J23: =J20*J22 -> 30600 | K23: =K20*K22 -> 31620 | L23: =L20*L22 -> 31620 | ... P23: =P20*P22 -> 10044 | Q23: =SUM(E23:P23) -> 233232 | R23: Revenue | S23: =S20*S22 -> 12931.65 | T23: =T20*T22 -> 11680.2 | U23: =U20*U22 -> 17242.2 | V23: =V20*V22 -> 22711.5 | W23: =W20*W22 -> 28737 | X23: =X20*X22 -> 39397.5 | Y23: =Y20*Y22 -> 40710.75 | Z23: =Z20*Z22 -> 40710.75 | ... AD23: =AD20*AD22 -> 12931.65 | AE23: =SUM(S23:AD23) -> 300286.2 | AF23: Revenue | AG23: =AG20*AG22 -> 15983.519 | AH23: =AH20*AH22 -> 14436.727 | AI23: =AI20*AI22 -> 21311.359 | AJ23: =AJ20*AJ22 -> 28071.414 | AK23: =AK20*AK22 -> 35518.932 | AL23: =AL20*AL22 -> 48695.31 | AM23: =AM20*AM22 -> 50318.487 | AN23: =AN20*AN22 -> 50318.487 | ... AR23: =AR20*AR22 -> 15983.519 | AS23: =SUM(AG23:AR23) -> 371153.74 | AT23: Revenue | AU23: =AU20*AU22 -> 17834.944 | AV23: =AV20*AV22 -> 16108.981 | AW23: =AW20*AW22 -> 23779.925 | AX23: =AX20*AX22 -> 31323.019 | AY23: =AY20*AY22 -> 39633.208 | AZ23: =AZ20*AZ22 -> 54335.85 | BA23: =BA20*BA22 -> 56147.045 | BB23: =BB20*BB22 -> 56147.045 | ... BF23: =BF20*BF22 -> 17834.944 | BG23: =SUM(AU23:BF23) -> 414145.72 | BH23: Revenue | BI23: =BI20*BI22 -> 18841.017 | BJ23: =BJ20*BJ22 -> 17017.693 | BK23: =BK20*BK22 -> 25121.357 | BL23: =BL20*BL22 -> 33089.959 | BM23: =BM20*BM22 -> 41868.928 | BN23: =BN20*BN22 -> 57400.949 | BO23: =BO20*BO22 -> 59314.314 | BP23: =BP20*BP22 -> 59314.314 | ... BT23: =BT20*BT22 -> 18841.017 | BU23: =SUM(BI23:BT23) -> 437507.78 | BV23: Revenue
D24: ='ToT (Intake Form)'!C35 -> Safari Tent Large | E24: ='ToT (Intake Form)'!C36 -> 3 | F24: =E24 -> 3 | G24: =F24 -> 3 | H24: =G24 -> 3 | I24: =H24 -> 3 | J24: =I24 -> 3 | K24: =J24 -> 3 | L24: =K24 -> 3 | M24: =L24 -> 3 | ... P24: =O24 -> 3 | Q24: =AVERAGE(E24:P24) -> 3 | R24: =$D24 -> Safari Tent Large | S24: =Q24 -> 3 | T24: =S24 -> 3 | U24: =T24 -> 3 | V24: =U24 -> 3 | W24: =V24 -> 3 | X24: =W24 -> 3 | Y24: =X24 -> 3 | Z24: =Y24 -> 3 | AA24: =Z24 -> 3 | ... AD24: =AC24 -> 3 | AE24: =AVERAGE(S24:AD24) -> 3 | AF24: =$D24 -> Safari Tent Large | AG24: =AE24 -> 3 | AH24: =AG24 -> 3 | AI24: =AH24 -> 3 | AJ24: =AI24 -> 3 | AK24: =AJ24 -> 3 | AL24: =AK24 -> 3 | AM24: =AL24 -> 3 | AN24: =AM24 -> 3 | AO24: =AN24 -> 3 | ... AR24: =AQ24 -> 3 | AS24: =AVERAGE(AG24:AR24) -> 3 | AT24: =$D24 -> Safari Tent Large | AU24: =AS24 -> 3 | AV24: =AU24 -> 3 | AW24: =AV24 -> 3 | AX24: =AW24 -> 3 | AY24: =AX24 -> 3 | AZ24: =AY24 -> 3 | BA24: =AZ24 -> 3 | BB24: =BA24 -> 3 | BC24: =BB24 -> 3 | ... BF24: =BE24 -> 3 | BG24: =AVERAGE(AU24:BF24) -> 3 | BH24: =$D24 -> Safari Tent Large | BI24: =BF24 -> 3 | BJ24: =BI24 -> 3 | BK24: =BJ24 -> 3 | BL24: =BK24 -> 3 | BM24: =BL24 -> 3 | BN24: =BM24 -> 3 | BO24: =BN24 -> 3 | BP24: =BO24 -> 3 | BQ24: =BP24 -> 3 | ... BT24: =BS24 -> 3 | BU24: =AVERAGE(BI24:BT24) -> 3 | BV24: =D24 -> Safari Tent Large
B25: Year 1 % Occupancy | C25: ='Occ. Proj'!N30 -> 0.6 | D25: =D5 -> ADR | E25: ='Rates Proj'!M55 -> 400 | F25: =E25 -> 400 | G25: =F25 -> 400 | H25: 450 | I25: 475 | J25: ='Rates Proj'!N55 -> 500 | K25: =J25 -> 500 | L25: =K25 -> 500 | M25: 450 | N25: 450 | O25: =E25 -> 400 | P25: =O25 -> 400 | Q25: =IFERROR(Q28/Q27,0) -> 451.68779 | R25: =R5 -> ADR | S25: =E25*(1+$C$3) -> 412 | T25: =F25*(1+$C$3) -> 412 | U25: =G25*(1+$C$3) -> 412 | V25: =H25*(1+$C$3) -> 463.5 | W25: =I25*(1+$C$3) -> 489.25 | X25: =J25*(1+$C$3) -> 515 | Y25: =K25*(1+$C$3) -> 515 | Z25: =L25*(1+$C$3) -> 515 | ... AD25: =P25*(1+$C$3) -> 412 | AE25: =IFERROR(AE28/AE27,0) -> 465.23842 | AF25: =AF5 -> ADR | AG25: =S25*(1+$C$3) -> 424.36 | AH25: =T25*(1+$C$3) -> 424.36 | AI25: =U25*(1+$C$3) -> 424.36 | AJ25: =V25*(1+$C$3) -> 477.405 | AK25: =W25*(1+$C$3) -> 503.9275 | AL25: =X25*(1+$C$3) -> 530.45 | AM25: =Y25*(1+$C$3) -> 530.45 | AN25: =Z25*(1+$C$3) -> 530.45 | ... AR25: =AD25*(1+$C$3) -> 424.36 | AS25: =IFERROR(AS28/AS27,0) -> 479.19557 | AT25: =AT5 -> ADR | AU25: =AG25*(1+$C$3) -> 437.0908 | AV25: =AH25*(1+$C$3) -> 437.0908 | AW25: =AI25*(1+$C$3) -> 437.0908 | AX25: =AJ25*(1+$C$3) -> 491.72715 | AY25: =AK25*(1+$C$3) -> 519.04533 | AZ25: =AL25*(1+$C$3) -> 546.3635 | BA25: =AM25*(1+$C$3) -> 546.3635 | BB25: =AN25*(1+$C$3) -> 546.3635 | ... BF25: =AR25*(1+$C$3) -> 437.0908 | BG25: =IFERROR(BG28/BG27,0) -> 493.57144 | BH25: =BH5 -> ADR | BI25: =AU25*(1+$C$3) -> 450.20352 | BJ25: =AV25*(1+$C$3) -> 450.20352 | BK25: =AW25*(1+$C$3) -> 450.20352 | BL25: =AX25*(1+$C$3) -> 506.47896 | BM25: =AY25*(1+$C$3) -> 534.61668 | BN25: =AZ25*(1+$C$3) -> 562.75441 | BO25: =BA25*(1+$C$3) -> 562.75441 | BP25: =BB25*(1+$C$3) -> 562.75441 | ... BT25: =BF25*(1+$C$3) -> 450.20352 | BU25: =IFERROR(BU28/BU27,0) -> 508.37858 | BV25: =BV5 -> ADR
B26: Year 2 % Occupancy | C26: ='Occ. Proj'!O30 -> 0.75 | D26: =D6 -> Occupancy | E26: =BI26*$C25 -> 0.27 | F26: =BJ26*$C25 -> 0.27 | G26: =BK26*$C25 -> 0.36 | H26: =BL26*$C25 -> 0.42 | I26: =BM26*$C25 -> 0.45 | J26: =BN26*$C25 -> 0.48 | K26: =BO26*$C25 -> 0.48 | L26: =BP26*$C25 -> 0.48 | ... P26: =BT26*$C25 -> 0.27 | Q26: =IFERROR(Q27/(Q24*$Q$3),0) -> 0.39567123 | R26: =R6 -> Occupancy | S26: =BI26*$C26 -> 0.3375 | T26: =BJ26*$C26 -> 0.3375 | U26: =BK26*$C26 -> 0.45 | V26: =BL26*$C26 -> 0.525 | W26: =BM26*$C26 -> 0.5625 | X26: =BN26*$C26 -> 0.6 | Y26: =BO26*$C26 -> 0.6 | Z26: =BP26*$C26 -> 0.6 | ... AD26: =BT26*$C26 -> 0.3375 | AE26: =IFERROR(AE27/(AE24*$Q$3),0) -> 0.49458904 | AF26: =AF6 -> Occupancy | AG26: =BI26*$C27 -> 0.405 | AH26: =BJ26*$C27 -> 0.405 | AI26: =BK26*$C27 -> 0.54 | AJ26: =BL26*$C27 -> 0.63 | AK26: =BM26*$C27 -> 0.675 | AL26: =BN26*$C27 -> 0.72 | AM26: =BO26*$C27 -> 0.72 | AN26: =BP26*$C27 -> 0.72 | ... AR26: =BT26*$C27 -> 0.405 | AS26: =IFERROR(AS27/(AS24*$Q$3),0) -> 0.59350685 | AT26: =AT6 -> Occupancy | AU26: =BI26*$C28 -> 0.43875 | AV26: =BJ26*$C28 -> 0.43875 | AW26: =BK26*$C28 -> 0.585 | AX26: =BL26*$C28 -> 0.6825 | AY26: =BM26*$C28 -> 0.73125 | AZ26: =BN26*$C28 -> 0.78 | BA26: =BO26*$C28 -> 0.78 | BB26: =BP26*$C28 -> 0.78 | ... BF26: =BT26*$C28 -> 0.43875 | BG26: =IFERROR(BG27/(BG24*$Q$3),0) -> 0.64296575 | BH26: =BH6 -> Occupancy | BI26: ='Occ. Proj'!$I$21 -> 0.45 | BJ26: ='Occ. Proj'!$I$21 -> 0.45 | BK26: =BK21 -> 0.6 | BL26: =BL21 -> 0.7 | BM26: =BM21 -> 0.75 | BN26: ='Occ. Proj'!$J$21 -> 0.8 | BO26: ='Occ. Proj'!$J$21 -> 0.8 | BP26: ='Occ. Proj'!$J$21 -> 0.8 | BQ26: =BQ21 -> 0.75 | BR26: =BR21 -> 0.75 | BS26: 0.6 | BT26: =BI26 -> 0.45 | BU26: =IFERROR(BU27/(BU24*$Q$3),0) -> 0.65945205 | BV26: =BV6 -> Occupancy
B27: Year 3 % Occupancy | C27: ='Occ. Proj'!P30 -> 0.9 | D27: =D12 -> Site Nights | E27: =E26*E3*E24 -> 25.11 | F27: =F26*F3*F24 -> 22.68 | G27: =G26*G3*G24 -> 33.48 | H27: =H26*H3*H24 -> 37.8 | I27: =I26*I3*I24 -> 41.85 | J27: =J26*J3*J24 -> 43.2 | K27: =K26*K3*K24 -> 44.64 | L27: =L26*L3*L24 -> 44.64 | ... P27: =P26*P3*P24 -> 25.11 | Q27: =SUM(E27:P27) -> 433.26 | R27: =R12 -> Site Nights | S27: =S26*S3*S24 -> 31.3875 | T27: =T26*T3*T24 -> 28.35 | U27: =U26*U3*U24 -> 41.85 | V27: =V26*V3*V24 -> 47.25 | W27: =W26*W3*W24 -> 52.3125 | X27: =X26*X3*X24 -> 54 | Y27: =Y26*Y3*Y24 -> 55.8 | Z27: =Z26*Z3*Z24 -> 55.8 | ... AD27: =AD26*AD3*AD24 -> 31.3875 | AE27: =SUM(S27:AD27) -> 541.575 | AF27: =AF12 -> Site Nights | AG27: =AG26*AG3*AG24 -> 37.665 | AH27: =AH26*AH3*AH24 -> 34.02 | AI27: =AI26*AI3*AI24 -> 50.22 | AJ27: =AJ26*AJ3*AJ24 -> 56.7 | AK27: =AK26*AK3*AK24 -> 62.775 | AL27: =AL26*AL3*AL24 -> 64.8 | AM27: =AM26*AM3*AM24 -> 66.96 | AN27: =AN26*AN3*AN24 -> 66.96 | ... AR27: =AR26*AR3*AR24 -> 37.665 | AS27: =SUM(AG27:AR27) -> 649.89 | AT27: =AT12 -> Site Nights | AU27: =AU26*AU3*AU24 -> 40.80375 | AV27: =AV26*AV3*AV24 -> 36.855 | AW27: =AW26*AW3*AW24 -> 54.405 | AX27: =AX26*AX3*AX24 -> 61.425 | AY27: =AY26*AY3*AY24 -> 68.00625 | AZ27: =AZ26*AZ3*AZ24 -> 70.2 | BA27: =BA26*BA3*BA24 -> 72.54 | BB27: =BB26*BB3*BB24 -> 72.54 | ... BF27: =BF26*BF3*BF24 -> 40.80375 | BG27: =SUM(AU27:BF27) -> 704.0475 | BH27: =BH12 -> Site Nights | BI27: =BI26*BI3*BI24 -> 41.85 | BJ27: =BJ26*BJ3*BJ24 -> 37.8 | BK27: =BK26*BK3*BK24 -> 55.8 | BL27: =BL26*BL3*BL24 -> 63 | BM27: =BM26*BM3*BM24 -> 69.75 | BN27: =BN26*BN3*BN24 -> 72 | BO27: =BO26*BO3*BO24 -> 74.4 | BP27: =BP26*BP3*BP24 -> 74.4 | ... BT27: =BT26*BT3*BT24 -> 41.85 | BU27: =SUM(BI27:BT27) -> 722.1 | BV27: =BV12 -> Site Nights
B28: Year 4 % Occupancy | C28: ='Occ. Proj'!Q30 -> 0.975 | D28: Revenue | E28: =E25*E27 -> 10044 | F28: =F25*F27 -> 9072 | G28: =G25*G27 -> 13392 | H28: =H25*H27 -> 17010 | I28: =I25*I27 -> 19878.75 | J28: =J25*J27 -> 21600 | K28: =K25*K27 -> 22320 | L28: =L25*L27 -> 22320 | ... P28: =P25*P27 -> 10044 | Q28: =SUM(E28:P28) -> 195698.25 | R28: Revenue | S28: =S25*S27 -> 12931.65 | T28: =T25*T27 -> 11680.2 | U28: =U25*U27 -> 17242.2 | V28: =V25*V27 -> 21900.375 | W28: =W25*W27 -> 25593.891 | X28: =X25*X27 -> 27810 | Y28: =Y25*Y27 -> 28737 | Z28: =Z25*Z27 -> 28737 | ... AD28: =AD25*AD27 -> 12931.65 | AE28: =SUM(S28:AD28) -> 251961.5 | AF28: Revenue | AG28: =AG25*AG27 -> 15983.519 | AH28: =AH25*AH27 -> 14436.727 | AI28: =AI25*AI27 -> 21311.359 | AJ28: =AJ25*AJ27 -> 27068.863 | AK28: =AK25*AK27 -> 31634.049 | AL28: =AL25*AL27 -> 34373.16 | AM28: =AM25*AM27 -> 35518.932 | AN28: =AN25*AN27 -> 35518.932 | ... AR28: =AR25*AR27 -> 15983.519 | AS28: =SUM(AG28:AR28) -> 311424.41 | AT28: Revenue | AU28: =AU25*AU27 -> 17834.944 | AV28: =AV25*AV27 -> 16108.981 | AW28: =AW25*AW27 -> 23779.925 | AX28: =AX25*AX27 -> 30204.34 | AY28: =AY25*AY27 -> 35298.326 | AZ28: =AZ25*AZ27 -> 38354.718 | BA28: =BA25*BA27 -> 39633.208 | BB28: =BB25*BB27 -> 39633.208 | ... BF28: =BF25*BF27 -> 17834.944 | BG28: =SUM(AU28:BF28) -> 347497.74 | BH28: Revenue | BI28: =BI25*BI27 -> 18841.017 | BJ28: =BJ25*BJ27 -> 17017.693 | BK28: =BK25*BK27 -> 25121.357 | BL28: =BL25*BL27 -> 31908.175 | BM28: =BM25*BM27 -> 37289.514 | BN28: =BN25*BN27 -> 40518.317 | BO28: =BO25*BO27 -> 41868.928 | BP28: =BP25*BP27 -> 41868.928 | ... BT28: =BT25*BT27 -> 18841.017 | BU28: =SUM(BI28:BT28) -> 367100.17 | BV28: Revenue
D29: ='ToT (Intake Form)'!C38 -> Safari Tent Medium | E29: ='ToT (Intake Form)'!C39 -> 2 | F29: =E29 -> 2 | G29: =F29 -> 2 | H29: =G29 -> 2 | I29: =H29 -> 2 | J29: =I29 -> 2 | K29: =J29 -> 2 | L29: =K29 -> 2 | M29: =L29 -> 2 | ... P29: =O29 -> 2 | Q29: =AVERAGE(E29:P29) -> 2 | R29: =$D29 -> Safari Tent Medium | S29: =Q29 -> 2 | T29: =S29 -> 2 | U29: =T29 -> 2 | V29: =U29 -> 2 | W29: =V29 -> 2 | X29: =W29 -> 2 | Y29: =X29 -> 2 | Z29: =Y29 -> 2 | AA29: =Z29 -> 2 | ... AD29: =AC29 -> 2 | AE29: =AVERAGE(S29:AD29) -> 2 | AF29: =$D29 -> Safari Tent Medium | AG29: =AE29 -> 2 | AH29: =AG29 -> 2 | AI29: =AH29 -> 2 | AJ29: =AI29 -> 2 | AK29: =AJ29 -> 2 | AL29: =AK29 -> 2 | AM29: =AL29 -> 2 | AN29: =AM29 -> 2 | AO29: =AN29 -> 2 | ... AR29: =AQ29 -> 2 | AS29: =AVERAGE(AG29:AR29) -> 2 | AT29: =$D29 -> Safari Tent Medium | AU29: =AS29 -> 2 | AV29: =AU29 -> 2 | AW29: =AV29 -> 2 | AX29: =AW29 -> 2 | AY29: =AX29 -> 2 | AZ29: =AY29 -> 2 | BA29: =AZ29 -> 2 | BB29: =BA29 -> 2 | BC29: =BB29 -> 2 | ... BF29: =BE29 -> 2 | BG29: =AVERAGE(AU29:BF29) -> 2 | BH29: =$D29 -> Safari Tent Medium | BI29: =BF29 -> 2 | BJ29: =BI29 -> 2 | BK29: =BJ29 -> 2 | BL29: =BK29 -> 2 | BM29: =BL29 -> 2 | BN29: =BM29 -> 2 | BO29: =BN29 -> 2 | BP29: =BO29 -> 2 | BQ29: =BP29 -> 2 | ... BT29: =BS29 -> 2 | BU29: =AVERAGE(BI29:BT29) -> 2 | BV29: =D29 -> Safari Tent Medium
B30: Year 1 % Occupancy | C30: ='Occ. Proj'!N31 -> 0.6 | D30: =D10 -> ADR | E30: ='Rates Proj'!M56 -> 600 | F30: =E30 -> 600 | G30: =F30 -> 600 | H30: 650 | I30: 700 | J30: ='Rates Proj'!N56 -> 750 | K30: =J30 -> 750 | L30: =K30 -> 750 | M30: 700 | N30: 700 | O30: =E30 -> 600 | P30: =O30 -> 600 | Q30: =IFERROR(Q33/Q32,0) -> 681.09903 | R30: =R10 -> ADR | S30: =E30*(1+$C$3) -> 618 | T30: =F30*(1+$C$3) -> 618 | U30: =G30*(1+$C$3) -> 618 | V30: =H30*(1+$C$3) -> 669.5 | W30: =I30*(1+$C$3) -> 721 | X30: =J30*(1+$C$3) -> 772.5 | Y30: =K30*(1+$C$3) -> 772.5 | Z30: =L30*(1+$C$3) -> 772.5 | ... AD30: =P30*(1+$C$3) -> 618 | AE30: =IFERROR(AE33/AE32,0) -> 701.532 | AF30: =AF10 -> ADR | AG30: =S30*(1+$C$3) -> 636.54 | AH30: =T30*(1+$C$3) -> 636.54 | AI30: =U30*(1+$C$3) -> 636.54 | AJ30: =V30*(1+$C$3) -> 689.585 | AK30: =W30*(1+$C$3) -> 742.63 | AL30: =X30*(1+$C$3) -> 795.675 | AM30: =Y30*(1+$C$3) -> 795.675 | AN30: =Z30*(1+$C$3) -> 795.675 | ... AR30: =AD30*(1+$C$3) -> 636.54 | AS30: =IFERROR(AS33/AS32,0) -> 722.57796 | AT30: =AT10 -> ADR | AU30: =AG30*(1+$C$3) -> 655.6362 | AV30: =AH30*(1+$C$3) -> 655.6362 | AW30: =AI30*(1+$C$3) -> 655.6362 | AX30: =AJ30*(1+$C$3) -> 710.27255 | AY30: =AK30*(1+$C$3) -> 764.9089 | AZ30: =AL30*(1+$C$3) -> 819.54525 | BA30: =AM30*(1+$C$3) -> 819.54525 | BB30: =AN30*(1+$C$3) -> 819.54525 | ... BF30: =AR30*(1+$C$3) -> 655.6362 | BG30: =IFERROR(BG33/BG32,0) -> 744.2553 | BH30: =BH10 -> ADR | BI30: =AU30*(1+$C$3) -> 675.30529 | BJ30: =AV30*(1+$C$3) -> 675.30529 | BK30: =AW30*(1+$C$3) -> 675.30529 | BL30: =AX30*(1+$C$3) -> 731.58073 | BM30: =AY30*(1+$C$3) -> 787.85617 | BN30: =AZ30*(1+$C$3) -> 844.13161 | BO30: =BA30*(1+$C$3) -> 844.13161 | BP30: =BB30*(1+$C$3) -> 844.13161 | ... BT30: =BF30*(1+$C$3) -> 675.30529 | BU30: =IFERROR(BU33/BU32,0) -> 766.58296 | BV30: =BV10 -> ADR
B31: Year 2 % Occupancy | C31: ='Occ. Proj'!O31 -> 0.75 | D31: =D11 -> Occupancy | E31: =BI31*$C30 -> 0.27 | F31: =BJ31*$C30 -> 0.27 | G31: =BK31*$C30 -> 0.36 | H31: =BL31*$C30 -> 0.42 | I31: =BM31*$C30 -> 0.45 | J31: =BN31*$C30 -> 0.51 | K31: =BO31*$C30 -> 0.54 | L31: =BP31*$C30 -> 0.54 | ... P31: =BT31*$C30 -> 0.27 | Q31: =IFERROR(Q32/(Q29*$Q$3),0) -> 0.40832877 | R31: =R11 -> Occupancy | S31: =BI31*$C31 -> 0.3375 | T31: =BJ31*$C31 -> 0.3375 | U31: =BK31*$C31 -> 0.45 | V31: =BL31*$C31 -> 0.525 | W31: =BM31*$C31 -> 0.5625 | X31: =BN31*$C31 -> 0.6375 | Y31: =BO31*$C31 -> 0.675 | Z31: =BP31*$C31 -> 0.675 | ... AD31: =BT31*$C31 -> 0.3375 | AE31: =IFERROR(AE32/(AE29*$Q$3),0) -> 0.51041096 | AF31: =AF11 -> Occupancy | AG31: =BI31*$C32 -> 0.405 | AH31: =BJ31*$C32 -> 0.405 | AI31: =BK31*$C32 -> 0.54 | AJ31: =BL31*$C32 -> 0.63 | AK31: =BM31*$C32 -> 0.675 | AL31: =BN31*$C32 -> 0.765 | AM31: =BO31*$C32 -> 0.81 | AN31: =BP31*$C32 -> 0.81 | ... AR31: =BT31*$C32 -> 0.405 | AS31: =IFERROR(AS32/(AS29*$Q$3),0) -> 0.61249315 | AT31: =AT11 -> Occupancy | AU31: =BI31*$C33 -> 0.43875 | AV31: =BJ31*$C33 -> 0.43875 | AW31: =BK31*$C33 -> 0.585 | AX31: =BL31*$C33 -> 0.6825 | AY31: =BM31*$C33 -> 0.73125 | AZ31: =BN31*$C33 -> 0.82875 | BA31: =BO31*$C33 -> 0.8775 | BB31: =BP31*$C33 -> 0.8775 | ... BF31: =BT31*$C33 -> 0.43875 | BG31: =IFERROR(BG32/(BG29*$Q$3),0) -> 0.66353425 | BH31: =BH11 -> Occupancy | BI31: ='Occ. Proj'!$I$20 -> 0.45 | BJ31: ='Occ. Proj'!$I$20 -> 0.45 | BK31: =BK26 -> 0.6 | BL31: =BL26 -> 0.7 | BM31: =BM26 -> 0.75 | BN31: ='Occ. Proj'!$J$20 -> 0.85 | BO31: ='Occ. Proj'!J22 -> 0.9 | BP31: ='Occ. Proj'!J22 -> 0.9 | BQ31: =BQ26 -> 0.75 | BR31: =BR26 -> 0.75 | BS31: 0.6 | BT31: =BI31 -> 0.45 | BU31: =IFERROR(BU32/(BU29*$Q$3),0) -> 0.68054795 | BV31: =BV11 -> Occupancy
B32: Year 3 % Occupancy | C32: ='Occ. Proj'!P31 -> 0.9 | D32: =D17 -> Site Nights | E32: =E31*E3*E29 -> 16.74 | F32: =F31*F3*F29 -> 15.12 | G32: =G31*G3*G29 -> 22.32 | H32: =H31*H3*H29 -> 25.2 | I32: =I31*I3*I29 -> 27.9 | J32: =J31*J3*J29 -> 30.6 | K32: =K31*K3*K29 -> 33.48 | L32: =L31*L3*L29 -> 33.48 | ... P32: =P31*P3*P29 -> 16.74 | Q32: =SUM(E32:P32) -> 298.08 | R32: =R17 -> Site Nights | S32: =S31*S3*S29 -> 20.925 | T32: =T31*T3*T29 -> 18.9 | U32: =U31*U3*U29 -> 27.9 | V32: =V31*V3*V29 -> 31.5 | W32: =W31*W3*W29 -> 34.875 | X32: =X31*X3*X29 -> 38.25 | Y32: =Y31*Y3*Y29 -> 41.85 | Z32: =Z31*Z3*Z29 -> 41.85 | ... AD32: =AD31*AD3*AD29 -> 20.925 | AE32: =SUM(S32:AD32) -> 372.6 | AF32: =AF17 -> Site Nights | AG32: =AG31*AG3*AG29 -> 25.11 | AH32: =AH31*AH3*AH29 -> 22.68 | AI32: =AI31*AI3*AI29 -> 33.48 | AJ32: =AJ31*AJ3*AJ29 -> 37.8 | AK32: =AK31*AK3*AK29 -> 41.85 | AL32: =AL31*AL3*AL29 -> 45.9 | AM32: =AM31*AM3*AM29 -> 50.22 | AN32: =AN31*AN3*AN29 -> 50.22 | ... AR32: =AR31*AR3*AR29 -> 25.11 | AS32: =SUM(AG32:AR32) -> 447.12 | AT32: =AT17 -> Site Nights | AU32: =AU31*AU3*AU29 -> 27.2025 | AV32: =AV31*AV3*AV29 -> 24.57 | AW32: =AW31*AW3*AW29 -> 36.27 | AX32: =AX31*AX3*AX29 -> 40.95 | AY32: =AY31*AY3*AY29 -> 45.3375 | AZ32: =AZ31*AZ3*AZ29 -> 49.725 | BA32: =BA31*BA3*BA29 -> 54.405 | BB32: =BB31*BB3*BB29 -> 54.405 | ... BF32: =BF31*BF3*BF29 -> 27.2025 | BG32: =SUM(AU32:BF32) -> 484.38 | BH32: =BH17 -> Site Nights | BI32: =BI31*BI3*BI29 -> 27.9 | BJ32: =BJ31*BJ3*BJ29 -> 25.2 | BK32: =BK31*BK3*BK29 -> 37.2 | BL32: =BL31*BL3*BL29 -> 42 | BM32: =BM31*BM3*BM29 -> 46.5 | BN32: =BN31*BN3*BN29 -> 51 | BO32: =BO31*BO3*BO29 -> 55.8 | BP32: =BP31*BP3*BP29 -> 55.8 | ... BT32: =BT31*BT3*BT29 -> 27.9 | BU32: =SUM(BI32:BT32) -> 496.8 | BV32: =BV17 -> Site Nights
B33: Year 4 % Occupancy | C33: ='Occ. Proj'!Q31 -> 0.975 | D33: Revenue | E33: =E30*E32 -> 10044 | F33: =F30*F32 -> 9072 | G33: =G30*G32 -> 13392 | H33: =H30*H32 -> 16380 | I33: =I30*I32 -> 19530 | J33: =J30*J32 -> 22950 | K33: =K30*K32 -> 25110 | L33: =L30*L32 -> 25110 | ... P33: =P30*P32 -> 10044 | Q33: =SUM(E33:P33) -> 203022 | R33: Revenue | S33: =S30*S32 -> 12931.65 | T33: =T30*T32 -> 11680.2 | U33: =U30*U32 -> 17242.2 | V33: =V30*V32 -> 21089.25 | W33: =W30*W32 -> 25144.875 | X33: =X30*X32 -> 29548.125 | Y33: =Y30*Y32 -> 32329.125 | Z33: =Z30*Z32 -> 32329.125 | ... AD33: =AD30*AD32 -> 12931.65 | AE33: =SUM(S33:AD33) -> 261390.82 | AF33: Revenue | AG33: =AG30*AG32 -> 15983.519 | AH33: =AH30*AH32 -> 14436.727 | AI33: =AI30*AI32 -> 21311.359 | AJ33: =AJ30*AJ32 -> 26066.313 | AK33: =AK30*AK32 -> 31079.066 | AL33: =AL30*AL32 -> 36521.483 | AM33: =AM30*AM32 -> 39958.799 | AN33: =AN30*AN32 -> 39958.799 | ... AR33: =AR30*AR32 -> 15983.519 | AS33: =SUM(AG33:AR33) -> 323079.06 | AT33: Revenue | AU33: =AU30*AU32 -> 17834.944 | AV33: =AV30*AV32 -> 16108.981 | AW33: =AW30*AW32 -> 23779.925 | AX33: =AX30*AX32 -> 29085.661 | AY33: =AY30*AY32 -> 34679.057 | AZ33: =AZ30*AZ32 -> 40751.888 | BA33: =BA30*BA32 -> 44587.359 | BB33: =BB30*BB32 -> 44587.359 | ... BF33: =BF30*BF32 -> 17834.944 | BG33: =SUM(AU33:BF33) -> 360502.38 | BH33: Revenue | BI33: =BI30*BI32 -> 18841.017 | BJ33: =BJ30*BJ32 -> 17017.693 | BK33: =BK30*BK32 -> 25121.357 | BL33: =BL30*BL32 -> 30726.391 | BM33: =BM30*BM32 -> 36635.312 | BN33: =BN30*BN32 -> 43050.712 | BO33: =BO30*BO32 -> 47102.544 | BP33: =BP30*BP32 -> 47102.544 | ... BT33: =BT30*BT32 -> 18841.017 | BU33: =SUM(BI33:BT33) -> 380838.42 | BV33: Revenue
D34: ='ToT (Intake Form)'!C41 -> USE FOR MONTHLY | E34: ='ToT (Intake Form)'!C42 -> 0 | F34: =E34 -> 0 | G34: =F34 -> 0 | H34: =G34 -> 0 | I34: =H34 -> 0 | J34: =I34 -> 0 | K34: =J34 -> 0 | L34: =K34 -> 0 | M34: =L34 -> 0 | ... P34: =O34 -> 0 | Q34: =AVERAGE(E34:P34) -> 0 | R34: =$D34 -> USE FOR MONTHLY | S34: =Q34 -> 0 | T34: =S34 -> 0 | U34: =T34 -> 0 | V34: =U34 -> 0 | W34: =V34 -> 0 | X34: =W34 -> 0 | Y34: =X34 -> 0 | Z34: =Y34 -> 0 | AA34: =Z34 -> 0 | ... AD34: =AC34 -> 0 | AE34: =AVERAGE(S34:AD34) -> 0 | AF34: =$D34 -> USE FOR MONTHLY | AG34: =AE34 -> 0 | AH34: =AG34 -> 0 | AI34: =AH34 -> 0 | AJ34: =AI34 -> 0 | AK34: =AJ34 -> 0 | AL34: =AK34 -> 0 | AM34: =AL34 -> 0 | AN34: =AM34 -> 0 | AO34: =AN34 -> 0 | ... AR34: =AQ34 -> 0 | AS34: =AVERAGE(AG34:AR34) -> 0 | AT34: =$D34 -> USE FOR MONTHLY | AU34: =AS34 -> 0 | AV34: =AU34 -> 0 | AW34: =AV34 -> 0 | AX34: =AW34 -> 0 | AY34: =AX34 -> 0 | AZ34: =AY34 -> 0 | BA34: =AZ34 -> 0 | BB34: =BA34 -> 0 | BC34: =BB34 -> 0 | ... BF34: =BE34 -> 0 | BG34: =AVERAGE(AU34:BF34) -> 0 | BH34: =$D34 -> USE FOR MONTHLY | BI34: =BF34 -> 0 | BJ34: =BI34 -> 0 | BK34: =BJ34 -> 0 | BL34: =BK34 -> 0 | BM34: =BL34 -> 0 | BN34: =BM34 -> 0 | BO34: =BN34 -> 0 | BP34: =BO34 -> 0 | BQ34: =BP34 -> 0 | ... BT34: =BS34 -> 0 | BU34: =AVERAGE(BI34:BT34) -> 0 | BV34: =D34 -> USE FOR MONTHLY
B35: Year 1 % Occupancy | C35: ='Occ. Proj'!N32 -> 0.6 | D35: =D15 -> ADR | E35: ='Rates Proj'!M58 -> 0 | F35: =E35 -> 0 | G35: =F35 -> 0 | H35: 650 | I35: 700 | J35: ='Rates Proj'!N58 -> 0 | K35: =J35 -> 0 | L35: =K35 -> 0 | M35: 700 | N35: 700 | O35: =E35 -> 0 | P35: =O35 -> 0 | Q35: =IFERROR(Q38/Q37,0) -> 0 | R35: =R15 -> ADR | S35: =E35*(1+$C$3) -> 0 | T35: =F35*(1+$C$3) -> 0 | U35: =G35*(1+$C$3) -> 0 | V35: =H35*(1+$C$3) -> 669.5 | W35: =I35*(1+$C$3) -> 721 | X35: =J35*(1+$C$3) -> 0 | Y35: =K35*(1+$C$3) -> 0 | Z35: =L35*(1+$C$3) -> 0 | ... AD35: =P35*(1+$C$3) -> 0 | AE35: =IFERROR(AE38/AE37,0) -> 0 | AF35: =AF15 -> ADR | AG35: =S35*(1+$C$3) -> 0 | AH35: =T35*(1+$C$3) -> 0 | AI35: =U35*(1+$C$3) -> 0 | AJ35: =V35*(1+$C$3) -> 689.585 | AK35: =W35*(1+$C$3) -> 742.63 | AL35: =X35*(1+$C$3) -> 0 | AM35: =Y35*(1+$C$3) -> 0 | AN35: =Z35*(1+$C$3) -> 0 | ... AR35: =AD35*(1+$C$3) -> 0 | AS35: =IFERROR(AS38/AS37,0) -> 0 | AT35: =AT15 -> ADR | AU35: =AG35*(1+$C$3) -> 0 | AV35: =AH35*(1+$C$3) -> 0 | AW35: =AI35*(1+$C$3) -> 0 | AX35: =AJ35*(1+$C$3) -> 710.27255 | AY35: =AK35*(1+$C$3) -> 764.9089 | AZ35: =AL35*(1+$C$3) -> 0 | BA35: =AM35*(1+$C$3) -> 0 | BB35: =AN35*(1+$C$3) -> 0 | ... BF35: =AR35*(1+$C$3) -> 0 | BG35: =IFERROR(BG38/BG37,0) -> 0 | BH35: =BH15 -> ADR | BI35: =AU35*(1+$C$3) -> 0 | BJ35: =AV35*(1+$C$3) -> 0 | BK35: =AW35*(1+$C$3) -> 0 | BL35: =AX35*(1+$C$3) -> 731.58073 | BM35: =AY35*(1+$C$3) -> 787.85617 | BN35: =AZ35*(1+$C$3) -> 0 | BO35: =BA35*(1+$C$3) -> 0 | BP35: =BB35*(1+$C$3) -> 0 | ... BT35: =BF35*(1+$C$3) -> 0 | BU35: =IFERROR(BU38/BU37,0) -> 0 | BV35: =BV15 -> ADR
B36: Year 2 % Occupancy | C36: ='Occ. Proj'!O32 -> 0.75 | D36: =D16 -> Occupancy | E36: =BI36*$C35 -> 0.27 | F36: =BJ36*$C35 -> 0.27 | G36: =BK36*$C35 -> 0.36 | H36: =BL36*$C35 -> 0.42 | I36: =BM36*$C35 -> 0.45 | J36: =BN36*$C35 -> 0.51 | K36: =BO36*$C35 -> 0 | L36: =BP36*$C35 -> 0 | ... P36: =BT36*$C35 -> 0.27 | Q36: =IFERROR(Q37/(Q34*$Q$3),0) -> 0 | R36: =R16 -> Occupancy | S36: =BI36*$C36 -> 0.3375 | T36: =BJ36*$C36 -> 0.3375 | U36: =BK36*$C36 -> 0.45 | V36: =BL36*$C36 -> 0.525 | W36: =BM36*$C36 -> 0.5625 | X36: =BN36*$C36 -> 0.6375 | Y36: =BO36*$C36 -> 0 | Z36: =BP36*$C36 -> 0 | ... AD36: =BT36*$C36 -> 0.3375 | AE36: =IFERROR(AE37/(AE34*$Q$3),0) -> 0 | AF36: =AF16 -> Occupancy | AG36: =BI36*$C37 -> 0.405 | AH36: =BJ36*$C37 -> 0.405 | AI36: =BK36*$C37 -> 0.54 | AJ36: =BL36*$C37 -> 0.63 | AK36: =BM36*$C37 -> 0.675 | AL36: =BN36*$C37 -> 0.765 | AM36: =BO36*$C37 -> 0 | AN36: =BP36*$C37 -> 0 | ... AR36: =BT36*$C37 -> 0.405 | AS36: =IFERROR(AS37/(AS34*$Q$3),0) -> 0 | AT36: =AT16 -> Occupancy | AU36: =BI36*$C38 -> 0.43875 | AV36: =BJ36*$C38 -> 0.43875 | AW36: =BK36*$C38 -> 0.585 | AX36: =BL36*$C38 -> 0.6825 | AY36: =BM36*$C38 -> 0.73125 | AZ36: =BN36*$C38 -> 0.82875 | BA36: =BO36*$C38 -> 0 | BB36: =BP36*$C38 -> 0 | ... BF36: =BT36*$C38 -> 0.43875 | BG36: =IFERROR(BG37/(BG34*$Q$3),0) -> 0 | BH36: =BH16 -> Occupancy | BI36: ='Occ. Proj'!$I$20 -> 0.45 | BJ36: ='Occ. Proj'!$I$20 -> 0.45 | BK36: =BK31 -> 0.6 | BL36: =BL31 -> 0.7 | BM36: =BM31 -> 0.75 | BN36: ='Occ. Proj'!$J$20 -> 0.85 | BO36: ='Occ. Proj'!J28 -> 0 | BP36: ='Occ. Proj'!J28 -> 0 | BQ36: =BQ31 -> 0.75 | BR36: =BR31 -> 0.75 | BS36: 0.6 | BT36: =BI36 -> 0.45 | BU36: =IFERROR(BU37/(BU34*$Q$3),0) -> 0 | BV36: =BV16 -> Occupancy
