Workbook

Sheet DEVELOPMENT COSTS
A1: DEVELOPMENT COSTS (REFERENCE & TRAINING) | D1: ↓ ADDITIONAL INSTRUCTIONS / STEPS / INFO BELOW ↓ | E1: YOUR PROJECT NOTES (For Sections on Left):
A2: Reference the Marshall Swift Valuation Guide (Saved in Dropbox: Sage Commercial Team Folder>Market Data>Marshall & Swift)
A3: General Development Costs:
A4: Quality Level: Base Horizontal Const. Costs (Excellent is most common if higher end, and because MVS estimates often come in low with lower grade quality pricing)
B5: MVS Section(s): for Manufactured Housing Parks - Section 63
C6: for quality level tables
B7: Quality Level: Training Video Link (Date Video Last Updated 0/0/0):
A9: Modifiers / Multipliers
B10: Multipliers: Training Video Link (Date Video Last Updated 0/0/0):
B12: MVS Section(s): Section 63 for sites / per site quantity or site square footage
C13: for MVS Zone Multiplier Map, # Space Multiplier, Gross Area per Space Multiplier
B15: MVS Section(s): Section 99 - Nearest State / City / County Multiplier
B16: Construction Class for City/State/Area Modifier (A, B, C, D, S): Training Video Link (Date Video Last Updated 0/0/0):
B18: Site Improvements Costing: Driveway Gates, Yard Improvements / Landscaping, Fences, Pools, Decks, etc.
B19: MVS Section(s): Section 66
A21: Additional Building Improvements and Amenities
B22: Example AI (ChatGPT) Search and Summary Prompt (Copy & Paste):
C23: *NOTE: There are 2 Approaches below, 1 for Web Research Only (tends to be most accurate), and 1 for MVS & Only using Web Research where necessary (good to compare with web research only version).
C24: STEP 1 AI PROMPT (WEB RESEARCH ADDL. BLDG. COSTING *TENDS TO BE MORE IN LINE WITH WHAT WE SEE FOR COSTS IN REAL LIFE):
C25: Resort Description: [TYPE YOUR RESORT SIZE IN ACRES, RESORT UNIT QUANTITY, RV SITE QUANTITY, RESORT QUALITY LEVEL]. I have already projected costs for the horizontal infrastructure construction of the [RV SITES or RV SITES & GLAMPING / LODGING UNITS or GLAMPING / LODGING UNITS], and [I have also estimated the costs for the glamping units themselves. OMIT IF NOT NEEDED FOR RV ONLY RESORTS]. In this message, I am including the list of Additional Building Improvements, Land Improvements, and Amenities for an outdoor hospitality development that requires cost estimates for construction, covering each item in the list, including all materials and labor. If there are also options for pre-built / modular, then include both stick-built and modular options with all details and pricing. Please use any and all legitimate internet resources you can find and use to estimate each item's costs: 1) Per Space Method 2) Calculator Method Quality Level: [TYPE QUALITY LEVEL DESCRIPTION, I.E., LOW, AVERAGE, GOOD, VERY GOOD, HIGH-END, LUXURY, & ANY OHTER DETAILS YOU FIND PERTINENT] I would like you to estimate the appropriate / applicable needed size, linear feet, quantity, and square footage of each item (and provide all those details of what you chose in your estimates), basing your projection for size and quantity on the information I provided about the resort unit and site quantities, resort size, resort area, and resort quality. If you need more information about an item (such as size, type, quality, or square footage) to provide accurate estimates, please ask, but I would prefer you locate the needed information yourself and project all costs, breakdowns, and information requested with citations / sources in one reply. But, I would prefer you locate the needed information yourself and project all costs, breakdowns, and information requested with citations / sources in one reply. I would really like you to find costs through the internet or other resources, and note how you estimated the costs or where you found any hard figures. Generally, I don't need FF&E Costs as we apply a percentage to the construction cost to calculate an overall FF&E Cost. Estimate costs for lighting as appropriate / needed for any pool deck area, pickleball and sports courts, or any other areas deemed in need of nighttime lighting, if appropriate for this resort. Please show the lighting cost for each item type next to, but separate from, the cost of the item itself. Cite your sources and show your work. Citations should be in a format that a human can easily understand. Provide company names used and website URLs, and with Website URLs separate each link in your reply so each can be individually seen by a human for copying and pasting elsewhere without them being grouped together. Here is the list: [TYPE OR PASTE YOUR ADDITIONAL BUILDINGS / AMENITIES LIST] Square Footage and Construction Class (A, B, C, D, S) and Any Special Finishings: [TYPE OR PASTE PER ITEM THE ITEM NAME FROM YOUR LIST WITH SQUARE FOOTAGE, NUMBER OF STORIES, SIZE, TYPE, CONSTRUCTION TYPE A, B, C, D, OR S & ANY SPECIAL FINISHES PREFERRED, OR OTHER HELPUL COSTING INFO YOU HAVE]. The Marshall and Swift Cost Manual is uploaded with this message for you to use. [USE THE ATTACHMENT FUNCTION TO UPLOAD THE CURRENT MARSHALL AND SWIFT COST MANUAL WITH THIS MESSAGE].
C27: STEP 2 AI PROMPT - WEB SEARCH ONLY: [Once you are satisfied with the AI's overall estimates generally, then send this next prompt].
C28: Please utilize the style guide in your saved memory (but add the following items) to now generate an Excel Spreadsheet with the 1st column listing the item you estimated costs for, the 2nd column with the Quantity of the item, 3rd column with Cost Per Item, 4th Column with either Square Feet (SF) of the item or Linear Feet (LF) or other appropriate measure, 5th Columns with Cost / Square Foot ($ / SF) or Cost / Linear Foot ($ / LF), 6th Column With Price Total for the Total Quantity & Overall Cost for that Item and at bottom the Grand Total for Total Quanity and Total Cost of All Items, 7th Column with Notes for where the Costing Came from for Each Line / Row Item (such as company names & website URLs. All links should be separate from each other so I can view, copy and paste each.). All FF&E Costs Estimates - should be on a separate Tab in the same Excel worksheet.
C30: STEP 1 AI PROMPT (MARSHALL & SWIFT ADDL. BLDG. COSTING *TENDS TO BE HIGHER THAN WHAT WE SEE FOR COSTS IN REAL LIFE):
C31: Resort Description: [TYPE YOUR RESORT SIZE IN ACRES, RESORT UNIT QUANTITY, RV SITE QUANTITY, RESORT QUALITY LEVEL]. I have already projected costs for the horizontal infrastructure construction of the RV sites and glamping unit sites using the Marshall and Swift Trailer and Manufactured Housing Park section, and I have also estimated the costs for the glamping units themselves. In this message, I am including the list of Additional Building Improvements, Land Improvements, and Amenities for an outdoor hospitality development that requires cost estimates for construction, covering each item in the list, including all materials and labor. If there are also options for pre-built / modular, then include both stick-built and modular options with all details and pricing. Please use the Marshall and Swift Cost Guide I provided and estimate each item's costs via both methods where possible: 1) Per Space Method 2) Calculator Method Only use the Marshall & Swift Multipliers as appropriate and / or as directed by the M&S Guide for the methods they are meant to apply to in the estimate calculations. Region Multiplier (M&S): [TYPE THE M&S REGION OR ACTUAL MULTIPLIER #] Local Cost Multiplier (M&S): [TYPE THE CITY, COUNTY, AND / OR STATE YOU'VE CHOSEN FROM M&S OR ACTUAL MULTIPLIER #] Number of Spaces Multiplier: [TYPE THE MULTIPLIER # YOU'VE CHOSEN] SF Square Foot / Space Multiplier: [TYPE THE MULTIPLIER # YOU'VE CHOSEN] Quality Level (M&S): [TYPE QUALITY LEVEL YOU'VE CHOSEN FROM M&S] I would like you to estimate the appropriate / applicable needed size, linear feet, quantity, and square footage of each item (and provide all those details of what you chose in your estimates), basing your projection for size and quantity on the information I provided about the resort unit and site quantities, resort size, resort area, and resort quality. If you need more information about an item (such as size, type, quality, or square footage) to provide accurate estimates, please ask, but I would prefer you locate the needed information yourself and project all costs, breakdowns, and information requested with citations / sources in one reply. If there is an item that cannot be estimated using the Marshall and Swift Costing Guide, please let me know. But, I would like you to find costs through the internet or other resources, and note how you estimated the costs or where you found any hard figures. Generally, I don't need FF&E Costs as we apply a percentage to the construction cost to calculate an overall FF&E Cost. Estimate costs for lighting as appropriate / needed for any pool deck area, pickleball and sports courts, or any other areas deemed in need of nighttime lighting, if appropriate for this resort. Please show the lighting cost for each item type next to, but separate from, the cost of the item itself. I want you to choose the Construction Class in the M&S Guide and the Finishings based on the quality level I provided with your best educated choice and report what you chose for any items they apply to. Cite your sources and show your work. Citations should be in a format that a human can easily understand. Provide Section # and Page Number in the Section for Marshall Swift Cost Guide references and calculations, and with Website URLs separate each link in your reply so each can be individually seen by a human for copying and pasting elsewhere without them being grouped together. Here is the list: [TYPE OR PASTE YOUR ADDITIONAL BUILDINGS / AMENITIES LIST] Square Footage and Construction Class (A, B, C, D, S) and Any Special Finishings: [TYPE OR PASTE PER ITEM THE ITEM NAME FROM YOUR LIST WITH SQUARE FOOTAGE, NUMBER OF STORIES, SIZE, TYPE, CONSTRUCTION TYPE A, B, C, D, OR S & ANY SPECIAL FINISHES PREFERRED, OR OTHER HELPUL COSTING INFO YOU HAVE]. The Marshall and Swift Cost Manual is uploaded with this message for you to use. [USE THE ATTACHMENT FUNCTION TO UPLOAD THE CURRENT MARSHALL AND SWIFT COST MANUAL WITH THIS MESSAGE].
C33: STEP 2 AI PROMPT - MARSHALL & SWIFT WITH SOME WEB SEARCH AS NECESSARY: [Once you are satisfied with the AI's overall estimates generally, then send this next prompt].
C34: Please utilize the style guide in your saved memory (but add the following items) to now generate an Excel Spreadsheet with the 1st column listing the item you estimated costs for, the 2nd column with the Quantity of the item, 3rd column with Cost Per Item, 4th Column with either Square Feet (SF) of the item or Linear Feet (LF) or other appropriate measure, 5th Columns with Cost / Square Foot ($ / SF) or Cost / Linear Foot ($ / LF), 6th Column With Price Total for the Total Quantity & Overall Cost for that Item and at bottom the Grand Total for Total Quanity and Total Cost of All Items, 7th Column with Notes for where the Costing Came from for Each Line / Row Item (ie, MVS for Marshall & Swift, or other Sources Cited, such as company names & website URLs. All links should be separate from each other so I can view, copy and paste each.). All FF&E Costs Estimates - should be on a separate Tab in the same Excel worksheet.
A36: Unit Costs (Glamping / Lodging)
B37: Unit Costs (Glamping / Lodging): Training Video Link (Date Video Last Updated 0/0/0):
C38: *NOTE: First check to see if the client can or has provided actual unit cost quotes.
C39: Research cost guides from manufacturers or Sage unit cost reference materials, OR the Walden Unit Cost Guide
C40: If Stick-built: Could use MVS and local / construction class multiplier (sometimes comes out high)
B42: Example AI (ChatGPT) Search and Summary Prompt (Copy & Paste):
C43: Estimate the cost for materials and labor to both stick-build or purchase modular / pre-built and install for the following units and specifications: [TYPE or LIST GLAMPING / LODGING UNIT TYPE(S) & QUANTITY OF EACH, TYPE QUALITY LEVEL EACH, TYPE SIZE IN SF EACH, & ADD DECKS / PLATFORM WHERE NEEDED PER UNIT TYPE]. Please exclude the horizontal site work needed for infrastructure, as I have already estimated this separately. Cite your sources and findings and show your work for any calculations or estimates.
B45: Example AI (ChatGPT) Search and Summary Prompt (Copy & Paste):
B46: Example AI (ChatGPT AGENT MODE) Search and Summary Prompt (Copy & Paste):

Sheet Site Dev Cost
F2: Excellent | H2: <---DROPDOWN BOX
B3: Site Development Costs | C3: # Sites | D3: P. Site | E3: Total | F3: Quality Level / Notes | H3: DO NOT CHANGE
B4: Number of Units/Sites | C4: ='[1]ToT (Intake Form)'!C53 -> 8 | H4: Excellent | I4: Good | J4: Average | K4: Low | L4: Cheap
B5: Engineering | C5: =C4 -> 8 | D5: =IF(F$2="Excellent", H5, IF(F$2="Good", I5, IF(F$2="Average", J5, IF(F$2="Low", K5, IF(F$2="Cheap", L5, ""))))) -> 2550 | E5: =C5*D5 -> 20400 | F5: =F$2 -> Excellent | H5: 2550 | I5: 1920 | J5: 1320 | K5: 935 | L5: 482 | M5: Engineering
B6: Grading | C6: =C5 -> 8 | D6: =IF(F$2="Excellent", H6, IF(F$2="Good", I6, IF(F$2="Average", J6, IF(F$2="Low", K6, IF(F$2="Cheap", L6, ""))))) -> 2430 | E6: =C6*D6 -> 19440 | F6: =F$2 -> Excellent | H6: 2430 | I6: 1750 | J6: 1140 | K6: 765 | L6: 412 | M6: Grading
B7: Street Paving | C7: =C6 -> 8 | D7: =IF(F$2="Excellent", H7, IF(F$2="Good", I7, IF(F$2="Average", J7, IF(F$2="Low", K7, IF(F$2="Cheap", L7, ""))))) -> 3675 | E7: =C7*D7 -> 29400 | F7: =F$2 -> Excellent | H7: 3675 | I7: 2775 | J7: 1960 | K7: 1510 | L7: 965 | M7: Street Paving
B8: Patios and Walks | C8: =C7 -> 8 | D8: =IF(F$2="Excellent", H8, IF(F$2="Good", I8, IF(F$2="Average", J8, IF(F$2="Low", K8, IF(F$2="Cheap", L8, ""))))) -> 3200 | E8: =C8*D8 -> 25600 | F8: =F$2 -> Excellent | H8: 3200 | I8: 2170 | J8: 1440 | K8: 975 | L8: 545 | M8: Patios and Walks
B9: Septic | C9: =C8 -> 8 | D9: =IF(F$2="Excellent", H9, IF(F$2="Good", I9, IF(F$2="Average", J9, IF(F$2="Low", K9, IF(F$2="Cheap", L9, ""))))) -> 2430 | E9: =C9*D9 -> 19440 | F9: =F$2 -> Excellent | H9: 2430 | I9: 2040 | J9: 1600 | K9: 1090 | L9: 750 | M9: Sewer
B10: Water | C10: =C9 -> 8 | D10: =IF(F$2="Excellent", H10, IF(F$2="Good", I10, IF(F$2="Average", J10, IF(F$2="Low", K10, IF(F$2="Cheap", L10, ""))))) -> 2390 | E10: =C10*D10 -> 19120 | F10: =F$2 -> Excellent | H10: 2390 | I10: 1830 | J10: 1300 | K10: 975 | L10: 595 | M10: Water
B11: Gas | C11: =C10 -> 8 | D11: N/A | E11: N/A | F11: =F$2 -> Excellent | H11: 1540 | I11: 1120 | J11: 695 | K11: 460 | L11: 0 | M11: Gas
B12: Electrical | C12: =C11 -> 8 | D12: =IF(F$2="Excellent", H12, IF(F$2="Good", I12, IF(F$2="Average", J12, IF(F$2="Low", K12, IF(F$2="Cheap", L12, ""))))) -> 4050 | E12: =C12*D12 -> 32400 | F12: =F$2 -> Excellent | H12: 4050 | I12: 3025 | J12: 2100 | K12: 1450 | L12: 810 | M12: Electrical
B13: Buildings | C13: =C12 -> 8 | D13: N/A | E13: N/A | F13: Separate Calc. | H13: 5300 | I13: 4725 | J13: 3700 | K13: 2900 | L13: 2170 | M13: Buildings
B14: Miscellaneous | C14: =C13 -> 8 | D14: =IF(F$2="Excellent", H14, IF(F$2="Good", I14, IF(F$2="Average", J14, IF(F$2="Low", K14, IF(F$2="Cheap", L14, ""))))) -> 3225 | E14: =C14*D14 -> 25800 | F14: =F$2 -> Excellent | H14: 3225 | I14: 2250 | J14: 1260 | K14: 780 | L14: 323 | M14: Miscellaneous
B15: Subtotal Cost per Unit | D15: =SUM(D5:D14) -> 23950 | E15: =SUM(E5:E14) -> 191600
H16: =SUM(H5:H14) -> 30790 | I16: =SUM(I5:I14) -> 23605 | J16: =SUM(J5:J14) -> 16515 | K16: =SUM(K5:K14) -> 11840 | L16: =SUM(L5:L14) -> 7052
B17: Cost Multipliers | C17: Area / # / SF | D17: Multipliers | F17: Notes
B18: Current Cost Multiplier | C18: Western | D18: 1.07 | E18: =D18 -> 1.07 | F18: MVS
B19: Local Multiplier | C19: ='[1]Excel Input'!C6 -> Subject City | D19: 0.94 | E19: =D19 -> 0.94 | F19: MVS
B20: Number of Spaces Multiplier | C20: =C5 -> 8 | D20: 1.18 | E20: =D20 -> 1.18 | F20: MVS
B21: Average Area (SF) per Space Multiplier | C21: ='[1]ToT (Intake Form)'!C19/'[1]ToT (Intake Form)'!C53 -> 201465 | D21: 0.97 | E21: =D21 -> 0.97 | F21: MVS
B22: Additional Multiplier | D22: 1 | E22: =D22 -> 1 | F22: Additional Multiplier
B23: Net Multiplier | D23: =D18*D19*D20*D21*D22 -> 1.1512387 | E23: =D23 -> 1.1512387
B25: Site Dev Costs (w/ Multiplier) | C25: # Sites | D25: P. Space | E25: $ Total | F25: Quality Level / Notes
B26: Engineering | C26: =C5 -> 8 | D26: =$D$23*D5 -> 2935.6586 | E26: =$E$23*E5 -> 23485.269 | F26: =F5 -> Excellent
B27: Grading | C27: =C6 -> 8 | D27: =$D$23*D6 -> 2797.51 | E27: =$E$23*E6 -> 22380.08 | F27: =F6 -> Excellent
B28: Street Paving | C28: =C7 -> 8 | D28: =$D$23*D7 -> 4230.8021 | E28: =$E$23*E7 -> 33846.417 | F28: =F7 -> Excellent
B29: Patios and Walks | C29: =C8 -> 8 | D29: =$D$23*D8 -> 3683.9638 | E29: =$E$23*E8 -> 29471.71 | F29: =F8 -> Excellent
B30: Sewer | C30: =C9 -> 8 | D30: =$D$23*D9 -> 2797.51 | E30: =$E$23*E9 -> 22380.08 | F30: =F9 -> Excellent
B31: Water | C31: =C10 -> 8 | D31: =$D$23*D10 -> 2751.4604 | E31: =$E$23*E10 -> 22011.684 | F31: =F10 -> Excellent
B32: Gas | C32: =C11 -> 8 | D32: =D11 -> N/A | E32: =E11 -> N/A | F32: =F11 -> Excellent
B33: Electrical | C33: =C12 -> 8 | D33: =$D$23*D12 -> 4662.5167 | E33: =$E$23*E12 -> 37300.133 | F33: =F12 -> Excellent
B34: =B13 -> Buildings | C34: =C13 -> 8 | D34: =D13 -> N/A | E34: =E13 -> N/A | F34: =F13 -> Separate Calc.
B35: =B14 -> Miscellaneous | C35: =C14 -> 8 | D35: =$D$23*D14 -> 3712.7447 | E35: =$E$23*E14 -> 29701.958 | F35: =F14 -> Excellent
B36: Total Site Dev Costs (w/ Multiplier) | D36: =SUM(D26:D35) -> 27572.166 | E36: =SUM(E26:E35) -> 220577.33
B38: Unit Costs | C38: # | D38: P. Unit | E38: Total | F38: Notes
B39: ='[1]ToT (Intake Form)'!C42 -> Cabin 1 | C39: ='[1]ToT (Intake Form)'!C41 -> 1 | D39: 120000 | E39: =C39*D39 -> 120000 | F39: ='[1]ToT (Intake Form)'!C43 -> 399 SF park model with a queen bed, a bedroom with a bunk bed, living area, full, kitchen, full bathroom, and covered porch.
B40: ='[1]ToT (Intake Form)'!C45 -> Cabin 2 | C40: ='[1]ToT (Intake Form)'!C44 -> 1 | D40: 90000 | E40: =C40*D40 -> 90000 | F40: ='[1]ToT (Intake Form)'!C46 -> Unit Description
B41: ='[1]ToT (Intake Form)'!C48 -> Cabin 3 | C41: ='[1]ToT (Intake Form)'!C47 -> 1 | D41: 110000 | E41: =C41*D41 -> 110000 | F41: ='[1]ToT (Intake Form)'!C49 -> Unit Description
B42: Total Unit Costs | C42: =SUM(C39:C41) -> 3 | E42: =SUM(E39:E41) -> 320000
B44: Total Site Development Costs + Unit Costs | E44: =SUM(E36,E39:E41) -> 540577.33

Sheet Add. Bldg Improv.
B2: Additional Structures / Site Improvements | C2: SF | D2: $ / SF | E2: Total | F2: Notes
B3: Clubhouse with laundry and showers | C3: ='[1]Excel Input'!C49 -> 3000 | D3: 300 | E3: =C3*D3 -> 900000 | F3: Based on MVS + Client Description
B4: Swimming pool with deck | C4: 5500 | D4: =E4/C4 -> 109.09091 | E4: 600000 | F4: SOA Estimate Based Client Description
B5: Cabana with hot tub | C5: 2249 | D5: =E5/C5 -> 56.669631 | E5: =(2249*50)+15000 -> 127450 | F5: SOA Estimate Based Client Description
B6: 4 pickleball courts | C6: 4 | E6: =25000*4 -> 100000 | F6: SOA Estimate Based Client Description
B7: Outdoor cabana with kitchen | C7: 500 | D7: 125 | E7: =D7*C7 -> 62500 | F7: SOA Estimate Based Client Description
B8: 2 shade cabanas | C8: 750 | D8: 50 | E8: =D8*C8 -> 37500 | F8: SOA Estimate Based Client Description
B9: 2 bathhouses with laundry | C9: 2000 | D9: 300 | E9: =D9*C9 -> 600000 | F9: SOA Estimate Based Client Description
B10: Drive-thru RV wash | C10: 1 | E10: 400000 | F10: SOA Estimate Based Client Description
B11: Covered dog wash area | C11: 1 | E11: 35000 | F11: SOA Estimate Based Client Description
B12: Two-story maintenance storage shops | C12: 1800 | D12: 100 | E12: =D12*C12 -> 180000 | F12: SOA Estimate Based Client Description
B13: Outdoor fun park area | C13: 4500 | D13: 25 | E13: =D13*C13 -> 112500 | F13: SOA Estimate Based Client Description
B14: 1 mile walking trail | C14: 1 | E14: 2000 | F14: SOA Estimate Based Client Description
B15: Total Add. Bldg Improv. | C15: =SUM(C2:C13) -> 20305 | D15: =E15/C15 -> 155.37799 | E15: =SUM(E2:E13) -> 3154950
B18: <--- Replacement Reserves % is now being set in the Monthly Pro Forma Assumptions, generally 3% starting Year 3, may be higher % up to 5% if lots of frequently replaced items such as Canvas for Safari Tents, etc.
B21: Personal Property | E21: Total
B22: Park Model Cabins | E22: ='Site Dev Cost'!E39 -> 120000 | H22: ??? Aren't we still using the 12.5% of Addl. Bldg. Improv. And 12.5% of Unit Costs to estimate Personal Property $ on the Total Project Cost Tab???
B23: FF&E | E23: ='Total Proj. Cost'!D10 -> 434368.75
B25: Total Personal Property / FF&E | E25: =E22+E23+E24 -> 554368.75
J26: Zook Cabin Pricing:
J27: The prices listed below are if someone orders only one Park Model. We do offer discounts for multiples.
J28: Here is information and pricing on our RV certified Park Model Cabins. See the pricing and availability below.
J29: Please note that the pricing includes all the appliances, mini split heating/cooling unit, and delivery to Salt Lake City, UT.
J30: Aspen Park Model – Click here to see this model – Price: $122,300
J31: Studio Park Model – Click here to see this model – Price: $103,700
J32: Cascade Park Model – Click here to see this cabin – Price: $138,800
J33: Pocono Park Model – Click here to see this cabin – Price: $122,500
J34: Rockwood Park Model – Click here to see this cabin – Price: $159,200
J35: Alpine Park Model – Click here to see this cabin – Price: $147,400
J36: A-Frame Park Model – Click here to see this cabin – Price: $155,500
J37: Luna Park Model – Click here to see this cabin – Price: $153,900
... J39: Each unit comes with a title and VIN.

Sheet Total Proj. Cost
B2: Total Project Cost | C2: $/Site or % | D2: Total | E2: % | F2: Notes
B3: Number of Sites (RV & Lodging) | C3: ='Site Dev Cost'!C4 -> 8 | H3: <= If no lodging units or glamping units (RV Only), then remove the word 'lodging' from line item label
B4: Total Site Development Costs | C4: =D4/C3 -> 27572.166 | D4: ='Site Dev Cost'!E36 -> 220577.33 | E4: =D4/D8 -> 0.059687647
B5: Number of Lodging Units | C5: =SUM('[1]ToT (Intake Form)'!C41,'[1]ToT (Intake Form)'!C44,'[1]ToT (Intake Form)'!C47) -> 3 | H5: <= If no lodging units or glamping units (RV Only), then zero out and hide the line item
B6: Unit Costs (Lodging) | C6: =D6/C5 -> 106666.67 | D6: ='Site Dev Cost'!E42 -> 320000 | E6: =D6/D7 -> 0.10142791 | H6: <= If no lodging units or glamping units (RV Only), then zero out and hide the line item
B7: Total Additional Building Improvements | C7: =D7/C3 -> 394368.75 | D7: ='Add. Bldg Improv.'!E15 -> 3154950 | E7: =D7/D8 -> 0.85372119
B8: Total Hard Costs | C8: =D8/C3 -> 461940.92 | D8: =SUM(D3:D7) -> 3695527.3 | E8: =D8/D8 -> 1
B10: FF&E Addtl. Bldg + Lodging Units | C10: 0.125 | D10: =(D7+D6)*C10 -> 434368.75
B11: Soft Costs (Percentage of Hard Costs) | C11: 0.1 | D11: =C11*D8 -> 369552.73 | F11: =F12 -> Industry Average
B12: Hard Cost Contingency (Percentage of Hard Costs) | C12: 0.1 | D12: =D8*C12 -> 369552.73 | F12: =F13 -> Industry Average
B13: Pre-opening Expense | C13: =D13/'Site Dev Cost'!C4 -> 13858.227 | D13: =0.03*D8 -> 110865.82 | F13: Industry Average | H13: This can vary | J13: <= Pre-opening Expense Estimate: Approximately 2-5% of hard costs give or take based on the complexity of the project.
B14: 18-Month Interest Reserve | D14: =IFERROR([1]IRR!M27,0) -> 1021028 | E14: =D14/$D$16 -> 0.095415192 | F14: Industry Average | H14: This can vary it can also be removed if it is profitable early on
B15: Land Acquisition Costs | C15: =D15/C3 -> 587500 | D15: ='[1]ToT (Intake Form)'!C74 -> 4700000 | E15: =D15/$D$16 -> 0.43921558 | F15: Client Provided Figure
B16: Total Development Cost | C16: =D16/C3 -> 1337611.9 | D16: =SUM(D8:D15) -> 10700895 | E16: =D16/D16 -> 1

Sheet Construction Comps
B2: Construction Cost Comparables
D4: 1 | G4: 2 | J4: 3 | M4: 4 | P4: 5 | S4: 6
C6: Location | D6: South | G6: Southeast | J6: Southeast | M6: Southeast | P6: Southwest | S6: Southwest
C7: Quality | D7: Very High | G7: High | J7: Very High | M7: High | P7: High | S7: Standard
C8: Amenity Level | D8: High | G8: High | J8: Standard | M8: High | P8: High | S8: Standard
C9: Cost Year | D9: 2024 | G9: 2023 | J9: 2021 | M9: 2021 | P9: 2024 | S9: 2024
C10: Inflation Adjustment * | D10: 0.03 | G10: 0.060379223 | J10: 0.1923817 | M10: =J10 -> 0.1923817 | P10: =D10 -> 0.03 | S10: 0.03
D11: =D10+1 -> 1.03 | G11: =G10+1 -> 1.0603792 | J11: =J10+1 -> 1.1923817 | M11: =M10+1 -> 1.1923817 | P11: =P10+1 -> 1.03 | S11: =S10+1 -> 1.03
C12: Total Sites / Units | D12: 141 | G12: 102 | J12: 248 | M12: 400 | P12: 138 | S12: 149
C13: # of RV Sites | D13: 141 | G13: 102 | J13: 152 | M13: 280 | P13: 123 | S13: 149
C14: # of Lodging Units | D14: =D12-D13 -> 0 | G14: =G12-G13 -> 0 | J14: =J12-J13 -> 96 | M14: =M12-M13 -> 120 | P14: =P12-P13 -> 15 | S14: =S12-S13 -> 0
J15: Phase 1 of Project**
C16: Total Project Cost | D16: Total | E16: Per Site | F16: % | G16: Total | H16: Per Site | I16: % | J16: Total | K16: Per Site | L16: % | M16: Total | N16: Per Site | O16: % | P16: Total | Q16: Per Site | R16: % | S16: Total | T16: Per Site | U16: %
C17: Total Site Development | G17: =H17*G12 -> 4110029.9 | H17: =38000*$G$11 -> 40294.41 | I17: =G17/G20 -> 0.62556488 | J17: =8992990*$J$11 -> 10723077 | K17: =J17/$J$12 -> 43238.213 | L17: =J17/J20 -> 0.54462711 | M17: =12904752*M11 -> 15387390 | N17: =M17/$M$12 -> 38468.475 | O17: =M17/M20 -> 0.4985967 | S17: =(5751283-60000-200000-350000-45000)*1.03 -> 5249171.5 | T17: =S17/S13 -> 35229.339 | U17: =S17/S20 -> 0.93573599
C18: Tot. Add'l Bldg. Improv. | G18: =(820000+1500000)*$G$11 -> 2460079.8 | H18: =G18/$G$12 -> 24118.429 | I18: =G18/G20 -> 0.37443512 | J18: =(8778345-J19)*$J$11 -> 1161626.3 | K18: =J18/$J$12 -> 4683.9771 | L18: =J18/J20 -> 0.058999222 | M18: =(14755000-M19)*M11 -> 4456399.1 | N18: =M18/$M$12 -> 11140.998 | O18: =M18/M20 -> 0.14440044 | S18: =350000*1.03 -> 360500 | T18: =S18/S13 -> 2419.4631 | U18: =S18/S20 -> 0.064264013
C19: Lodging Unit Costs | D19: 0 | E19: 0 | G19: 0 | H19: 0 | J19: =(85*77000)*$J$11 -> 7804138.2 | K19: =J19/J14 -> 81293.107 | L19: =J19/J20 -> 0.39637367 | M19: =(120*77000)*M11 -> 11017607 | N19: =M19/M14 -> 91813.391 | O19: =M19/M20 -> 0.35700287 | S19: 0 | T19: 0
C20: Total Hard Costs | D20: =16574904*$D$11 -> 17072151 | E20: =D20/$D$12 -> 121079.09 | F20: =D20/D26 -> 0.9209926 | G20: =SUM(G17:G19) -> 6570109.7 | H20: =G20/$G$12 -> 64412.84 | I20: =G20/G26 -> 0.53219277 | J20: =SUM(J17:J19) -> 19688841 | K20: =J20/$J$12 -> 79390.489 | L20: =J20/J26 -> 0.56144355 | M20: =SUM(M17:M19) -> 30861396 | N20: =M20/$M$12 -> 77153.491 | O20: =M20/M26 -> 0.63800756 | P20: =11603414*$P$11 -> 11951516 | Q20: =P20/$P$12 -> 86605.191 | R20: =P20/P26 -> 0.71133544 | S20: =S17+S18 -> 5609671.5 | T20: =S20/S13 -> 37648.802 | U20: =S20/S26 -> 0.69287545
C21: Soft Costs | D21: =1421879*$D$11 -> 1464535.4 | E21: =D21/$D$12 -> 10386.776 | F21: =D21/D26 -> 0.079007398 | G21: =(250000+204890)*$G$11 -> 482355.9 | H21: =G21/$G$12 -> 4728.9795 | I21: =G21/G26 -> 0.039071848 | J21: =2044315*$J$11 -> 2437603.8 | K21: =J21/$J$12 -> 9829.0476 | L21: =J21/J26 -> 0.069510283 | M21: =2185000*M11 -> 2605354 | N21: =M21/$M$12 -> 6513.3851 | O21: =M21/M26 -> 0.05386132 | P21: =988021*$P$11 -> 1017661.6 | Q21: =P21/$P$12 -> 7374.3596 | R21: =P21/P26 -> 0.060569618 | S21: =(1981624-662282)*1.03 -> 1358922.3 | T21: =S21/S13 -> 9120.2836 | U21: =S21/S26 -> 0.16784652
C22: Hard Cost Contingency | G22: =650000*$G$11 -> 689246.49 | H22: =G22/$G$12 -> 6757.3186 | I22: =G22/G26 -> 0.055830423 | J22: =58188*$J$11 -> 69382.307 | K22: =J22/$J$12 -> 279.76737 | L22: =J22/J26 -> 0.0019784937 | M22: =1000000*M11 -> 1192381.7 | N22: =M22/$M$12 -> 2980.9543 | O22: =M22/M26 -> 0.02465049 | S22: =662282*1.03 -> 682150.46 | T22: =S22/S13 -> 4578.191 | U22: =S22/S26 -> 0.084255434
C23: Pre-opening Expense | G23: =2000008*$G$11 -> 2120766.9 | H23: =G23/$G$12 -> 20791.833 | I23: =G23/G26 -> 0.1717866
C24: Interest Reserve | J24: =795553*$J$11 -> 948602.84 | K24: =J24/$J$12 -> 3825.0115 | L24: =J24/J26 -> 0.027050193 | M24: =1500000*M11 -> 1788572.6 | N24: =M24/$M$12 -> 4471.4314 | O24: =M24/M26 -> 0.036975735 | P24: =728780*$P$11 -> 750643.4 | Q24: =P24/$P$12 -> 5439.4449 | R24: =P24/P26 -> 0.044677113
C25: Land Acquisition Costs | G25: =(2325000+16500)*$G$11 -> 2482878 | H25: =G25/$G$12 -> 24341.941 | I25: =G25/G26 -> 0.20111836 | J25: =10000000*$J$11 -> 11923817 | K25: =J25/$J$12 -> 48079.907 | L25: =J25/J26 -> 0.34001748 | M25: =10000000*M11 -> 11923817 | N25: =M25/$M$12 -> 29809.543 | O25: =M25/M26 -> 0.2465049 | P25: =2991940*$P$11 -> 3081698.2 | Q25: =P25/$P$12 -> 22331.146 | R25: =P25/P26 -> 0.18341783 | S25: =432500*1.03 -> 445475 | T25: =S25/$P$12 -> 3228.0797 | U25: =S25/S26 -> 0.055022596
C26: Total Development Cost | D26: =SUM(D20:D25) -> 18536686 | E26: =D26/$D$12 -> 131465.86 | G26: =SUM(G20:G25) -> 12345357 | H26: =G26/$G$12 -> 121032.91 | J26: =SUM(J20:J25) -> 35068247 | K26: =J26/$J$12 -> 141404.22 | M26: =SUM(M20:M25) -> 48371522 | N26: =M26/$M$12 -> 120928.8 | P26: =SUM(P20:P25) -> 16801520 | Q26: =P26/$P$12 -> 121750.14 | S26: =SUM(S20:S25) -> 8096219.2 | T26: =S26/$P$12 -> 58668.255
C28: * All costs have been adjusted for inflation to reflect 2025 values.
C29: ** Phase 1 included infrastructure costs for Phase 2. Increasing the development cost per site.
C30: NOTE: Lodging Unit Costs - the majority of the comparable RV resorts with lodging unit cost data have very high lodging unit quantities, which tends to lower the cost per unit.

Sheet Construction Summary
B2: Comparable Construction Cost Summary (per Site)
C3: Per Site | F3: % Total Development
C4: Min | D4: Max | E4: Average | F4: Min | G4: Max | H4: Average
B5: Total Site Development | C5: =MIN('Construction Comps'!E17,'Construction Comps'!H17,'Construction Comps'!K17,'Construction Comps'!N17,'Construction Comps'!Q17,'Construction Comps'!T17) -> 35229.339 | D5: =MAX(('Construction Comps'!E17,'Construction Comps'!H17,'Construction Comps'!K17,'Construction Comps'!N17,'Construction Comps'!Q17,'Construction Comps'!T17, 'Construction Comps'!T17)) -> 43238.213 | E5: =AVERAGE('Construction Comps'!E17,'Construction Comps'!H17,'Construction Comps'!K17,'Construction Comps'!N17,'Construction Comps'!Q17,'Construction Comps'!T17, 'Construction Comps'!T17) -> 38491.955
B6: Tot. Add'l Bldg. Improv. | C6: =MIN('Construction Comps'!E18,'Construction Comps'!H18,'Construction Comps'!K18,'Construction Comps'!N18,'Construction Comps'!Q18,'Construction Comps'!T18) -> 2419.4631 | D6: =MAX(('Construction Comps'!E18,'Construction Comps'!H18,'Construction Comps'!K18,'Construction Comps'!N18,'Construction Comps'!Q18,'Construction Comps'!T18, 'Construction Comps'!T18)) -> 24118.429 | E6: =AVERAGE('Construction Comps'!E18,'Construction Comps'!H18,'Construction Comps'!K18,'Construction Comps'!N18,'Construction Comps'!Q18,'Construction Comps'!T18,'Construction Comps'!T18) -> 8956.4661
B7: Lodging Unit Costs | C7: =MIN('Construction Comps'!E19,'Construction Comps'!H19,'Construction Comps'!K19,'Construction Comps'!N19,'Construction Comps'!Q19) -> 0 | D7: =MAX(('Construction Comps'!E19,'Construction Comps'!H19,'Construction Comps'!K19,'Construction Comps'!N19,'Construction Comps'!Q19, 'Construction Comps'!T20)) -> 91813.391 | E7: =AVERAGE('Construction Comps'!K19,'Construction Comps'!N19,'Construction Comps'!Q19) -> 86553.249
B8: Total Hard Cost per Site | C8: =MIN('Construction Comps'!E20,'Construction Comps'!H20,'Construction Comps'!K20,'Construction Comps'!N20,'Construction Comps'!Q20, 'Construction Comps'!T20) -> 37648.802 | D8: =MAX(('Construction Comps'!E20,'Construction Comps'!H20,'Construction Comps'!K20,'Construction Comps'!N20,'Construction Comps'!Q20, 'Construction Comps'!T20)) -> 121079.09 | E8: =AVERAGE('Construction Comps'!E20,'Construction Comps'!H20,'Construction Comps'!K20,'Construction Comps'!N20,'Construction Comps'!Q20, 'Construction Comps'!T20) -> 77714.983 | F8: =MIN('Construction Comps'!F20,'Construction Comps'!I20,'Construction Comps'!L20,'Construction Comps'!O20,'Construction Comps'!R20, 'Construction Comps'!U20) -> 0.53219277 | G8: =MAX('Construction Comps'!F20,'Construction Comps'!I20,'Construction Comps'!L20,'Construction Comps'!O20,'Construction Comps'!R20, 'Construction Comps'!U20) -> 0.9209926 | H8: =AVERAGE('Construction Comps'!F20,'Construction Comps'!I20,'Construction Comps'!L20,'Construction Comps'!O20,'Construction Comps'!R20,'Construction Comps'!U20) -> 0.67614123
B9: Soft Costs | C9: =MIN('Construction Comps'!E21,'Construction Comps'!H21,'Construction Comps'!K21,'Construction Comps'!N21,'Construction Comps'!Q21,'Construction Comps'!T21) -> 4728.9795 | D9: =MAX(('Construction Comps'!E21,'Construction Comps'!H21,'Construction Comps'!K21,'Construction Comps'!N21,'Construction Comps'!Q21, 'Construction Comps'!T21)) -> 10386.776 | E9: =AVERAGE('Construction Comps'!E21,'Construction Comps'!H21,'Construction Comps'!K21,'Construction Comps'!N21,'Construction Comps'!Q21,'Construction Comps'!T21) -> 7992.1385 | F9: =MIN('Construction Comps'!F21,'Construction Comps'!I21,'Construction Comps'!L21,'Construction Comps'!O21,'Construction Comps'!R21, 'Construction Comps'!U21) -> 0.039071848 | G9: =MAX('Construction Comps'!F21,'Construction Comps'!I21,'Construction Comps'!L21,'Construction Comps'!O21,'Construction Comps'!R21, 'Construction Comps'!U21) -> 0.16784652 | H9: =AVERAGE('Construction Comps'!F21,'Construction Comps'!I21,'Construction Comps'!L21,'Construction Comps'!O21,'Construction Comps'!R21,'Construction Comps'!U21) -> 0.078311165
B10: Hard Cost Contingency | C10: =MIN('Construction Comps'!E22,'Construction Comps'!H22,'Construction Comps'!K22,'Construction Comps'!N22,'Construction Comps'!Q22,'Construction Comps'!T22) -> 279.76737 | D10: =MAX(('Construction Comps'!E22,'Construction Comps'!H22,'Construction Comps'!K22,'Construction Comps'!N22,'Construction Comps'!Q22, 'Construction Comps'!T22)) -> 6757.3186 | E10: =AVERAGE('Construction Comps'!E22,'Construction Comps'!H22,'Construction Comps'!K22,'Construction Comps'!N22,'Construction Comps'!Q22,'Construction Comps'!T22) -> 3649.0578 | F10: =MIN('Construction Comps'!F22,'Construction Comps'!I22,'Construction Comps'!L22,'Construction Comps'!O22,'Construction Comps'!R22, 'Construction Comps'!U22) -> 0.0019784937 | G10: =MAX('Construction Comps'!F22,'Construction Comps'!I22,'Construction Comps'!L22,'Construction Comps'!O22,'Construction Comps'!R22, 'Construction Comps'!U22) -> 0.084255434 | H10: =AVERAGE('Construction Comps'!F22,'Construction Comps'!I22,'Construction Comps'!L22,'Construction Comps'!O22,'Construction Comps'!R22,'Construction Comps'!U22) -> 0.04167871
B11: Pre-opening Expense | C11: =MIN('Construction Comps'!E23,'Construction Comps'!H23,'Construction Comps'!K23,'Construction Comps'!N23,'Construction Comps'!Q23) -> 20791.833 | D11: =MAX(('Construction Comps'!E23,'Construction Comps'!H23,'Construction Comps'!K23,'Construction Comps'!N23,'Construction Comps'!Q23)) -> 20791.833 | E11: =AVERAGE('Construction Comps'!E23,'Construction Comps'!H23,'Construction Comps'!K23,'Construction Comps'!N23,'Construction Comps'!Q23) -> 20791.833 | F11: =MIN('Construction Comps'!F23,'Construction Comps'!I23,'Construction Comps'!L23,'Construction Comps'!O23,'Construction Comps'!R23) -> 0.1717866 | G11: =MAX('Construction Comps'!F23,'Construction Comps'!I23,'Construction Comps'!L23,'Construction Comps'!O23,'Construction Comps'!R23) -> 0.1717866 | H11: =AVERAGE('Construction Comps'!F23,'Construction Comps'!I23,'Construction Comps'!L23,'Construction Comps'!O23,'Construction Comps'!R23) -> 0.1717866
B12: Interest Reserve | C12: =MIN('Construction Comps'!E24,'Construction Comps'!H24,'Construction Comps'!K24,'Construction Comps'!N24,'Construction Comps'!Q24) -> 3825.0115 | D12: =MAX(('Construction Comps'!E24,'Construction Comps'!H24,'Construction Comps'!K24,'Construction Comps'!N24,'Construction Comps'!Q24)) -> 5439.4449 | E12: =AVERAGE('Construction Comps'!E24,'Construction Comps'!H24,'Construction Comps'!K24,'Construction Comps'!N24,'Construction Comps'!Q24) -> 4578.6293 | F12: =MIN('Construction Comps'!F24,'Construction Comps'!I24,'Construction Comps'!L24,'Construction Comps'!O24,'Construction Comps'!R24) -> 0.027050193 | G12: =MAX('Construction Comps'!F24,'Construction Comps'!I24,'Construction Comps'!L24,'Construction Comps'!O24,'Construction Comps'!R24) -> 0.044677113 | H12: =AVERAGE('Construction Comps'!F24,'Construction Comps'!I24,'Construction Comps'!L24,'Construction Comps'!O24,'Construction Comps'!R24) -> 0.036234347
B13: Land Acquisition Costs | C13: =MIN('Construction Comps'!E25,'Construction Comps'!H25,'Construction Comps'!K25,'Construction Comps'!N25,'Construction Comps'!Q25,'Construction Comps'!T25) -> 3228.0797 | D13: =MAX(('Construction Comps'!E25,'Construction Comps'!H25,'Construction Comps'!K25,'Construction Comps'!N25,'Construction Comps'!Q25, 'Construction Comps'!T25)) -> 48079.907 | E13: =AVERAGE('Construction Comps'!E25,'Construction Comps'!H25,'Construction Comps'!K25,'Construction Comps'!N25,'Construction Comps'!Q25,'Construction Comps'!T25) -> 25558.123 | F13: =MIN('Construction Comps'!F25,'Construction Comps'!I25,'Construction Comps'!L25,'Construction Comps'!O25,'Construction Comps'!R25, 'Construction Comps'!U25) -> 0.055022596 | G13: =MAX('Construction Comps'!F25,'Construction Comps'!I25,'Construction Comps'!L25,'Construction Comps'!O25,'Construction Comps'!R25, 'Construction Comps'!U25) -> 0.34001748 | H13: =AVERAGE('Construction Comps'!F25,'Construction Comps'!I25,'Construction Comps'!L25,'Construction Comps'!O25,'Construction Comps'!R25,'Construction Comps'!U25) -> 0.20521623
B14: Total Dev. Cost per Site | C14: =MIN('Construction Comps'!E26,'Construction Comps'!H26,'Construction Comps'!K26,'Construction Comps'!N26,'Construction Comps'!Q26,'Construction Comps'!T26) -> 58668.255 | D14: =MAX(('Construction Comps'!E26,'Construction Comps'!H26,'Construction Comps'!K26,'Construction Comps'!N26,'Construction Comps'!Q26, 'Construction Comps'!T26)) -> 141404.22 | E14: =AVERAGE('Construction Comps'!E26,'Construction Comps'!H26,'Construction Comps'!K26,'Construction Comps'!N26,'Construction Comps'!Q26,'Construction Comps'!T26) -> 115875.03
B16: NOTE: Lodging Unit Costs - the majority of the comparable RV resorts with lodging unit cost data have very high lodging unit quantities, which tends to lower the cost per unit.
